Workbook

Sheet Dashboard
B2: Budget & Commitments Dashboard | N2: CVR Month: May, 2026
B6: Total EAC | D6: Cost to Date | F6: Remaining | H6: Actuals | J6: Accrued | L6: Committed | N6: Over Budget | P6: Under Budget
B8: 1.1975881e+08 | D8: 96573487 | F8: 23185327 | H8: 21642147 | J8: 26722.21 | L8: 74904618 | N8: 0 | P8: 0
B54: Cost Code Summary
B55: Cost Code | C55: Item | H55: EAC | J55: CTD | L55: Remaining | N55: Actuals | P55: O/U
B56: 0-4004-01 | C56: 0-4004-01 Racking Materials | H56: 38327781 | J56: 46723601 | L56: -8395820 | N56: 10391392 | P56: ▲ Over
B57: 0-4004-05 | C57: 0-4004-05 PV Power Cable Materi | H57: 21422369 | J57: 20543723 | L57: 878646.07 | N57: 4497552.6 | P57: ✓ Under
B58: 0-4004-02 | C58: 0-4004-02 Inverter Materials | H58: 16780788 | J58: 21943590 | L58: -5162801.8 | N58: 4983660 | P58: ▲ Over
B59: 0-4004-08 | C59: 0-4004-08 PV Harness & LBDs | H59: 11679119 | J59: 0 | L59: 11679119 | N59: 0 | P59: ✓ Under
B60: 0-4013 | C60: 0-4013-Contingency | H60: 4883701.6 | J60: 0 | L60: 4883701.6 | N60: 0 | P60: ✓ Under
B61: 0-4109 | C61: 0-4109-Site Roadways | H61: 3249926 | J61: 1993005 | L61: 1256921.1 | N61: 0 | P61: ✓ Under
B62: 0-4024 | C62: 0-4024-Engineering | H62: 2800000 | J62: 1380959.6 | L62: 1419040.4 | N62: 1157305.6 | P62: ✓ Under
B63: 0-4008 | C63: 0-4008-Supplies | H63: 2425247.7 | J63: 179686.48 | L63: 2245561.2 | N63: 108788 | P63: ✓ Under
B64: 0-4004-07 | C64: 0-4004-07 Scada | H64: 1987506.3 | J64: 0 | L64: 1987506.3 | N64: 0 | P64: ✓ Under
B65: 0-4505 | C65: 0-4505-AC-MV Boring | H65: 1958336.6 | J65: 0 | L65: 1958336.6 | N65: 0 | P65: ✓ Under
B66: 0-4004-10 | C66: 0-4004-10 PV Electrical Materia | H66: 1936306 | J66: 36466.4 | L66: 1899839.6 | N66: 34328.11 | P66: ✓ Under
B67: 0-4010 | C67: 0-4010-FOG | H67: 1835125.6 | J67: -20637.25 | L67: 1855762.9 | N67: 42925.37 | P67: ✓ Under
... B124: 0-4xxy | C124: Opps | H124: -2420810.6 | J124: 0 | L124: -2420810.6 | N124: 0 | P124: ▲ Over

Sheet Category Table
A1: CVR Month: | B1: May, 2026 | C1: =SUBTOTAL(9,C4:C370) | D1: =SUBTOTAL(9,D4:D370) | E1: =SUBTOTAL(9,E4:E370) | F1: =SUBTOTAL(9,F4:F370) | G1: =SUBTOTAL(9,G4:G370) | H1: =SUBTOTAL(9,H4:H370) | I1: =SUBTOTAL(9,I4:I370) | J1: =SUBTOTAL(9,J4:J370) | ... AO1: =SUBTOTAL(9,AO4:AO370) | AP1: =IF(AM1>0, "Under",IF(AM1<0,"Over","")) | AQ1: =IF(AN1>0, "Under",IF(AN1<0,"Over","")) | AR1: =IF(AO1>0, "Under",IF(AO1<0,"Over",""))
C2: SU | D2: OC | E2: MA | F2: SU | G2: OC | H2: MA | I2: SU | J2: OC | K2: MA | L2: SU | M2: OC | N2: MA | O2: SU | P2: OC | Q2: MA | R2: SU | S2: OC | T2: MA | U2: SU | V2: OC | W2: MA | X2: SU | Y2: OC | Z2: MA | AA2: SU | AB2: OC | AC2: MA | AD2: SU | AE2: OC | AF2: MA | AG2: SU | AH2: OC | AI2: MA | AM2: SU | AN2: OC | AO2: MA | AP2: SU | AQ2: OC | AR2: MA
A3: Cost Code | B3: Item | C3: Subcontracts CVR Actual Cost | D3: Supplies CVR Actual Cost | E3: Material CVR Actual Cost | F3: Subcontracts CVR FC | G3: Supplies CVR FC | H3: Material CVR FC | I3: Subcontracts CVR Accruals | J3: Supplies CVR Accruals | K3: Material CVR Accruals | L3: Subcontracts CVR Out PO's | M3: Supplies CVR Out PO's | N3: Material CVR Out PO's | O3: Subcontracts CVR EAC | P3: Supplies CVR EAC | Q3: Material CVR EAC | R3: Subcontracts PO Log Amount | S3: Supplies PO Log Amount | T3: Material PO Log Amount | U3: Subcontracts Accrued Costs | V3: Supplies Accrued Costs | W3: Material Accrued Costs | X3: Subcontracts Comms Actuals | Y3: Supplies Comms Actuals | Z3: Material Comms Actuals | AA3: Subcontracts Committed | AB3: Supplies Committed | AC3: Material Committed | AD3: Subcontracts Total Comms JTD Cost | AE3: Supplies Total Comms JTD Cost | AF3: Material Total Comms JTD Cost | AG3: Subcontracts CTD | AH3: Supplies CTD | AI3: Material CTD | AJ3: Subcontracts Manual Adjustment | AK3: Supplies Manual Adjustment | AL3: Material Manual Adjustment | AM3: Subcontracts Rem EAC | AN3: Supplies Rem EAC | AO3: Material Rem EAC | AP3: Subcontracts Over/Under | AQ3: Supplies Over/Under | AR3: Material Over/Under
A4: 0-4000 | B4: 0-4000-Mobilization | C4: 0 | D4: 38865 | E4: 0 | F4: 178048.73 | G4: 0 | H4: 0 | I4: 0 | J4: 0 | K4: 0 | L4: 0 | M4: 0 | N4: 0 | O4: =L4+I4+F4+C4 | P4: =M4+J4+G4+D4 | Q4: =N4+K4+H4+E4 | R4: =SUMIFS('PO Log'!$E:$E,'PO Log'!$D:$D,'Category Table'!R$2,'PO Log'!$C:$C,'Category Table'!$A4) | S4: =SUMIFS('PO Log'!$E:$E,'PO Log'!$D:$D,'Category Table'!S$2,'PO Log'!$C:$C,'Category Table'!$A4) | T4: =SUMIFS('PO Log'!$E:$E,'PO Log'!$D:$D,'Category Table'!T$2,'PO Log'!$C:$C,'Category Table'!$A4) | U4: =SUMIFS('Committments Dump'!$Q:$Q,'Committments Dump'!$C:$C,'Category Table'!U$2,'Committments Dump'!$B:$B,'Category Table'!$A4) | V4: =SUMIFS('Committments Dump'!$Q:$Q,'Committments Dump'!$C:$C,'Category Table'!V$2,'Committments Dump'!$B:$B,'Category Table'!$A4) | W4: =SUMIFS('Committments Dump'!$Q:$Q,'Committments Dump'!$C:$C,'Category Table'!W$2,'Committments Dump'!$B:$B,'Category Table'!$A4) | X4: =SUMIFS('Committments Dump'!$R:$R,'Committments Dump'!$C:$C,'Category Table'!X$2,'Committments Dump'!$B:$B,'Category Table'!$A4) | Y4: =SUMIFS('Committments Dump'!$R:$R,'Committments Dump'!$C:$C,'Category Table'!Y$2,'Committments Dump'!$B:$B,'Category Table'!$A4) | Z4: =SUMIFS('Committments Dump'!$R:$R,'Committments Dump'!$C:$C,'Category Table'!Z$2,'Committments Dump'!$B:$B,'Category Table'!$A4) | AA4: =SUMIFS('Committments Dump'!$S:$S,'Committments Dump'!$C:$C,'Category Table'!AA$2,'Committments Dump'!$B:$B,'Category Table'!$A4) | AB4: =SUMIFS('Committments Dump'!$S:$S,'Committments Dump'!$C:$C,'Category Table'!AB$2,'Committments Dump'!$B:$B,'Category Table'!$A4) | AC4: =SUMIFS('Committments Dump'!$S:$S,'Committments Dump'!$C:$C,'Category Table'!AC$2,'Committments Dump'!$B:$B,'Category Table'!$A4) | AD4: =U4+X4+AA4 | AE4: =V4+Y4+AB4 | AF4: =W4+Z4+AC4 | AG4: =R4+AD4 | AH4: =S4+AE4 | AI4: =T4+AF4 | AM4: =(O4-AG4)+AJ4 | AN4: =(P4-AH4)+AK4 | AO4: =(Q4-AI4)+AL4 | AP4: =IF(AM4>0, "Under",IF(AM4<0,"Over","")) | AQ4: =IF(AN4>0, "Under",IF(AN4<0,"Over","")) | AR4: =IF(AO4>0, "Under",IF(AO4<0,"Over",""))
A5: 0-4001 | B5: 0-4001-Demobilization | C5: 0 | D5: 2350 | E5: 0 | F5: 220300.84 | G5: 0 | H5: 0 | I5: 0 | J5: 0 | K5: 0 | L5: 0 | M5: 0 | N5: 0 | O5: =L5+I5+F5+C5 | P5: =M5+J5+G5+D5 | Q5: =N5+K5+H5+E5 | R5: =SUMIFS('PO Log'!$E:$E,'PO Log'!$D:$D,'Category Table'!R$2,'PO Log'!$C:$C,'Category Table'!$A5) | S5: =SUMIFS('PO Log'!$E:$E,'PO Log'!$D:$D,'Category Table'!S$2,'PO Log'!$C:$C,'Category Table'!$A5) | T5: =SUMIFS('PO Log'!$E:$E,'PO Log'!$D:$D,'Category Table'!T$2,'PO Log'!$C:$C,'Category Table'!$A5) | U5: =SUMIFS('Committments Dump'!$Q:$Q,'Committments Dump'!$C:$C,'Category Table'!U$2,'Committments Dump'!$B:$B,'Category Table'!$A5) | V5: =SUMIFS('Committments Dump'!$Q:$Q,'Committments Dump'!$C:$C,'Category Table'!V$2,'Committments Dump'!$B:$B,'Category Table'!$A5) | W5: =SUMIFS('Committments Dump'!$Q:$Q,'Committments Dump'!$C:$C,'Category Table'!W$2,'Committments Dump'!$B:$B,'Category Table'!$A5) | X5: =SUMIFS('Committments Dump'!$R:$R,'Committments Dump'!$C:$C,'Category Table'!X$2,'Committments Dump'!$B:$B,'Category Table'!$A5) | Y5: =SUMIFS('Committments Dump'!$R:$R,'Committments Dump'!$C:$C,'Category Table'!Y$2,'Committments Dump'!$B:$B,'Category Table'!$A5) | Z5: =SUMIFS('Committments Dump'!$R:$R,'Committments Dump'!$C:$C,'Category Table'!Z$2,'Committments Dump'!$B:$B,'Category Table'!$A5) | AA5: =SUMIFS('Committments Dump'!$S:$S,'Committments Dump'!$C:$C,'Category Table'!AA$2,'Committments Dump'!$B:$B,'Category Table'!$A5) | AB5: =SUMIFS('Committments Dump'!$S:$S,'Committments Dump'!$C:$C,'Category Table'!AB$2,'Committments Dump'!$B:$B,'Category Table'!$A5) | AC5: =SUMIFS('Committments Dump'!$S:$S,'Committments Dump'!$C:$C,'Category Table'!AC$2,'Committments Dump'!$B:$B,'Category Table'!$A5) | AD5: =U5+X5+AA5 | AE5: =V5+Y5+AB5 | AF5: =W5+Z5+AC5 | AG5: =R5+AD5 | AH5: =S5+AE5 | AI5: =T5+AF5 | AM5: =(O5-AG5)+AJ5 | AN5: =(P5-AH5)+AK5 | AO5: =(Q5-AI5)+AL5 | AP5: =IF(AM5>0, "Under",IF(AM5<0,"Over","")) | AQ5: =IF(AN5>0, "Under",IF(AN5<0,"Over","")) | AR5: =IF(AO5>0, "Under",IF(AO5<0,"Over",""))
A6: 0-4004-01 | B6: 0-4004-01 Racking Materials | C6: 0 | D6: 1035502.4 | E6: 9355889.1 | H6: -8395820 | I6: 0 | J6: 0 | K6: 0 | L6: 0 | M6: 11408138 | N6: 24924071 | O6: =L6+I6+F6+C6 | P6: =M6+J6+G6+D6 | Q6: =N6+K6+H6+E6 | R6: =SUMIFS('PO Log'!$E:$E,'PO Log'!$D:$D,'Category Table'!R$2,'PO Log'!$C:$C,'Category Table'!$A6) | S6: =SUMIFS('PO Log'!$E:$E,'PO Log'!$D:$D,'Category Table'!S$2,'PO Log'!$C:$C,'Category Table'!$A6) | T6: =SUMIFS('PO Log'!$E:$E,'PO Log'!$D:$D,'Category Table'!T$2,'PO Log'!$C:$C,'Category Table'!$A6) | U6: =SUMIFS('Committments Dump'!$Q:$Q,'Committments Dump'!$C:$C,'Category Table'!U$2,'Committments Dump'!$B:$B,'Category Table'!$A6) | V6: =SUMIFS('Committments Dump'!$Q:$Q,'Committments Dump'!$C:$C,'Category Table'!V$2,'Committments Dump'!$B:$B,'Category Table'!$A6) | W6: =SUMIFS('Committments Dump'!$Q:$Q,'Committments Dump'!$C:$C,'Category Table'!W$2,'Committments Dump'!$B:$B,'Category Table'!$A6) | X6: =SUMIFS('Committments Dump'!$R:$R,'Committments Dump'!$C:$C,'Category Table'!X$2,'Committments Dump'!$B:$B,'Category Table'!$A6) | Y6: =SUMIFS('Committments Dump'!$R:$R,'Committments Dump'!$C:$C,'Category Table'!Y$2,'Committments Dump'!$B:$B,'Category Table'!$A6) | Z6: =SUMIFS('Committments Dump'!$R:$R,'Committments Dump'!$C:$C,'Category Table'!Z$2,'Committments Dump'!$B:$B,'Category Table'!$A6) | AA6: =SUMIFS('Committments Dump'!$S:$S,'Committments Dump'!$C:$C,'Category Table'!AA$2,'Committments Dump'!$B:$B,'Category Table'!$A6) | AB6: =SUMIFS('Committments Dump'!$S:$S,'Committments Dump'!$C:$C,'Category Table'!AB$2,'Committments Dump'!$B:$B,'Category Table'!$A6) | AC6: =SUMIFS('Committments Dump'!$S:$S,'Committments Dump'!$C:$C,'Category Table'!AC$2,'Committments Dump'!$B:$B,'Category Table'!$A6) | AD6: =U6+X6+AA6 | AE6: =V6+Y6+AB6 | AF6: =W6+Z6+AC6 | AG6: =R6+AD6 | AH6: =S6+AE6 | AI6: =T6+AF6 | AM6: =(O6-AG6)+AJ6 | AN6: =(P6-AH6)+AK6 | AO6: =(Q6-AI6)+AL6 | AP6: =IF(AM6>0, "Under",IF(AM6<0,"Over","")) | AQ6: =IF(AN6>0, "Under",IF(AN6<0,"Over","")) | AR6: =IF(AO6>0, "Under",IF(AO6<0,"Over",""))
A7: 0-4004-02 | B7: 0-4004-02 Inverter Materials | C7: 0 | D7: 0 | E7: 4983660 | F7: -350000 | H7: -4812801.8 | I7: 0 | J7: 0 | K7: 0 | L7: 0 | M7: 0 | N7: 16959930 | O7: =L7+I7+F7+C7 | P7: =M7+J7+G7+D7 | Q7: =N7+K7+H7+E7 | R7: =SUMIFS('PO Log'!$E:$E,'PO Log'!$D:$D,'Category Table'!R$2,'PO Log'!$C:$C,'Category Table'!$A7) | S7: =SUMIFS('PO Log'!$E:$E,'PO Log'!$D:$D,'Category Table'!S$2,'PO Log'!$C:$C,'Category Table'!$A7) | T7: =SUMIFS('PO Log'!$E:$E,'PO Log'!$D:$D,'Category Table'!T$2,'PO Log'!$C:$C,'Category Table'!$A7) | U7: =SUMIFS('Committments Dump'!$Q:$Q,'Committments Dump'!$C:$C,'Category Table'!U$2,'Committments Dump'!$B:$B,'Category Table'!$A7) | V7: =SUMIFS('Committments Dump'!$Q:$Q,'Committments Dump'!$C:$C,'Category Table'!V$2,'Committments Dump'!$B:$B,'Category Table'!$A7) | W7: =SUMIFS('Committments Dump'!$Q:$Q,'Committments Dump'!$C:$C,'Category Table'!W$2,'Committments Dump'!$B:$B,'Category Table'!$A7) | X7: =SUMIFS('Committments Dump'!$R:$R,'Committments Dump'!$C:$C,'Category Table'!X$2,'Committments Dump'!$B:$B,'Category Table'!$A7) | Y7: =SUMIFS('Committments Dump'!$R:$R,'Committments Dump'!$C:$C,'Category Table'!Y$2,'Committments Dump'!$B:$B,'Category Table'!$A7) | Z7: =SUMIFS('Committments Dump'!$R:$R,'Committments Dump'!$C:$C,'Category Table'!Z$2,'Committments Dump'!$B:$B,'Category Table'!$A7) | AA7: =SUMIFS('Committments Dump'!$S:$S,'Committments Dump'!$C:$C,'Category Table'!AA$2,'Committments Dump'!$B:$B,'Category Table'!$A7) | AB7: =SUMIFS('Committments Dump'!$S:$S,'Committments Dump'!$C:$C,'Category Table'!AB$2,'Committments Dump'!$B:$B,'Category Table'!$A7) | AC7: =SUMIFS('Committments Dump'!$S:$S,'Committments Dump'!$C:$C,'Category Table'!AC$2,'Committments Dump'!$B:$B,'Category Table'!$A7) | AD7: =U7+X7+AA7 | AE7: =V7+Y7+AB7 | AF7: =W7+Z7+AC7 | AG7: =R7+AD7 | AH7: =S7+AE7 | AI7: =T7+AF7 | AM7: =(O7-AG7)+AJ7 | AN7: =(P7-AH7)+AK7 | AO7: =(Q7-AI7)+AL7 | AP7: =IF(AM7>0, "Under",IF(AM7<0,"Over","")) | AQ7: =IF(AN7>0, "Under",IF(AN7<0,"Over","")) | AR7: =IF(AO7>0, "Under",IF(AO7<0,"Over",""))
A8: 0-4004-04 | B8: 0-4004-04 HV Breakers | C8: 0 | D8: 0 | E8: 0 | F8: 0 | G8: 0 | H8: 0 | I8: 0 | J8: 0 | K8: 0 | L8: 0 | M8: 0 | N8: 0 | O8: =L8+I8+F8+C8 | P8: =M8+J8+G8+D8 | Q8: =N8+K8+H8+E8 | R8: =SUMIFS('PO Log'!$E:$E,'PO Log'!$D:$D,'Category Table'!R$2,'PO Log'!$C:$C,'Category Table'!$A8) | S8: =SUMIFS('PO Log'!$E:$E,'PO Log'!$D:$D,'Category Table'!S$2,'PO Log'!$C:$C,'Category Table'!$A8) | T8: =SUMIFS('PO Log'!$E:$E,'PO Log'!$D:$D,'Category Table'!T$2,'PO Log'!$C:$C,'Category Table'!$A8) | U8: =SUMIFS('Committments Dump'!$Q:$Q,'Committments Dump'!$C:$C,'Category Table'!U$2,'Committments Dump'!$B:$B,'Category Table'!$A8) | V8: =SUMIFS('Committments Dump'!$Q:$Q,'Committments Dump'!$C:$C,'Category Table'!V$2,'Committments Dump'!$B:$B,'Category Table'!$A8) | W8: =SUMIFS('Committments Dump'!$Q:$Q,'Committments Dump'!$C:$C,'Category Table'!W$2,'Committments Dump'!$B:$B,'Category Table'!$A8) | X8: =SUMIFS('Committments Dump'!$R:$R,'Committments Dump'!$C:$C,'Category Table'!X$2,'Committments Dump'!$B:$B,'Category Table'!$A8) | Y8: =SUMIFS('Committments Dump'!$R:$R,'Committments Dump'!$C:$C,'Category Table'!Y$2,'Committments Dump'!$B:$B,'Category Table'!$A8) | Z8: =SUMIFS('Committments Dump'!$R:$R,'Committments Dump'!$C:$C,'Category Table'!Z$2,'Committments Dump'!$B:$B,'Category Table'!$A8) | AA8: =SUMIFS('Committments Dump'!$S:$S,'Committments Dump'!$C:$C,'Category Table'!AA$2,'Committments Dump'!$B:$B,'Category Table'!$A8) | AB8: =SUMIFS('Committments Dump'!$S:$S,'Committments Dump'!$C:$C,'Category Table'!AB$2,'Committments Dump'!$B:$B,'Category Table'!$A8) | AC8: =SUMIFS('Committments Dump'!$S:$S,'Committments Dump'!$C:$C,'Category Table'!AC$2,'Committments Dump'!$B:$B,'Category Table'!$A8) | AD8: =U8+X8+AA8 | AE8: =V8+Y8+AB8 | AF8: =W8+Z8+AC8 | AG8: =R8+AD8 | AH8: =S8+AE8 | AI8: =T8+AF8 | AM8: =(O8-AG8)+AJ8 | AN8: =(P8-AH8)+AK8 | AO8: =(Q8-AI8)+AL8 | AP8: =IF(AM8>0, "Under",IF(AM8<0,"Over","")) | AQ8: =IF(AN8>0, "Under",IF(AN8<0,"Over","")) | AR8: =IF(AO8>0, "Under",IF(AO8<0,"Over",""))
A9: 0-4004-05 | B9: 0-4004-05 PV Power Cable Materi | C9: 0 | D9: 0 | E9: 4497552.6 | F9: 1264434 | G9: -385787.98 | I9: 0 | J9: 0 | K9: 21748.27 | L9: 0 | M9: 1033828.5 | N9: 14990594 | O9: =L9+I9+F9+C9 | P9: =M9+J9+G9+D9 | Q9: =N9+K9+H9+E9 | R9: =SUMIFS('PO Log'!$E:$E,'PO Log'!$D:$D,'Category Table'!R$2,'PO Log'!$C:$C,'Category Table'!$A9) | S9: =SUMIFS('PO Log'!$E:$E,'PO Log'!$D:$D,'Category Table'!S$2,'PO Log'!$C:$C,'Category Table'!$A9) | T9: =SUMIFS('PO Log'!$E:$E,'PO Log'!$D:$D,'Category Table'!T$2,'PO Log'!$C:$C,'Category Table'!$A9) | U9: =SUMIFS('Committments Dump'!$Q:$Q,'Committments Dump'!$C:$C,'Category Table'!U$2,'Committments Dump'!$B:$B,'Category Table'!$A9) | V9: =SUMIFS('Committments Dump'!$Q:$Q,'Committments Dump'!$C:$C,'Category Table'!V$2,'Committments Dump'!$B:$B,'Category Table'!$A9) | W9: =SUMIFS('Committments Dump'!$Q:$Q,'Committments Dump'!$C:$C,'Category Table'!W$2,'Committments Dump'!$B:$B,'Category Table'!$A9) | X9: =SUMIFS('Committments Dump'!$R:$R,'Committments Dump'!$C:$C,'Category Table'!X$2,'Committments Dump'!$B:$B,'Category Table'!$A9) | Y9: =SUMIFS('Committments Dump'!$R:$R,'Committments Dump'!$C:$C,'Category Table'!Y$2,'Committments Dump'!$B:$B,'Category Table'!$A9) | Z9: =SUMIFS('Committments Dump'!$R:$R,'Committments Dump'!$C:$C,'Category Table'!Z$2,'Committments Dump'!$B:$B,'Category Table'!$A9) | AA9: =SUMIFS('Committments Dump'!$S:$S,'Committments Dump'!$C:$C,'Category Table'!AA$2,'Committments Dump'!$B:$B,'Category Table'!$A9) | AB9: =SUMIFS('Committments Dump'!$S:$S,'Committments Dump'!$C:$C,'Category Table'!AB$2,'Committments Dump'!$B:$B,'Category Table'!$A9) | AC9: =SUMIFS('Committments Dump'!$S:$S,'Committments Dump'!$C:$C,'Category Table'!AC$2,'Committments Dump'!$B:$B,'Category Table'!$A9) | AD9: =U9+X9+AA9 | AE9: =V9+Y9+AB9 | AF9: =W9+Z9+AC9 | AG9: =R9+AD9 | AH9: =S9+AE9 | AI9: =T9+AF9 | AM9: =(O9-AG9)+AJ9 | AN9: =(P9-AH9)+AK9 | AO9: =(Q9-AI9)+AL9 | AP9: =IF(AM9>0, "Under",IF(AM9<0,"Over","")) | AQ9: =IF(AN9>0, "Under",IF(AN9<0,"Over","")) | AR9: =IF(AO9>0, "Under",IF(AO9<0,"Over",""))
A10: 0-4004-06 | B10: 0-4004-06 Cable Management | C10: 0 | D10: 0 | E10: 0 | F10: 0 | G10: 0 | H10: 1624884 | I10: 0 | J10: 0 | K10: 0 | L10: 0 | M10: 0 | N10: 0 | O10: =L10+I10+F10+C10 | P10: =M10+J10+G10+D10 | Q10: =N10+K10+H10+E10 | R10: =SUMIFS('PO Log'!$E:$E,'PO Log'!$D:$D,'Category Table'!R$2,'PO Log'!$C:$C,'Category Table'!$A10) | S10: =SUMIFS('PO Log'!$E:$E,'PO Log'!$D:$D,'Category Table'!S$2,'PO Log'!$C:$C,'Category Table'!$A10) | T10: =SUMIFS('PO Log'!$E:$E,'PO Log'!$D:$D,'Category Table'!T$2,'PO Log'!$C:$C,'Category Table'!$A10) | U10: =SUMIFS('Committments Dump'!$Q:$Q,'Committments Dump'!$C:$C,'Category Table'!U$2,'Committments Dump'!$B:$B,'Category Table'!$A10) | V10: =SUMIFS('Committments Dump'!$Q:$Q,'Committments Dump'!$C:$C,'Category Table'!V$2,'Committments Dump'!$B:$B,'Category Table'!$A10) | W10: =SUMIFS('Committments Dump'!$Q:$Q,'Committments Dump'!$C:$C,'Category Table'!W$2,'Committments Dump'!$B:$B,'Category Table'!$A10) | X10: =SUMIFS('Committments Dump'!$R:$R,'Committments Dump'!$C:$C,'Category Table'!X$2,'Committments Dump'!$B:$B,'Category Table'!$A10) | Y10: =SUMIFS('Committments Dump'!$R:$R,'Committments Dump'!$C:$C,'Category Table'!Y$2,'Committments Dump'!$B:$B,'Category Table'!$A10) | Z10: =SUMIFS('Committments Dump'!$R:$R,'Committments Dump'!$C:$C,'Category Table'!Z$2,'Committments Dump'!$B:$B,'Category Table'!$A10) | AA10: =SUMIFS('Committments Dump'!$S:$S,'Committments Dump'!$C:$C,'Category Table'!AA$2,'Committments Dump'!$B:$B,'Category Table'!$A10) | AB10: =SUMIFS('Committments Dump'!$S:$S,'Committments Dump'!$C:$C,'Category Table'!AB$2,'Committments Dump'!$B:$B,'Category Table'!$A10) | AC10: =SUMIFS('Committments Dump'!$S:$S,'Committments Dump'!$C:$C,'Category Table'!AC$2,'Committments Dump'!$B:$B,'Category Table'!$A10) | AD10: =U10+X10+AA10 | AE10: =V10+Y10+AB10 | AF10: =W10+Z10+AC10 | AG10: =R10+AD10 | AH10: =S10+AE10 | AI10: =T10+AF10 | AM10: =(O10-AG10)+AJ10 | AN10: =(P10-AH10)+AK10 | AO10: =(Q10-AI10)+AL10 | AP10: =IF(AM10>0, "Under",IF(AM10<0,"Over","")) | AQ10: =IF(AN10>0, "Under",IF(AN10<0,"Over","")) | AR10: =IF(AO10>0, "Under",IF(AO10<0,"Over",""))
A11: 0-4004-07 | B11: 0-4004-07 Scada | C11: 0 | D11: 0 | E11: 0 | F11: 138740 | G11: 0 | H11: 1848766.3 | I11: 0 | J11: 0 | K11: 0 | L11: 0 | M11: 0 | N11: 0 | O11: =L11+I11+F11+C11 | P11: =M11+J11+G11+D11 | Q11: =N11+K11+H11+E11 | R11: =SUMIFS('PO Log'!$E:$E,'PO Log'!$D:$D,'Category Table'!R$2,'PO Log'!$C:$C,'Category Table'!$A11) | S11: =SUMIFS('PO Log'!$E:$E,'PO Log'!$D:$D,'Category Table'!S$2,'PO Log'!$C:$C,'Category Table'!$A11) | T11: =SUMIFS('PO Log'!$E:$E,'PO Log'!$D:$D,'Category Table'!T$2,'PO Log'!$C:$C,'Category Table'!$A11) | U11: =SUMIFS('Committments Dump'!$Q:$Q,'Committments Dump'!$C:$C,'Category Table'!U$2,'Committments Dump'!$B:$B,'Category Table'!$A11) | V11: =SUMIFS('Committments Dump'!$Q:$Q,'Committments Dump'!$C:$C,'Category Table'!V$2,'Committments Dump'!$B:$B,'Category Table'!$A11) | W11: =SUMIFS('Committments Dump'!$Q:$Q,'Committments Dump'!$C:$C,'Category Table'!W$2,'Committments Dump'!$B:$B,'Category Table'!$A11) | X11: =SUMIFS('Committments Dump'!$R:$R,'Committments Dump'!$C:$C,'Category Table'!X$2,'Committments Dump'!$B:$B,'Category Table'!$A11) | Y11: =SUMIFS('Committments Dump'!$R:$R,'Committments Dump'!$C:$C,'Category Table'!Y$2,'Committments Dump'!$B:$B,'Category Table'!$A11) | Z11: =SUMIFS('Committments Dump'!$R:$R,'Committments Dump'!$C:$C,'Category Table'!Z$2,'Committments Dump'!$B:$B,'Category Table'!$A11) | AA11: =SUMIFS('Committments Dump'!$S:$S,'Committments Dump'!$C:$C,'Category Table'!AA$2,'Committments Dump'!$B:$B,'Category Table'!$A11) | AB11: =SUMIFS('Committments Dump'!$S:$S,'Committments Dump'!$C:$C,'Category Table'!AB$2,'Committments Dump'!$B:$B,'Category Table'!$A11) | AC11: =SUMIFS('Committments Dump'!$S:$S,'Committments Dump'!$C:$C,'Category Table'!AC$2,'Committments Dump'!$B:$B,'Category Table'!$A11) | AD11: =U11+X11+AA11 | AE11: =V11+Y11+AB11 | AF11: =W11+Z11+AC11 | AG11: =R11+AD11 | AH11: =S11+AE11 | AI11: =T11+AF11 | AM11: =(O11-AG11)+AJ11 | AN11: =(P11-AH11)+AK11 | AO11: =(Q11-AI11)+AL11 | AP11: =IF(AM11>0, "Under",IF(AM11<0,"Over","")) | AQ11: =IF(AN11>0, "Under",IF(AN11<0,"Over","")) | AR11: =IF(AO11>0, "Under",IF(AO11<0,"Over",""))
A12: 0-4004-08 | B12: 0-4004-08 PV Harness & LBDs | C12: 0 | D12: 0 | E12: 0 | F12: 0 | G12: 0 | H12: 11679119 | I12: 0 | J12: 0 | K12: 0 | L12: 0 | M12: 0 | N12: 0 | O12: =L12+I12+F12+C12 | P12: =M12+J12+G12+D12 | Q12: =N12+K12+H12+E12 | R12: =SUMIFS('PO Log'!$E:$E,'PO Log'!$D:$D,'Category Table'!R$2,'PO Log'!$C:$C,'Category Table'!$A12) | S12: =SUMIFS('PO Log'!$E:$E,'PO Log'!$D:$D,'Category Table'!S$2,'PO Log'!$C:$C,'Category Table'!$A12) | T12: =SUMIFS('PO Log'!$E:$E,'PO Log'!$D:$D,'Category Table'!T$2,'PO Log'!$C:$C,'Category Table'!$A12) | U12: =SUMIFS('Committments Dump'!$Q:$Q,'Committments Dump'!$C:$C,'Category Table'!U$2,'Committments Dump'!$B:$B,'Category Table'!$A12) | V12: =SUMIFS('Committments Dump'!$Q:$Q,'Committments Dump'!$C:$C,'Category Table'!V$2,'Committments Dump'!$B:$B,'Category Table'!$A12) | W12: =SUMIFS('Committments Dump'!$Q:$Q,'Committments Dump'!$C:$C,'Category Table'!W$2,'Committments Dump'!$B:$B,'Category Table'!$A12) | X12: =SUMIFS('Committments Dump'!$R:$R,'Committments Dump'!$C:$C,'Category Table'!X$2,'Committments Dump'!$B:$B,'Category Table'!$A12) | Y12: =SUMIFS('Committments Dump'!$R:$R,'Committments Dump'!$C:$C,'Category Table'!Y$2,'Committments Dump'!$B:$B,'Category Table'!$A12) | Z12: =SUMIFS('Committments Dump'!$R:$R,'Committments Dump'!$C:$C,'Category Table'!Z$2,'Committments Dump'!$B:$B,'Category Table'!$A12) | AA12: =SUMIFS('Committments Dump'!$S:$S,'Committments Dump'!$C:$C,'Category Table'!AA$2,'Committments Dump'!$B:$B,'Category Table'!$A12) | AB12: =SUMIFS('Committments Dump'!$S:$S,'Committments Dump'!$C:$C,'Category Table'!AB$2,'Committments Dump'!$B:$B,'Category Table'!$A12) | AC12: =SUMIFS('Committments Dump'!$S:$S,'Committments Dump'!$C:$C,'Category Table'!AC$2,'Committments Dump'!$B:$B,'Category Table'!$A12) | AD12: =U12+X12+AA12 | AE12: =V12+Y12+AB12 | AF12: =W12+Z12+AC12 | AG12: =R12+AD12 | AH12: =S12+AE12 | AI12: =T12+AF12 | AM12: =(O12-AG12)+AJ12 | AN12: =(P12-AH12)+AK12 | AO12: =(Q12-AI12)+AL12 | AP12: =IF(AM12>0, "Under",IF(AM12<0,"Over","")) | AQ12: =IF(AN12>0, "Under",IF(AN12<0,"Over","")) | AR12: =IF(AO12>0, "Under",IF(AO12<0,"Over",""))
A13: 0-4004-10 | B13: 0-4004-10 PV Electrical Materia | C13: 0 | D13: 123.43 | E13: 34204.68 | F13: 0 | G13: -132692.59 | H13: 2032532.2 | I13: 0 | J13: 10.4 | K13: 2127.89 | L13: 0 | M13: 0 | N13: 4.0927262e-12 | O13: =L13+I13+F13+C13 | P13: =M13+J13+G13+D13 | Q13: =N13+K13+H13+E13 | R13: =SUMIFS('PO Log'!$E:$E,'PO Log'!$D:$D,'Category Table'!R$2,'PO Log'!$C:$C,'Category Table'!$A13) | S13: =SUMIFS('PO Log'!$E:$E,'PO Log'!$D:$D,'Category Table'!S$2,'PO Log'!$C:$C,'Category Table'!$A13) | T13: =SUMIFS('PO Log'!$E:$E,'PO Log'!$D:$D,'Category Table'!T$2,'PO Log'!$C:$C,'Category Table'!$A13) | U13: =SUMIFS('Committments Dump'!$Q:$Q,'Committments Dump'!$C:$C,'Category Table'!U$2,'Committments Dump'!$B:$B,'Category Table'!$A13) | V13: =SUMIFS('Committments Dump'!$Q:$Q,'Committments Dump'!$C:$C,'Category Table'!V$2,'Committments Dump'!$B:$B,'Category Table'!$A13) | W13: =SUMIFS('Committments Dump'!$Q:$Q,'Committments Dump'!$C:$C,'Category Table'!W$2,'Committments Dump'!$B:$B,'Category Table'!$A13) | X13: =SUMIFS('Committments Dump'!$R:$R,'Committments Dump'!$C:$C,'Category Table'!X$2,'Committments Dump'!$B:$B,'Category Table'!$A13) | Y13: =SUMIFS('Committments Dump'!$R:$R,'Committments Dump'!$C:$C,'Category Table'!Y$2,'Committments Dump'!$B:$B,'Category Table'!$A13) | Z13: =SUMIFS('Committments Dump'!$R:$R,'Committments Dump'!$C:$C,'Category Table'!Z$2,'Committments Dump'!$B:$B,'Category Table'!$A13) | AA13: =SUMIFS('Committments Dump'!$S:$S,'Committments Dump'!$C:$C,'Category Table'!AA$2,'Committments Dump'!$B:$B,'Category Table'!$A13) | AB13: =SUMIFS('Committments Dump'!$S:$S,'Committments Dump'!$C:$C,'Category Table'!AB$2,'Committments Dump'!$B:$B,'Category Table'!$A13) | AC13: =SUMIFS('Committments Dump'!$S:$S,'Committments Dump'!$C:$C,'Category Table'!AC$2,'Committments Dump'!$B:$B,'Category Table'!$A13) | AD13: =U13+X13+AA13 | AE13: =V13+Y13+AB13 | AF13: =W13+Z13+AC13 | AG13: =R13+AD13 | AH13: =S13+AE13 | AI13: =T13+AF13 | AM13: =(O13-AG13)+AJ13 | AN13: =(P13-AH13)+AK13 | AO13: =(Q13-AI13)+AL13 | AP13: =IF(AM13>0, "Under",IF(AM13<0,"Over","")) | AQ13: =IF(AN13>0, "Under",IF(AN13<0,"Over","")) | AR13: =IF(AO13>0, "Under",IF(AO13<0,"Over",""))
A14: 0-4004-12 | B14: 0-4004-12 Non Tracker Piles | C14: 0 | D14: 0 | E14: 0 | F14: 0 | G14: 0 | I14: 0 | J14: 0 | K14: 0 | L14: 0 | M14: 212948.61 | N14: 754485.45 | O14: =L14+I14+F14+C14 | P14: =M14+J14+G14+D14 | Q14: =N14+K14+H14+E14 | R14: =SUMIFS('PO Log'!$E:$E,'PO Log'!$D:$D,'Category Table'!R$2,'PO Log'!$C:$C,'Category Table'!$A14) | S14: =SUMIFS('PO Log'!$E:$E,'PO Log'!$D:$D,'Category Table'!S$2,'PO Log'!$C:$C,'Category Table'!$A14) | T14: =SUMIFS('PO Log'!$E:$E,'PO Log'!$D:$D,'Category Table'!T$2,'PO Log'!$C:$C,'Category Table'!$A14) | U14: =SUMIFS('Committments Dump'!$Q:$Q,'Committments Dump'!$C:$C,'Category Table'!U$2,'Committments Dump'!$B:$B,'Category Table'!$A14) | V14: =SUMIFS('Committments Dump'!$Q:$Q,'Committments Dump'!$C:$C,'Category Table'!V$2,'Committments Dump'!$B:$B,'Category Table'!$A14) | W14: =SUMIFS('Committments Dump'!$Q:$Q,'Committments Dump'!$C:$C,'Category Table'!W$2,'Committments Dump'!$B:$B,'Category Table'!$A14) | X14: =SUMIFS('Committments Dump'!$R:$R,'Committments Dump'!$C:$C,'Category Table'!X$2,'Committments Dump'!$B:$B,'Category Table'!$A14) | Y14: =SUMIFS('Committments Dump'!$R:$R,'Committments Dump'!$C:$C,'Category Table'!Y$2,'Committments Dump'!$B:$B,'Category Table'!$A14) | Z14: =SUMIFS('Committments Dump'!$R:$R,'Committments Dump'!$C:$C,'Category Table'!Z$2,'Committments Dump'!$B:$B,'Category Table'!$A14) | AA14: =SUMIFS('Committments Dump'!$S:$S,'Committments Dump'!$C:$C,'Category Table'!AA$2,'Committments Dump'!$B:$B,'Category Table'!$A14) | AB14: =SUMIFS('Committments Dump'!$S:$S,'Committments Dump'!$C:$C,'Category Table'!AB$2,'Committments Dump'!$B:$B,'Category Table'!$A14) | AC14: =SUMIFS('Committments Dump'!$S:$S,'Committments Dump'!$C:$C,'Category Table'!AC$2,'Committments Dump'!$B:$B,'Category Table'!$A14) | AD14: =U14+X14+AA14 | AE14: =V14+Y14+AB14 | AF14: =W14+Z14+AC14 | AG14: =R14+AD14 | AH14: =S14+AE14 | AI14: =T14+AF14 | AM14: =(O14-AG14)+AJ14 | AN14: =(P14-AH14)+AK14 | AO14: =(Q14-AI14)+AL14 | AP14: =IF(AM14>0, "Under",IF(AM14<0,"Over","")) | AQ14: =IF(AN14>0, "Under",IF(AN14<0,"Over","")) | AR14: =IF(AO14>0, "Under",IF(AO14<0,"Over",""))
A15: 0-4004-13 | B15: 0-4004-13 CenterPoint's Breaker | C15: 0 | D15: 0 | E15: 0 | F15: 0 | G15: 0 | H15: -33000 | I15: 0 | J15: 0 | K15: 0 | L15: 0 | M15: 0 | N15: 333000 | O15: =L15+I15+F15+C15 | P15: =M15+J15+G15+D15 | Q15: =N15+K15+H15+E15 | R15: =SUMIFS('PO Log'!$E:$E,'PO Log'!$D:$D,'Category Table'!R$2,'PO Log'!$C:$C,'Category Table'!$A15) | S15: =SUMIFS('PO Log'!$E:$E,'PO Log'!$D:$D,'Category Table'!S$2,'PO Log'!$C:$C,'Category Table'!$A15) | T15: =SUMIFS('PO Log'!$E:$E,'PO Log'!$D:$D,'Category Table'!T$2,'PO Log'!$C:$C,'Category Table'!$A15) | U15: =SUMIFS('Committments Dump'!$Q:$Q,'Committments Dump'!$C:$C,'Category Table'!U$2,'Committments Dump'!$B:$B,'Category Table'!$A15) | V15: =SUMIFS('Committments Dump'!$Q:$Q,'Committments Dump'!$C:$C,'Category Table'!V$2,'Committments Dump'!$B:$B,'Category Table'!$A15) | W15: =SUMIFS('Committments Dump'!$Q:$Q,'Committments Dump'!$C:$C,'Category Table'!W$2,'Committments Dump'!$B:$B,'Category Table'!$A15) | X15: =SUMIFS('Committments Dump'!$R:$R,'Committments Dump'!$C:$C,'Category Table'!X$2,'Committments Dump'!$B:$B,'Category Table'!$A15) | Y15: =SUMIFS('Committments Dump'!$R:$R,'Committments Dump'!$C:$C,'Category Table'!Y$2,'Committments Dump'!$B:$B,'Category Table'!$A15) | Z15: =SUMIFS('Committments Dump'!$R:$R,'Committments Dump'!$C:$C,'Category Table'!Z$2,'Committments Dump'!$B:$B,'Category Table'!$A15) | AA15: =SUMIFS('Committments Dump'!$S:$S,'Committments Dump'!$C:$C,'Category Table'!AA$2,'Committments Dump'!$B:$B,'Category Table'!$A15) | AB15: =SUMIFS('Committments Dump'!$S:$S,'Committments Dump'!$C:$C,'Category Table'!AB$2,'Committments Dump'!$B:$B,'Category Table'!$A15) | AC15: =SUMIFS('Committments Dump'!$S:$S,'Committments Dump'!$C:$C,'Category Table'!AC$2,'Committments Dump'!$B:$B,'Category Table'!$A15) | AD15: =U15+X15+AA15 | AE15: =V15+Y15+AB15 | AF15: =W15+Z15+AC15 | AG15: =R15+AD15 | AH15: =S15+AE15 | AI15: =T15+AF15 | AM15: =(O15-AG15)+AJ15 | AN15: =(P15-AH15)+AK15 | AO15: =(Q15-AI15)+AL15 | AP15: =IF(AM15>0, "Under",IF(AM15<0,"Over","")) | AQ15: =IF(AN15>0, "Under",IF(AN15<0,"Over","")) | AR15: =IF(AO15>0, "Under",IF(AO15<0,"Over",""))
A16: 0-4005 | B16: 0-4005-FOE | C16: 0 | D16: 20433.51 | E16: 0 | F16: 0 | G16: 3435.3685 | H16: 0 | I16: 0 | J16: 0 | K16: 0 | L16: 0 | M16: 0 | N16: 0 | O16: =L16+I16+F16+C16 | P16: =M16+J16+G16+D16 | Q16: =N16+K16+H16+E16 | R16: =SUMIFS('PO Log'!$E:$E,'PO Log'!$D:$D,'Category Table'!R$2,'PO Log'!$C:$C,'Category Table'!$A16) | S16: =SUMIFS('PO Log'!$E:$E,'PO Log'!$D:$D,'Category Table'!S$2,'PO Log'!$C:$C,'Category Table'!$A16) | T16: =SUMIFS('PO Log'!$E:$E,'PO Log'!$D:$D,'Category Table'!T$2,'PO Log'!$C:$C,'Category Table'!$A16) | U16: =SUMIFS('Committments Dump'!$Q:$Q,'Committments Dump'!$C:$C,'Category Table'!U$2,'Committments Dump'!$B:$B,'Category Table'!$A16) | V16: =SUMIFS('Committments Dump'!$Q:$Q,'Committments Dump'!$C:$C,'Category Table'!V$2,'Committments Dump'!$B:$B,'Category Table'!$A16) | W16: =SUMIFS('Committments Dump'!$Q:$Q,'Committments Dump'!$C:$C,'Category Table'!W$2,'Committments Dump'!$B:$B,'Category Table'!$A16) | X16: =SUMIFS('Committments Dump'!$R:$R,'Committments Dump'!$C:$C,'Category Table'!X$2,'Committments Dump'!$B:$B,'Category Table'!$A16) | Y16: =SUMIFS('Committments Dump'!$R:$R,'Committments Dump'!$C:$C,'Category Table'!Y$2,'Committments Dump'!$B:$B,'Category Table'!$A16) | Z16: =SUMIFS('Committments Dump'!$R:$R,'Committments Dump'!$C:$C,'Category Table'!Z$2,'Committments Dump'!$B:$B,'Category Table'!$A16) | AA16: =SUMIFS('Committments Dump'!$S:$S,'Committments Dump'!$C:$C,'Category Table'!AA$2,'Committments Dump'!$B:$B,'Category Table'!$A16) | AB16: =SUMIFS('Committments Dump'!$S:$S,'Committments Dump'!$C:$C,'Category Table'!AB$2,'Committments Dump'!$B:$B,'Category Table'!$A16) | AC16: =SUMIFS('Committments Dump'!$S:$S,'Committments Dump'!$C:$C,'Category Table'!AC$2,'Committments Dump'!$B:$B,'Category Table'!$A16) | AD16: =U16+X16+AA16 | AE16: =V16+Y16+AB16 | AF16: =W16+Z16+AC16 | AG16: =R16+AD16 | AH16: =S16+AE16 | AI16: =T16+AF16 | AM16: =(O16-AG16)+AJ16 | AN16: =(P16-AH16)+AK16 | AO16: =(Q16-AI16)+AL16 | AP16: =IF(AM16>0, "Under",IF(AM16<0,"Over","")) | AQ16: =IF(AN16>0, "Under",IF(AN16<0,"Over","")) | AR16: =IF(AO16>0, "Under",IF(AO16<0,"Over",""))
A17: 0-4005-02 | B17: 0-4005-02 Commish FOE | C17: 0 | D17: 0 | E17: 0 | F17: 0 | G17: 0 | H17: 0 | I17: 0 | J17: 0 | K17: 0 | L17: 0 | M17: 0 | N17: 0 | O17: =L17+I17+F17+C17 | P17: =M17+J17+G17+D17 | Q17: =N17+K17+H17+E17 | R17: =SUMIFS('PO Log'!$E:$E,'PO Log'!$D:$D,'Category Table'!R$2,'PO Log'!$C:$C,'Category Table'!$A17) | S17: =SUMIFS('PO Log'!$E:$E,'PO Log'!$D:$D,'Category Table'!S$2,'PO Log'!$C:$C,'Category Table'!$A17) | T17: =SUMIFS('PO Log'!$E:$E,'PO Log'!$D:$D,'Category Table'!T$2,'PO Log'!$C:$C,'Category Table'!$A17) | U17: =SUMIFS('Committments Dump'!$Q:$Q,'Committments Dump'!$C:$C,'Category Table'!U$2,'Committments Dump'!$B:$B,'Category Table'!$A17) | V17: =SUMIFS('Committments Dump'!$Q:$Q,'Committments Dump'!$C:$C,'Category Table'!V$2,'Committments Dump'!$B:$B,'Category Table'!$A17) | W17: =SUMIFS('Committments Dump'!$Q:$Q,'Committments Dump'!$C:$C,'Category Table'!W$2,'Committments Dump'!$B:$B,'Category Table'!$A17) | X17: =SUMIFS('Committments Dump'!$R:$R,'Committments Dump'!$C:$C,'Category Table'!X$2,'Committments Dump'!$B:$B,'Category Table'!$A17) | Y17: =SUMIFS('Committments Dump'!$R:$R,'Committments Dump'!$C:$C,'Category Table'!Y$2,'Committments Dump'!$B:$B,'Category Table'!$A17) | Z17: =SUMIFS('Committments Dump'!$R:$R,'Committments Dump'!$C:$C,'Category Table'!Z$2,'Committments Dump'!$B:$B,'Category Table'!$A17) | AA17: =SUMIFS('Committments Dump'!$S:$S,'Committments Dump'!$C:$C,'Category Table'!AA$2,'Committments Dump'!$B:$B,'Category Table'!$A17) | AB17: =SUMIFS('Committments Dump'!$S:$S,'Committments Dump'!$C:$C,'Category Table'!AB$2,'Committments Dump'!$B:$B,'Category Table'!$A17) | AC17: =SUMIFS('Committments Dump'!$S:$S,'Committments Dump'!$C:$C,'Category Table'!AC$2,'Committments Dump'!$B:$B,'Category Table'!$A17) | AD17: =U17+X17+AA17 | AE17: =V17+Y17+AB17 | AF17: =W17+Z17+AC17 | AG17: =R17+AD17 | AH17: =S17+AE17 | AI17: =T17+AF17 | AM17: =(O17-AG17)+AJ17 | AN17: =(P17-AH17)+AK17 | AO17: =(Q17-AI17)+AL17 | AP17: =IF(AM17>0, "Under",IF(AM17<0,"Over","")) | AQ17: =IF(AN17>0, "Under",IF(AN17<0,"Over","")) | AR17: =IF(AO17>0, "Under",IF(AO17<0,"Over",""))
A18: 0-4006 | B18: 0-4006-Yard and Trailer | C18: 0 | D18: 35420.42 | E18: 0 | F18: 76535.447 | H18: 0 | I18: 0 | J18: 0 | K18: 0 | L18: 0 | M18: 277325.56 | N18: 0 | O18: =L18+I18+F18+C18 | P18: =M18+J18+G18+D18 | Q18: =N18+K18+H18+E18 | R18: =SUMIFS('PO Log'!$E:$E,'PO Log'!$D:$D,'Category Table'!R$2,'PO Log'!$C:$C,'Category Table'!$A18) | S18: =SUMIFS('PO Log'!$E:$E,'PO Log'!$D:$D,'Category Table'!S$2,'PO Log'!$C:$C,'Category Table'!$A18) | T18: =SUMIFS('PO Log'!$E:$E,'PO Log'!$D:$D,'Category Table'!T$2,'PO Log'!$C:$C,'Category Table'!$A18) | U18: =SUMIFS('Committments Dump'!$Q:$Q,'Committments Dump'!$C:$C,'Category Table'!U$2,'Committments Dump'!$B:$B,'Category Table'!$A18) | V18: =SUMIFS('Committments Dump'!$Q:$Q,'Committments Dump'!$C:$C,'Category Table'!V$2,'Committments Dump'!$B:$B,'Category Table'!$A18) | W18: =SUMIFS('Committments Dump'!$Q:$Q,'Committments Dump'!$C:$C,'Category Table'!W$2,'Committments Dump'!$B:$B,'Category Table'!$A18) | X18: =SUMIFS('Committments Dump'!$R:$R,'Committments Dump'!$C:$C,'Category Table'!X$2,'Committments Dump'!$B:$B,'Category Table'!$A18) | Y18: =SUMIFS('Committments Dump'!$R:$R,'Committments Dump'!$C:$C,'Category Table'!Y$2,'Committments Dump'!$B:$B,'Category Table'!$A18) | Z18: =SUMIFS('Committments Dump'!$R:$R,'Committments Dump'!$C:$C,'Category Table'!Z$2,'Committments Dump'!$B:$B,'Category Table'!$A18) | AA18: =SUMIFS('Committments Dump'!$S:$S,'Committments Dump'!$C:$C,'Category Table'!AA$2,'Committments Dump'!$B:$B,'Category Table'!$A18) | AB18: =SUMIFS('Committments Dump'!$S:$S,'Committments Dump'!$C:$C,'Category Table'!AB$2,'Committments Dump'!$B:$B,'Category Table'!$A18) | AC18: =SUMIFS('Committments Dump'!$S:$S,'Committments Dump'!$C:$C,'Category Table'!AC$2,'Committments Dump'!$B:$B,'Category Table'!$A18) | AD18: =U18+X18+AA18 | AE18: =V18+Y18+AB18 | AF18: =W18+Z18+AC18 | AG18: =R18+AD18 | AH18: =S18+AE18 | AI18: =T18+AF18 | AM18: =(O18-AG18)+AJ18 | AN18: =(P18-AH18)+AK18 | AO18: =(Q18-AI18)+AL18 | AP18: =IF(AM18>0, "Under",IF(AM18<0,"Over","")) | AQ18: =IF(AN18>0, "Under",IF(AN18<0,"Over","")) | AR18: =IF(AO18>0, "Under",IF(AO18<0,"Over",""))
A19: 0-4007 | B19: 0-4007-Mowing | C19: 0 | D19: 0 | E19: 0 | F19: 0 | G19: 0 | H19: 0 | I19: 0 | J19: 0 | K19: 0 | L19: 0 | M19: 0 | N19: 0 | O19: =L19+I19+F19+C19 | P19: =M19+J19+G19+D19 | Q19: =N19+K19+H19+E19 | R19: =SUMIFS('PO Log'!$E:$E,'PO Log'!$D:$D,'Category Table'!R$2,'PO Log'!$C:$C,'Category Table'!$A19) | S19: =SUMIFS('PO Log'!$E:$E,'PO Log'!$D:$D,'Category Table'!S$2,'PO Log'!$C:$C,'Category Table'!$A19) | T19: =SUMIFS('PO Log'!$E:$E,'PO Log'!$D:$D,'Category Table'!T$2,'PO Log'!$C:$C,'Category Table'!$A19) | U19: =SUMIFS('Committments Dump'!$Q:$Q,'Committments Dump'!$C:$C,'Category Table'!U$2,'Committments Dump'!$B:$B,'Category Table'!$A19) | V19: =SUMIFS('Committments Dump'!$Q:$Q,'Committments Dump'!$C:$C,'Category Table'!V$2,'Committments Dump'!$B:$B,'Category Table'!$A19) | W19: =SUMIFS('Committments Dump'!$Q:$Q,'Committments Dump'!$C:$C,'Category Table'!W$2,'Committments Dump'!$B:$B,'Category Table'!$A19) | X19: =SUMIFS('Committments Dump'!$R:$R,'Committments Dump'!$C:$C,'Category Table'!X$2,'Committments Dump'!$B:$B,'Category Table'!$A19) | Y19: =SUMIFS('Committments Dump'!$R:$R,'Committments Dump'!$C:$C,'Category Table'!Y$2,'Committments Dump'!$B:$B,'Category Table'!$A19) | Z19: =SUMIFS('Committments Dump'!$R:$R,'Committments Dump'!$C:$C,'Category Table'!Z$2,'Committments Dump'!$B:$B,'Category Table'!$A19) | AA19: =SUMIFS('Committments Dump'!$S:$S,'Committments Dump'!$C:$C,'Category Table'!AA$2,'Committments Dump'!$B:$B,'Category Table'!$A19) | AB19: =SUMIFS('Committments Dump'!$S:$S,'Committments Dump'!$C:$C,'Category Table'!AB$2,'Committments Dump'!$B:$B,'Category Table'!$A19) | AC19: =SUMIFS('Committments Dump'!$S:$S,'Committments Dump'!$C:$C,'Category Table'!AC$2,'Committments Dump'!$B:$B,'Category Table'!$A19) | AD19: =U19+X19+AA19 | AE19: =V19+Y19+AB19 | AF19: =W19+Z19+AC19 | AG19: =R19+AD19 | AH19: =S19+AE19 | AI19: =T19+AF19 | AM19: =(O19-AG19)+AJ19 | AN19: =(P19-AH19)+AK19 | AO19: =(Q19-AI19)+AL19 | AP19: =IF(AM19>0, "Under",IF(AM19<0,"Over","")) | AQ19: =IF(AN19>0, "Under",IF(AN19<0,"Over","")) | AR19: =IF(AO19>0, "Under",IF(AO19<0,"Over",""))
A20: 0-4008 | B20: 0-4008-Supplies | C20: 0 | D20: 108788 | E20: 0 | F20: 0 | G20: 2245561.2 | H20: 0 | I20: 0 | J20: 10749.05 | K20: 0 | L20: 0 | M20: 60149.43 | N20: 0 | O20: =L20+I20+F20+C20 | P20: =M20+J20+G20+D20 | Q20: =N20+K20+H20+E20 | R20: =SUMIFS('PO Log'!$E:$E,'PO Log'!$D:$D,'Category Table'!R$2,'PO Log'!$C:$C,'Category Table'!$A20) | S20: =SUMIFS('PO Log'!$E:$E,'PO Log'!$D:$D,'Category Table'!S$2,'PO Log'!$C:$C,'Category Table'!$A20) | T20: =SUMIFS('PO Log'!$E:$E,'PO Log'!$D:$D,'Category Table'!T$2,'PO Log'!$C:$C,'Category Table'!$A20) | U20: =SUMIFS('Committments Dump'!$Q:$Q,'Committments Dump'!$C:$C,'Category Table'!U$2,'Committments Dump'!$B:$B,'Category Table'!$A20) | V20: =SUMIFS('Committments Dump'!$Q:$Q,'Committments Dump'!$C:$C,'Category Table'!V$2,'Committments Dump'!$B:$B,'Category Table'!$A20) | W20: =SUMIFS('Committments Dump'!$Q:$Q,'Committments Dump'!$C:$C,'Category Table'!W$2,'Committments Dump'!$B:$B,'Category Table'!$A20) | X20: =SUMIFS('Committments Dump'!$R:$R,'Committments Dump'!$C:$C,'Category Table'!X$2,'Committments Dump'!$B:$B,'Category Table'!$A20) | Y20: =SUMIFS('Committments Dump'!$R:$R,'Committments Dump'!$C:$C,'Category Table'!Y$2,'Committments Dump'!$B:$B,'Category Table'!$A20) | Z20: =SUMIFS('Committments Dump'!$R:$R,'Committments Dump'!$C:$C,'Category Table'!Z$2,'Committments Dump'!$B:$B,'Category Table'!$A20) | AA20: =SUMIFS('Committments Dump'!$S:$S,'Committments Dump'!$C:$C,'Category Table'!AA$2,'Committments Dump'!$B:$B,'Category Table'!$A20) | AB20: =SUMIFS('Committments Dump'!$S:$S,'Committments Dump'!$C:$C,'Category Table'!AB$2,'Committments Dump'!$B:$B,'Category Table'!$A20) | AC20: =SUMIFS('Committments Dump'!$S:$S,'Committments Dump'!$C:$C,'Category Table'!AC$2,'Committments Dump'!$B:$B,'Category Table'!$A20) | AD20: =U20+X20+AA20 | AE20: =V20+Y20+AB20 | AF20: =W20+Z20+AC20 | AG20: =R20+AD20 | AH20: =S20+AE20 | AI20: =T20+AF20 | AM20: =(O20-AG20)+AJ20 | AN20: =(P20-AH20)+AK20 | AO20: =(Q20-AI20)+AL20 | AP20: =IF(AM20>0, "Under",IF(AM20<0,"Over","")) | AQ20: =IF(AN20>0, "Under",IF(AN20<0,"Over","")) | AR20: =IF(AO20>0, "Under",IF(AO20<0,"Over",""))
A21: 0-4010 | B21: 0-4010-FOG | C21: 0 | D21: 42925.37 | E21: 0 | F21: 0 | G21: 1855762.9 | H21: 0 | I21: 0 | J21: -63562.62 | K21: 0 | L21: 0 | M21: 0 | N21: 0 | O21: =L21+I21+F21+C21 | P21: =M21+J21+G21+D21 | Q21: =N21+K21+H21+E21 | R21: =SUMIFS('PO Log'!$E:$E,'PO Log'!$D:$D,'Category Table'!R$2,'PO Log'!$C:$C,'Category Table'!$A21) | S21: =SUMIFS('PO Log'!$E:$E,'PO Log'!$D:$D,'Category Table'!S$2,'PO Log'!$C:$C,'Category Table'!$A21) | T21: =SUMIFS('PO Log'!$E:$E,'PO Log'!$D:$D,'Category Table'!T$2,'PO Log'!$C:$C,'Category Table'!$A21) | U21: =SUMIFS('Committments Dump'!$Q:$Q,'Committments Dump'!$C:$C,'Category Table'!U$2,'Committments Dump'!$B:$B,'Category Table'!$A21) | V21: =SUMIFS('Committments Dump'!$Q:$Q,'Committments Dump'!$C:$C,'Category Table'!V$2,'Committments Dump'!$B:$B,'Category Table'!$A21) | W21: =SUMIFS('Committments Dump'!$Q:$Q,'Committments Dump'!$C:$C,'Category Table'!W$2,'Committments Dump'!$B:$B,'Category Table'!$A21) | X21: =SUMIFS('Committments Dump'!$R:$R,'Committments Dump'!$C:$C,'Category Table'!X$2,'Committments Dump'!$B:$B,'Category Table'!$A21) | Y21: =SUMIFS('Committments Dump'!$R:$R,'Committments Dump'!$C:$C,'Category Table'!Y$2,'Committments Dump'!$B:$B,'Category Table'!$A21) | Z21: =SUMIFS('Committments Dump'!$R:$R,'Committments Dump'!$C:$C,'Category Table'!Z$2,'Committments Dump'!$B:$B,'Category Table'!$A21) | AA21: =SUMIFS('Committments Dump'!$S:$S,'Committments Dump'!$C:$C,'Category Table'!AA$2,'Committments Dump'!$B:$B,'Category Table'!$A21) | AB21: =SUMIFS('Committments Dump'!$S:$S,'Committments Dump'!$C:$C,'Category Table'!AB$2,'Committments Dump'!$B:$B,'Category Table'!$A21) | AC21: =SUMIFS('Committments Dump'!$S:$S,'Committments Dump'!$C:$C,'Category Table'!AC$2,'Committments Dump'!$B:$B,'Category Table'!$A21) | AD21: =U21+X21+AA21 | AE21: =V21+Y21+AB21 | AF21: =W21+Z21+AC21 | AG21: =R21+AD21 | AH21: =S21+AE21 | AI21: =T21+AF21 | AM21: =(O21-AG21)+AJ21 | AN21: =(P21-AH21)+AK21 | AO21: =(Q21-AI21)+AL21 | AP21: =IF(AM21>0, "Under",IF(AM21<0,"Over","")) | AQ21: =IF(AN21>0, "Under",IF(AN21<0,"Over","")) | AR21: =IF(AO21>0, "Under",IF(AO21<0,"Over",""))
A22: 0-4013 | B22: 0-4013-Contingency | C22: 0 | D22: 0 | E22: 0 | F22: 4883701.6 | H22: 0 | I22: 0 | J22: 0 | K22: 0 | L22: 0 | M22: 0 | N22: 0 | O22: =L22+I22+F22+C22 | P22: =M22+J22+G22+D22 | Q22: =N22+K22+H22+E22 | R22: =SUMIFS('PO Log'!$E:$E,'PO Log'!$D:$D,'Category Table'!R$2,'PO Log'!$C:$C,'Category Table'!$A22) | S22: =SUMIFS('PO Log'!$E:$E,'PO Log'!$D:$D,'Category Table'!S$2,'PO Log'!$C:$C,'Category Table'!$A22) | T22: =SUMIFS('PO Log'!$E:$E,'PO Log'!$D:$D,'Category Table'!T$2,'PO Log'!$C:$C,'Category Table'!$A22) | U22: =SUMIFS('Committments Dump'!$Q:$Q,'Committments Dump'!$C:$C,'Category Table'!U$2,'Committments Dump'!$B:$B,'Category Table'!$A22) | V22: =SUMIFS('Committments Dump'!$Q:$Q,'Committments Dump'!$C:$C,'Category Table'!V$2,'Committments Dump'!$B:$B,'Category Table'!$A22) | W22: =SUMIFS('Committments Dump'!$Q:$Q,'Committments Dump'!$C:$C,'Category Table'!W$2,'Committments Dump'!$B:$B,'Category Table'!$A22) | X22: =SUMIFS('Committments Dump'!$R:$R,'Committments Dump'!$C:$C,'Category Table'!X$2,'Committments Dump'!$B:$B,'Category Table'!$A22) | Y22: =SUMIFS('Committments Dump'!$R:$R,'Committments Dump'!$C:$C,'Category Table'!Y$2,'Committments Dump'!$B:$B,'Category Table'!$A22) | Z22: =SUMIFS('Committments Dump'!$R:$R,'Committments Dump'!$C:$C,'Category Table'!Z$2,'Committments Dump'!$B:$B,'Category Table'!$A22) | AA22: =SUMIFS('Committments Dump'!$S:$S,'Committments Dump'!$C:$C,'Category Table'!AA$2,'Committments Dump'!$B:$B,'Category Table'!$A22) | AB22: =SUMIFS('Committments Dump'!$S:$S,'Committments Dump'!$C:$C,'Category Table'!AB$2,'Committments Dump'!$B:$B,'Category Table'!$A22) | AC22: =SUMIFS('Committments Dump'!$S:$S,'Committments Dump'!$C:$C,'Category Table'!AC$2,'Committments Dump'!$B:$B,'Category Table'!$A22) | AD22: =U22+X22+AA22 | AE22: =V22+Y22+AB22 | AF22: =W22+Z22+AC22 | AG22: =R22+AD22 | AH22: =S22+AE22 | AI22: =T22+AF22 | AM22: =(O22-AG22)+AJ22 | AN22: =(P22-AH22)+AK22 | AO22: =(Q22-AI22)+AL22 | AP22: =IF(AM22>0, "Under",IF(AM22<0,"Over","")) | AQ22: =IF(AN22>0, "Under",IF(AN22<0,"Over","")) | AR22: =IF(AO22>0, "Under",IF(AO22<0,"Over",""))
A23: 0-4013-01 | B23: 0-4013-01-LD's | C23: 0 | D23: 0 | E23: 0 | F23: 1800000 | G23: 0 | H23: 0 | I23: 0 | J23: 0 | K23: 0 | L23: 0 | M23: 0 | N23: 0 | O23: =L23+I23+F23+C23 | P23: =M23+J23+G23+D23 | Q23: =N23+K23+H23+E23 | R23: =SUMIFS('PO Log'!$E:$E,'PO Log'!$D:$D,'Category Table'!R$2,'PO Log'!$C:$C,'Category Table'!$A23) | S23: =SUMIFS('PO Log'!$E:$E,'PO Log'!$D:$D,'Category Table'!S$2,'PO Log'!$C:$C,'Category Table'!$A23) | T23: =SUMIFS('PO Log'!$E:$E,'PO Log'!$D:$D,'Category Table'!T$2,'PO Log'!$C:$C,'Category Table'!$A23) | U23: =SUMIFS('Committments Dump'!$Q:$Q,'Committments Dump'!$C:$C,'Category Table'!U$2,'Committments Dump'!$B:$B,'Category Table'!$A23) | V23: =SUMIFS('Committments Dump'!$Q:$Q,'Committments Dump'!$C:$C,'Category Table'!V$2,'Committments Dump'!$B:$B,'Category Table'!$A23) | W23: =SUMIFS('Committments Dump'!$Q:$Q,'Committments Dump'!$C:$C,'Category Table'!W$2,'Committments Dump'!$B:$B,'Category Table'!$A23) | X23: =SUMIFS('Committments Dump'!$R:$R,'Committments Dump'!$C:$C,'Category Table'!X$2,'Committments Dump'!$B:$B,'Category Table'!$A23) | Y23: =SUMIFS('Committments Dump'!$R:$R,'Committments Dump'!$C:$C,'Category Table'!Y$2,'Committments Dump'!$B:$B,'Category Table'!$A23) | Z23: =SUMIFS('Committments Dump'!$R:$R,'Committments Dump'!$C:$C,'Category Table'!Z$2,'Committments Dump'!$B:$B,'Category Table'!$A23) | AA23: =SUMIFS('Committments Dump'!$S:$S,'Committments Dump'!$C:$C,'Category Table'!AA$2,'Committments Dump'!$B:$B,'Category Table'!$A23) | AB23: =SUMIFS('Committments Dump'!$S:$S,'Committments Dump'!$C:$C,'Category Table'!AB$2,'Committments Dump'!$B:$B,'Category Table'!$A23) | AC23: =SUMIFS('Committments Dump'!$S:$S,'Committments Dump'!$C:$C,'Category Table'!AC$2,'Committments Dump'!$B:$B,'Category Table'!$A23) | AD23: =U23+X23+AA23 | AE23: =V23+Y23+AB23 | AF23: =W23+Z23+AC23 | AG23: =R23+AD23 | AH23: =S23+AE23 | AI23: =T23+AF23 | AM23: =(O23-AG23)+AJ23 | AN23: =(P23-AH23)+AK23 | AO23: =(Q23-AI23)+AL23 | AP23: =IF(AM23>0, "Under",IF(AM23<0,"Over","")) | AQ23: =IF(AN23>0, "Under",IF(AN23<0,"Over","")) | AR23: =IF(AO23>0, "Under",IF(AO23<0,"Over",""))
A24: 0-4013-02 | B24: 0-4013-02-Weather Cont. | C24: 0 | D24: 0 | E24: 0 | F24: 1386221 | G24: 0 | H24: 0 | I24: 0 | J24: 0 | K24: 0 | L24: 0 | M24: 0 | N24: 0 | O24: =L24+I24+F24+C24 | P24: =M24+J24+G24+D24 | Q24: =N24+K24+H24+E24 | R24: =SUMIFS('PO Log'!$E:$E,'PO Log'!$D:$D,'Category Table'!R$2,'PO Log'!$C:$C,'Category Table'!$A24) | S24: =SUMIFS('PO Log'!$E:$E,'PO Log'!$D:$D,'Category Table'!S$2,'PO Log'!$C:$C,'Category Table'!$A24) | T24: =SUMIFS('PO Log'!$E:$E,'PO Log'!$D:$D,'Category Table'!T$2,'PO Log'!$C:$C,'Category Table'!$A24) | U24: =SUMIFS('Committments Dump'!$Q:$Q,'Committments Dump'!$C:$C,'Category Table'!U$2,'Committments Dump'!$B:$B,'Category Table'!$A24) | V24: =SUMIFS('Committments Dump'!$Q:$Q,'Committments Dump'!$C:$C,'Category Table'!V$2,'Committments Dump'!$B:$B,'Category Table'!$A24) | W24: =SUMIFS('Committments Dump'!$Q:$Q,'Committments Dump'!$C:$C,'Category Table'!W$2,'Committments Dump'!$B:$B,'Category Table'!$A24) | X24: =SUMIFS('Committments Dump'!$R:$R,'Committments Dump'!$C:$C,'Category Table'!X$2,'Committments Dump'!$B:$B,'Category Table'!$A24) | Y24: =SUMIFS('Committments Dump'!$R:$R,'Committments Dump'!$C:$C,'Category Table'!Y$2,'Committments Dump'!$B:$B,'Category Table'!$A24) | Z24: =SUMIFS('Committments Dump'!$R:$R,'Committments Dump'!$C:$C,'Category Table'!Z$2,'Committments Dump'!$B:$B,'Category Table'!$A24) | AA24: =SUMIFS('Committments Dump'!$S:$S,'Committments Dump'!$C:$C,'Category Table'!AA$2,'Committments Dump'!$B:$B,'Category Table'!$A24) | AB24: =SUMIFS('Committments Dump'!$S:$S,'Committments Dump'!$C:$C,'Category Table'!AB$2,'Committments Dump'!$B:$B,'Category Table'!$A24) | AC24: =SUMIFS('Committments Dump'!$S:$S,'Committments Dump'!$C:$C,'Category Table'!AC$2,'Committments Dump'!$B:$B,'Category Table'!$A24) | AD24: =U24+X24+AA24 | AE24: =V24+Y24+AB24 | AF24: =W24+Z24+AC24 | AG24: =R24+AD24 | AH24: =S24+AE24 | AI24: =T24+AF24 | AM24: =(O24-AG24)+AJ24 | AN24: =(P24-AH24)+AK24 | AO24: =(Q24-AI24)+AL24 | AP24: =IF(AM24>0, "Under",IF(AM24<0,"Over","")) | AQ24: =IF(AN24>0, "Under",IF(AN24<0,"Over","")) | AR24: =IF(AO24>0, "Under",IF(AO24<0,"Over",""))
A25: 0-4015 | B25: 0-4015-Survey | C25: 28288.75 | D25: 956.01 | E25: 325.83 | F25: 466368.3 | G25: -144949.54 | H25: 0 | I25: 0 | J25: 0 | K25: 0 | L25: 0 | M25: 0 | N25: 0 | O25: =L25+I25+F25+C25 | P25: =M25+J25+G25+D25 | Q25: =N25+K25+H25+E25 | R25: =SUMIFS('PO Log'!$E:$E,'PO Log'!$D:$D,'Category Table'!R$2,'PO Log'!$C:$C,'Category Table'!$A25) | S25: =SUMIFS('PO Log'!$E:$E,'PO Log'!$D:$D,'Category Table'!S$2,'PO Log'!$C:$C,'Category Table'!$A25) | T25: =SUMIFS('PO Log'!$E:$E,'PO Log'!$D:$D,'Category Table'!T$2,'PO Log'!$C:$C,'Category Table'!$A25) | U25: =SUMIFS('Committments Dump'!$Q:$Q,'Committments Dump'!$C:$C,'Category Table'!U$2,'Committments Dump'!$B:$B,'Category Table'!$A25) | V25: =SUMIFS('Committments Dump'!$Q:$Q,'Committments Dump'!$C:$C,'Category Table'!V$2,'Committments Dump'!$B:$B,'Category Table'!$A25) | W25: =SUMIFS('Committments Dump'!$Q:$Q,'Committments Dump'!$C:$C,'Category Table'!W$2,'Committments Dump'!$B:$B,'Category Table'!$A25) | X25: =SUMIFS('Committments Dump'!$R:$R,'Committments Dump'!$C:$C,'Category Table'!X$2,'Committments Dump'!$B:$B,'Category Table'!$A25) | Y25: =SUMIFS('Committments Dump'!$R:$R,'Committments Dump'!$C:$C,'Category Table'!Y$2,'Committments Dump'!$B:$B,'Category Table'!$A25) | Z25: =SUMIFS('Committments Dump'!$R:$R,'Committments Dump'!$C:$C,'Category Table'!Z$2,'Committments Dump'!$B:$B,'Category Table'!$A25) | AA25: =SUMIFS('Committments Dump'!$S:$S,'Committments Dump'!$C:$C,'Category Table'!AA$2,'Committments Dump'!$B:$B,'Category Table'!$A25) | AB25: =SUMIFS('Committments Dump'!$S:$S,'Committments Dump'!$C:$C,'Category Table'!AB$2,'Committments Dump'!$B:$B,'Category Table'!$A25) | AC25: =SUMIFS('Committments Dump'!$S:$S,'Committments Dump'!$C:$C,'Category Table'!AC$2,'Committments Dump'!$B:$B,'Category Table'!$A25) | AD25: =U25+X25+AA25 | AE25: =V25+Y25+AB25 | AF25: =W25+Z25+AC25 | AG25: =R25+AD25 | AH25: =S25+AE25 | AI25: =T25+AF25 | AM25: =(O25-AG25)+AJ25 | AN25: =(P25-AH25)+AK25 | AO25: =(Q25-AI25)+AL25 | AP25: =IF(AM25>0, "Under",IF(AM25<0,"Over","")) | AQ25: =IF(AN25>0, "Under",IF(AN25<0,"Over","")) | AR25: =IF(AO25>0, "Under",IF(AO25<0,"Over",""))
A26: 0-4016 | B26: 0-4016-Permits | C26: 20024.36 | D26: 0 | E26: 0 | F26: 0 | G26: 0 | H26: 36554.39 | I26: 0 | J26: 0 | K26: 0 | L26: 43421.25 | M26: 0 | N26: 0 | O26: =L26+I26+F26+C26 | P26: =M26+J26+G26+D26 | Q26: =N26+K26+H26+E26 | R26: =SUMIFS('PO Log'!$E:$E,'PO Log'!$D:$D,'Category Table'!R$2,'PO Log'!$C:$C,'Category Table'!$A26) | S26: =SUMIFS('PO Log'!$E:$E,'PO Log'!$D:$D,'Category Table'!S$2,'PO Log'!$C:$C,'Category Table'!$A26) | T26: =SUMIFS('PO Log'!$E:$E,'PO Log'!$D:$D,'Category Table'!T$2,'PO Log'!$C:$C,'Category Table'!$A26) | U26: =SUMIFS('Committments Dump'!$Q:$Q,'Committments Dump'!$C:$C,'Category Table'!U$2,'Committments Dump'!$B:$B,'Category Table'!$A26) | V26: =SUMIFS('Committments Dump'!$Q:$Q,'Committments Dump'!$C:$C,'Category Table'!V$2,'Committments Dump'!$B:$B,'Category Table'!$A26) | W26: =SUMIFS('Committments Dump'!$Q:$Q,'Committments Dump'!$C:$C,'Category Table'!W$2,'Committments Dump'!$B:$B,'Category Table'!$A26) | X26: =SUMIFS('Committments Dump'!$R:$R,'Committments Dump'!$C:$C,'Category Table'!X$2,'Committments Dump'!$B:$B,'Category Table'!$A26) | Y26: =SUMIFS('Committments Dump'!$R:$R,'Committments Dump'!$C:$C,'Category Table'!Y$2,'Committments Dump'!$B:$B,'Category Table'!$A26) | Z26: =SUMIFS('Committments Dump'!$R:$R,'Committments Dump'!$C:$C,'Category Table'!Z$2,'Committments Dump'!$B:$B,'Category Table'!$A26) | AA26: =SUMIFS('Committments Dump'!$S:$S,'Committments Dump'!$C:$C,'Category Table'!AA$2,'Committments Dump'!$B:$B,'Category Table'!$A26) | AB26: =SUMIFS('Committments Dump'!$S:$S,'Committments Dump'!$C:$C,'Category Table'!AB$2,'Committments Dump'!$B:$B,'Category Table'!$A26) | AC26: =SUMIFS('Committments Dump'!$S:$S,'Committments Dump'!$C:$C,'Category Table'!AC$2,'Committments Dump'!$B:$B,'Category Table'!$A26) | AD26: =U26+X26+AA26 | AE26: =V26+Y26+AB26 | AF26: =W26+Z26+AC26 | AG26: =R26+AD26 | AH26: =S26+AE26 | AI26: =T26+AF26 | AM26: =(O26-AG26)+AJ26 | AN26: =(P26-AH26)+AK26 | AO26: =(Q26-AI26)+AL26 | AP26: =IF(AM26>0, "Under",IF(AM26<0,"Over","")) | AQ26: =IF(AN26>0, "Under",IF(AN26<0,"Over","")) | AR26: =IF(AO26>0, "Under",IF(AO26<0,"Over",""))
A27: 0-4017 | B27: 0-4017-Utility Locate | C27: 0 | D27: 849.86 | E27: 0 | F27: 2821.59 | G27: 0 | H27: 0 | I27: 0 | J27: 0 | K27: 0 | L27: 0 | M27: 21328.55 | N27: 0 | O27: =L27+I27+F27+C27 | P27: =M27+J27+G27+D27 | Q27: =N27+K27+H27+E27 | R27: =SUMIFS('PO Log'!$E:$E,'PO Log'!$D:$D,'Category Table'!R$2,'PO Log'!$C:$C,'Category Table'!$A27) | S27: =SUMIFS('PO Log'!$E:$E,'PO Log'!$D:$D,'Category Table'!S$2,'PO Log'!$C:$C,'Category Table'!$A27) | T27: =SUMIFS('PO Log'!$E:$E,'PO Log'!$D:$D,'Category Table'!T$2,'PO Log'!$C:$C,'Category Table'!$A27) | U27: =SUMIFS('Committments Dump'!$Q:$Q,'Committments Dump'!$C:$C,'Category Table'!U$2,'Committments Dump'!$B:$B,'Category Table'!$A27) | V27: =SUMIFS('Committments Dump'!$Q:$Q,'Committments Dump'!$C:$C,'Category Table'!V$2,'Committments Dump'!$B:$B,'Category Table'!$A27) | W27: =SUMIFS('Committments Dump'!$Q:$Q,'Committments Dump'!$C:$C,'Category Table'!W$2,'Committments Dump'!$B:$B,'Category Table'!$A27) | X27: =SUMIFS('Committments Dump'!$R:$R,'Committments Dump'!$C:$C,'Category Table'!X$2,'Committments Dump'!$B:$B,'Category Table'!$A27) | Y27: =SUMIFS('Committments Dump'!$R:$R,'Committments Dump'!$C:$C,'Category Table'!Y$2,'Committments Dump'!$B:$B,'Category Table'!$A27) | Z27: =SUMIFS('Committments Dump'!$R:$R,'Committments Dump'!$C:$C,'Category Table'!Z$2,'Committments Dump'!$B:$B,'Category Table'!$A27) | AA27: =SUMIFS('Committments Dump'!$S:$S,'Committments Dump'!$C:$C,'Category Table'!AA$2,'Committments Dump'!$B:$B,'Category Table'!$A27) | AB27: =SUMIFS('Committments Dump'!$S:$S,'Committments Dump'!$C:$C,'Category Table'!AB$2,'Committments Dump'!$B:$B,'Category Table'!$A27) | AC27: =SUMIFS('Committments Dump'!$S:$S,'Committments Dump'!$C:$C,'Category Table'!AC$2,'Committments Dump'!$B:$B,'Category Table'!$A27) | AD27: =U27+X27+AA27 | AE27: =V27+Y27+AB27 | AF27: =W27+Z27+AC27 | AG27: =R27+AD27 | AH27: =S27+AE27 | AI27: =T27+AF27 | AM27: =(O27-AG27)+AJ27 | AN27: =(P27-AH27)+AK27 | AO27: =(Q27-AI27)+AL27 | AP27: =IF(AM27>0, "Under",IF(AM27<0,"Over","")) | AQ27: =IF(AN27>0, "Under",IF(AN27<0,"Over","")) | AR27: =IF(AO27>0, "Under",IF(AO27<0,"Over",""))
A28: 0-4024 | B28: 0-4024-Engineering | C28: 1128965 | D28: 28340.55 | E28: 0 | F28: 1419040.4 | G28: 0 | H28: 0 | I28: 0 | J28: 0 | K28: 0 | L28: 223654.01 | M28: 0 | N28: 0 | O28: =L28+I28+F28+C28 | P28: =M28+J28+G28+D28 | Q28: =N28+K28+H28+E28 | R28: =SUMIFS('PO Log'!$E:$E,'PO Log'!$D:$D,'Category Table'!R$2,'PO Log'!$C:$C,'Category Table'!$A28) | S28: =SUMIFS('PO Log'!$E:$E,'PO Log'!$D:$D,'Category Table'!S$2,'PO Log'!$C:$C,'Category Table'!$A28) | T28: =SUMIFS('PO Log'!$E:$E,'PO Log'!$D:$D,'Category Table'!T$2,'PO Log'!$C:$C,'Category Table'!$A28) | U28: =SUMIFS('Committments Dump'!$Q:$Q,'Committments Dump'!$C:$C,'Category Table'!U$2,'Committments Dump'!$B:$B,'Category Table'!$A28) | V28: =SUMIFS('Committments Dump'!$Q:$Q,'Committments Dump'!$C:$C,'Category Table'!V$2,'Committments Dump'!$B:$B,'Category Table'!$A28) | W28: =SUMIFS('Committments Dump'!$Q:$Q,'Committments Dump'!$C:$C,'Category Table'!W$2,'Committments Dump'!$B:$B,'Category Table'!$A28) | X28: =SUMIFS('Committments Dump'!$R:$R,'Committments Dump'!$C:$C,'Category Table'!X$2,'Committments Dump'!$B:$B,'Category Table'!$A28) | Y28: =SUMIFS('Committments Dump'!$R:$R,'Committments Dump'!$C:$C,'Category Table'!Y$2,'Committments Dump'!$B:$B,'Category Table'!$A28) | Z28: =SUMIFS('Committments Dump'!$R:$R,'Committments Dump'!$C:$C,'Category Table'!Z$2,'Committments Dump'!$B:$B,'Category Table'!$A28) | AA28: =SUMIFS('Committments Dump'!$S:$S,'Committments Dump'!$C:$C,'Category Table'!AA$2,'Committments Dump'!$B:$B,'Category Table'!$A28) | AB28: =SUMIFS('Committments Dump'!$S:$S,'Committments Dump'!$C:$C,'Category Table'!AB$2,'Committments Dump'!$B:$B,'Category Table'!$A28) | AC28: =SUMIFS('Committments Dump'!$S:$S,'Committments Dump'!$C:$C,'Category Table'!AC$2,'Committments Dump'!$B:$B,'Category Table'!$A28) | AD28: =U28+X28+AA28 | AE28: =V28+Y28+AB28 | AF28: =W28+Z28+AC28 | AG28: =R28+AD28 | AH28: =S28+AE28 | AI28: =T28+AF28 | AM28: =(O28-AG28)+AJ28 | AN28: =(P28-AH28)+AK28 | AO28: =(Q28-AI28)+AL28 | AP28: =IF(AM28>0, "Under",IF(AM28<0,"Over","")) | AQ28: =IF(AN28>0, "Under",IF(AN28<0,"Over","")) | AR28: =IF(AO28>0, "Under",IF(AO28<0,"Over",""))
A29: 0-4029 | B29: 0-4029-ACS | C29: 0 | D29: 0 | E29: 0 | F29: 1680000 | G29: 0 | H29: 0 | I29: 0 | J29: 0 | K29: 0 | L29: 0 | M29: 0 | N29: 0 | O29: =L29+I29+F29+C29 | P29: =M29+J29+G29+D29 | Q29: =N29+K29+H29+E29 | R29: =SUMIFS('PO Log'!$E:$E,'PO Log'!$D:$D,'Category Table'!R$2,'PO Log'!$C:$C,'Category Table'!$A29) | S29: =SUMIFS('PO Log'!$E:$E,'PO Log'!$D:$D,'Category Table'!S$2,'PO Log'!$C:$C,'Category Table'!$A29) | T29: =SUMIFS('PO Log'!$E:$E,'PO Log'!$D:$D,'Category Table'!T$2,'PO Log'!$C:$C,'Category Table'!$A29) | U29: =SUMIFS('Committments Dump'!$Q:$Q,'Committments Dump'!$C:$C,'Category Table'!U$2,'Committments Dump'!$B:$B,'Category Table'!$A29) | V29: =SUMIFS('Committments Dump'!$Q:$Q,'Committments Dump'!$C:$C,'Category Table'!V$2,'Committments Dump'!$B:$B,'Category Table'!$A29) | W29: =SUMIFS('Committments Dump'!$Q:$Q,'Committments Dump'!$C:$C,'Category Table'!W$2,'Committments Dump'!$B:$B,'Category Table'!$A29) | X29: =SUMIFS('Committments Dump'!$R:$R,'Committments Dump'!$C:$C,'Category Table'!X$2,'Committments Dump'!$B:$B,'Category Table'!$A29) | Y29: =SUMIFS('Committments Dump'!$R:$R,'Committments Dump'!$C:$C,'Category Table'!Y$2,'Committments Dump'!$B:$B,'Category Table'!$A29) | Z29: =SUMIFS('Committments Dump'!$R:$R,'Committments Dump'!$C:$C,'Category Table'!Z$2,'Committments Dump'!$B:$B,'Category Table'!$A29) | AA29: =SUMIFS('Committments Dump'!$S:$S,'Committments Dump'!$C:$C,'Category Table'!AA$2,'Committments Dump'!$B:$B,'Category Table'!$A29) | AB29: =SUMIFS('Committments Dump'!$S:$S,'Committments Dump'!$C:$C,'Category Table'!AB$2,'Committments Dump'!$B:$B,'Category Table'!$A29) | AC29: =SUMIFS('Committments Dump'!$S:$S,'Committments Dump'!$C:$C,'Category Table'!AC$2,'Committments Dump'!$B:$B,'Category Table'!$A29) | AD29: =U29+X29+AA29 | AE29: =V29+Y29+AB29 | AF29: =W29+Z29+AC29 | AG29: =R29+AD29 | AH29: =S29+AE29 | AI29: =T29+AF29 | AM29: =(O29-AG29)+AJ29 | AN29: =(P29-AH29)+AK29 | AO29: =(Q29-AI29)+AL29 | AP29: =IF(AM29>0, "Under",IF(AM29<0,"Over","")) | AQ29: =IF(AN29>0, "Under",IF(AN29<0,"Over","")) | AR29: =IF(AO29>0, "Under",IF(AO29<0,"Over",""))
A30: 0-4031 | B30: 0-4031-Hire-In and Orientation | C30: 0 | D30: 1549.5 | E30: 0 | F30: 0 | G30: 544.24541 | H30: 0 | I30: 0 | J30: 0 | K30: 0 | L30: 0 | M30: 0 | N30: 0 | O30: =L30+I30+F30+C30 | P30: =M30+J30+G30+D30 | Q30: =N30+K30+H30+E30 | R30: =SUMIFS('PO Log'!$E:$E,'PO Log'!$D:$D,'Category Table'!R$2,'PO Log'!$C:$C,'Category Table'!$A30) | S30: =SUMIFS('PO Log'!$E:$E,'PO Log'!$D:$D,'Category Table'!S$2,'PO Log'!$C:$C,'Category Table'!$A30) | T30: =SUMIFS('PO Log'!$E:$E,'PO Log'!$D:$D,'Category Table'!T$2,'PO Log'!$C:$C,'Category Table'!$A30) | U30: =SUMIFS('Committments Dump'!$Q:$Q,'Committments Dump'!$C:$C,'Category Table'!U$2,'Committments Dump'!$B:$B,'Category Table'!$A30) | V30: =SUMIFS('Committments Dump'!$Q:$Q,'Committments Dump'!$C:$C,'Category Table'!V$2,'Committments Dump'!$B:$B,'Category Table'!$A30) | W30: =SUMIFS('Committments Dump'!$Q:$Q,'Committments Dump'!$C:$C,'Category Table'!W$2,'Committments Dump'!$B:$B,'Category Table'!$A30) | X30: =SUMIFS('Committments Dump'!$R:$R,'Committments Dump'!$C:$C,'Category Table'!X$2,'Committments Dump'!$B:$B,'Category Table'!$A30) | Y30: =SUMIFS('Committments Dump'!$R:$R,'Committments Dump'!$C:$C,'Category Table'!Y$2,'Committments Dump'!$B:$B,'Category Table'!$A30) | Z30: =SUMIFS('Committments Dump'!$R:$R,'Committments Dump'!$C:$C,'Category Table'!Z$2,'Committments Dump'!$B:$B,'Category Table'!$A30) | AA30: =SUMIFS('Committments Dump'!$S:$S,'Committments Dump'!$C:$C,'Category Table'!AA$2,'Committments Dump'!$B:$B,'Category Table'!$A30) | AB30: =SUMIFS('Committments Dump'!$S:$S,'Committments Dump'!$C:$C,'Category Table'!AB$2,'Committments Dump'!$B:$B,'Category Table'!$A30) | AC30: =SUMIFS('Committments Dump'!$S:$S,'Committments Dump'!$C:$C,'Category Table'!AC$2,'Committments Dump'!$B:$B,'Category Table'!$A30) | AD30: =U30+X30+AA30 | AE30: =V30+Y30+AB30 | AF30: =W30+Z30+AC30 | AG30: =R30+AD30 | AH30: =S30+AE30 | AI30: =T30+AF30 | AM30: =(O30-AG30)+AJ30 | AN30: =(P30-AH30)+AK30 | AO30: =(Q30-AI30)+AL30 | AP30: =IF(AM30>0, "Under",IF(AM30<0,"Over","")) | AQ30: =IF(AN30>0, "Under",IF(AN30<0,"Over","")) | AR30: =IF(AO30>0, "Under",IF(AO30<0,"Over",""))
A31: 0-4115 | B31: 0-4115-Clean Up | C31: 0 | D31: 0 | E31: 0 | F31: 0 | G31: 0 | H31: 0 | I31: 0 | J31: 0 | K31: 0 | L31: 0 | M31: 0 | N31: 0 | O31: =L31+I31+F31+C31 | P31: =M31+J31+G31+D31 | Q31: =N31+K31+H31+E31 | R31: =SUMIFS('PO Log'!$E:$E,'PO Log'!$D:$D,'Category Table'!R$2,'PO Log'!$C:$C,'Category Table'!$A31) | S31: =SUMIFS('PO Log'!$E:$E,'PO Log'!$D:$D,'Category Table'!S$2,'PO Log'!$C:$C,'Category Table'!$A31) | T31: =SUMIFS('PO Log'!$E:$E,'PO Log'!$D:$D,'Category Table'!T$2,'PO Log'!$C:$C,'Category Table'!$A31) | U31: =SUMIFS('Committments Dump'!$Q:$Q,'Committments Dump'!$C:$C,'Category Table'!U$2,'Committments Dump'!$B:$B,'Category Table'!$A31) | V31: =SUMIFS('Committments Dump'!$Q:$Q,'Committments Dump'!$C:$C,'Category Table'!V$2,'Committments Dump'!$B:$B,'Category Table'!$A31) | W31: =SUMIFS('Committments Dump'!$Q:$Q,'Committments Dump'!$C:$C,'Category Table'!W$2,'Committments Dump'!$B:$B,'Category Table'!$A31) | X31: =SUMIFS('Committments Dump'!$R:$R,'Committments Dump'!$C:$C,'Category Table'!X$2,'Committments Dump'!$B:$B,'Category Table'!$A31) | Y31: =SUMIFS('Committments Dump'!$R:$R,'Committments Dump'!$C:$C,'Category Table'!Y$2,'Committments Dump'!$B:$B,'Category Table'!$A31) | Z31: =SUMIFS('Committments Dump'!$R:$R,'Committments Dump'!$C:$C,'Category Table'!Z$2,'Committments Dump'!$B:$B,'Category Table'!$A31) | AA31: =SUMIFS('Committments Dump'!$S:$S,'Committments Dump'!$C:$C,'Category Table'!AA$2,'Committments Dump'!$B:$B,'Category Table'!$A31) | AB31: =SUMIFS('Committments Dump'!$S:$S,'Committments Dump'!$C:$C,'Category Table'!AB$2,'Committments Dump'!$B:$B,'Category Table'!$A31) | AC31: =SUMIFS('Committments Dump'!$S:$S,'Committments Dump'!$C:$C,'Category Table'!AC$2,'Committments Dump'!$B:$B,'Category Table'!$A31) | AD31: =U31+X31+AA31 | AE31: =V31+Y31+AB31 | AF31: =W31+Z31+AC31 | AG31: =R31+AD31 | AH31: =S31+AE31 | AI31: =T31+AF31 | AM31: =(O31-AG31)+AJ31 | AN31: =(P31-AH31)+AK31 | AO31: =(Q31-AI31)+AL31 | AP31: =IF(AM31>0, "Under",IF(AM31<0,"Over","")) | AQ31: =IF(AN31>0, "Under",IF(AN31<0,"Over","")) | AR31: =IF(AO31>0, "Under",IF(AO31<0,"Over",""))
A32: 0-4300 | B32: 0-4300-Mechanical Receiving | C32: 0 | D32: 0 | E32: 0 | F32: 0 | G32: 0 | H32: 0 | I32: 0 | J32: 0 | K32: 0 | L32: 0 | M32: 0 | N32: 0 | O32: =L32+I32+F32+C32 | P32: =M32+J32+G32+D32 | Q32: =N32+K32+H32+E32 | R32: =SUMIFS('PO Log'!$E:$E,'PO Log'!$D:$D,'Category Table'!R$2,'PO Log'!$C:$C,'Category Table'!$A32) | S32: =SUMIFS('PO Log'!$E:$E,'PO Log'!$D:$D,'Category Table'!S$2,'PO Log'!$C:$C,'Category Table'!$A32) | T32: =SUMIFS('PO Log'!$E:$E,'PO Log'!$D:$D,'Category Table'!T$2,'PO Log'!$C:$C,'Category Table'!$A32) | U32: =SUMIFS('Committments Dump'!$Q:$Q,'Committments Dump'!$C:$C,'Category Table'!U$2,'Committments Dump'!$B:$B,'Category Table'!$A32) | V32: =SUMIFS('Committments Dump'!$Q:$Q,'Committments Dump'!$C:$C,'Category Table'!V$2,'Committments Dump'!$B:$B,'Category Table'!$A32) | W32: =SUMIFS('Committments Dump'!$Q:$Q,'Committments Dump'!$C:$C,'Category Table'!W$2,'Committments Dump'!$B:$B,'Category Table'!$A32) | X32: =SUMIFS('Committments Dump'!$R:$R,'Committments Dump'!$C:$C,'Category Table'!X$2,'Committments Dump'!$B:$B,'Category Table'!$A32) | Y32: =SUMIFS('Committments Dump'!$R:$R,'Committments Dump'!$C:$C,'Category Table'!Y$2,'Committments Dump'!$B:$B,'Category Table'!$A32) | Z32: =SUMIFS('Committments Dump'!$R:$R,'Committments Dump'!$C:$C,'Category Table'!Z$2,'Committments Dump'!$B:$B,'Category Table'!$A32) | AA32: =SUMIFS('Committments Dump'!$S:$S,'Committments Dump'!$C:$C,'Category Table'!AA$2,'Committments Dump'!$B:$B,'Category Table'!$A32) | AB32: =SUMIFS('Committments Dump'!$S:$S,'Committments Dump'!$C:$C,'Category Table'!AB$2,'Committments Dump'!$B:$B,'Category Table'!$A32) | AC32: =SUMIFS('Committments Dump'!$S:$S,'Committments Dump'!$C:$C,'Category Table'!AC$2,'Committments Dump'!$B:$B,'Category Table'!$A32) | AD32: =U32+X32+AA32 | AE32: =V32+Y32+AB32 | AF32: =W32+Z32+AC32 | AG32: =R32+AD32 | AH32: =S32+AE32 | AI32: =T32+AF32 | AM32: =(O32-AG32)+AJ32 | AN32: =(P32-AH32)+AK32 | AO32: =(Q32-AI32)+AL32 | AP32: =IF(AM32>0, "Under",IF(AM32<0,"Over","")) | AQ32: =IF(AN32>0, "Under",IF(AN32<0,"Over","")) | AR32: =IF(AO32>0, "Under",IF(AO32<0,"Over",""))
A33: 0-4301 | B33: 0-4301-Pile Layout | C33: 0 | D33: 0 | E33: 0 | F33: 0 | G33: 0 | H33: 0 | I33: 0 | J33: 0 | K33: 0 | L33: 0 | M33: 0 | N33: 0 | O33: =L33+I33+F33+C33 | P33: =M33+J33+G33+D33 | Q33: =N33+K33+H33+E33 | R33: =SUMIFS('PO Log'!$E:$E,'PO Log'!$D:$D,'Category Table'!R$2,'PO Log'!$C:$C,'Category Table'!$A33) | S33: =SUMIFS('PO Log'!$E:$E,'PO Log'!$D:$D,'Category Table'!S$2,'PO Log'!$C:$C,'Category Table'!$A33) | T33: =SUMIFS('PO Log'!$E:$E,'PO Log'!$D:$D,'Category Table'!T$2,'PO Log'!$C:$C,'Category Table'!$A33) | U33: =SUMIFS('Committments Dump'!$Q:$Q,'Committments Dump'!$C:$C,'Category Table'!U$2,'Committments Dump'!$B:$B,'Category Table'!$A33) | V33: =SUMIFS('Committments Dump'!$Q:$Q,'Committments Dump'!$C:$C,'Category Table'!V$2,'Committments Dump'!$B:$B,'Category Table'!$A33) | W33: =SUMIFS('Committments Dump'!$Q:$Q,'Committments Dump'!$C:$C,'Category Table'!W$2,'Committments Dump'!$B:$B,'Category Table'!$A33) | X33: =SUMIFS('Committments Dump'!$R:$R,'Committments Dump'!$C:$C,'Category Table'!X$2,'Committments Dump'!$B:$B,'Category Table'!$A33) | Y33: =SUMIFS('Committments Dump'!$R:$R,'Committments Dump'!$C:$C,'Category Table'!Y$2,'Committments Dump'!$B:$B,'Category Table'!$A33) | Z33: =SUMIFS('Committments Dump'!$R:$R,'Committments Dump'!$C:$C,'Category Table'!Z$2,'Committments Dump'!$B:$B,'Category Table'!$A33) | AA33: =SUMIFS('Committments Dump'!$S:$S,'Committments Dump'!$C:$C,'Category Table'!AA$2,'Committments Dump'!$B:$B,'Category Table'!$A33) | AB33: =SUMIFS('Committments Dump'!$S:$S,'Committments Dump'!$C:$C,'Category Table'!AB$2,'Committments Dump'!$B:$B,'Category Table'!$A33) | AC33: =SUMIFS('Committments Dump'!$S:$S,'Committments Dump'!$C:$C,'Category Table'!AC$2,'Committments Dump'!$B:$B,'Category Table'!$A33) | AD33: =U33+X33+AA33 | AE33: =V33+Y33+AB33 | AF33: =W33+Z33+AC33 | AG33: =R33+AD33 | AH33: =S33+AE33 | AI33: =T33+AF33 | AM33: =(O33-AG33)+AJ33 | AN33: =(P33-AH33)+AK33 | AO33: =(Q33-AI33)+AL33 | AP33: =IF(AM33>0, "Under",IF(AM33<0,"Over","")) | AQ33: =IF(AN33>0, "Under",IF(AN33<0,"Over","")) | AR33: =IF(AO33>0, "Under",IF(AO33<0,"Over",""))
A34: 0-4302 | B34: 0-4302-Pile Installs | C34: 0 | D34: 0 | E34: 0 | F34: 0 | G34: 0 | H34: 114488.16 | I34: 0 | J34: 0 | K34: 0 | L34: 0 | M34: 0 | N34: 0 | O34: =L34+I34+F34+C34 | P34: =M34+J34+G34+D34 | Q34: =N34+K34+H34+E34 | R34: =SUMIFS('PO Log'!$E:$E,'PO Log'!$D:$D,'Category Table'!R$2,'PO Log'!$C:$C,'Category Table'!$A34) | S34: =SUMIFS('PO Log'!$E:$E,'PO Log'!$D:$D,'Category Table'!S$2,'PO Log'!$C:$C,'Category Table'!$A34) | T34: =SUMIFS('PO Log'!$E:$E,'PO Log'!$D:$D,'Category Table'!T$2,'PO Log'!$C:$C,'Category Table'!$A34) | U34: =SUMIFS('Committments Dump'!$Q:$Q,'Committments Dump'!$C:$C,'Category Table'!U$2,'Committments Dump'!$B:$B,'Category Table'!$A34) | V34: =SUMIFS('Committments Dump'!$Q:$Q,'Committments Dump'!$C:$C,'Category Table'!V$2,'Committments Dump'!$B:$B,'Category Table'!$A34) | W34: =SUMIFS('Committments Dump'!$Q:$Q,'Committments Dump'!$C:$C,'Category Table'!W$2,'Committments Dump'!$B:$B,'Category Table'!$A34) | X34: =SUMIFS('Committments Dump'!$R:$R,'Committments Dump'!$C:$C,'Category Table'!X$2,'Committments Dump'!$B:$B,'Category Table'!$A34) | Y34: =SUMIFS('Committments Dump'!$R:$R,'Committments Dump'!$C:$C,'Category Table'!Y$2,'Committments Dump'!$B:$B,'Category Table'!$A34) | Z34: =SUMIFS('Committments Dump'!$R:$R,'Committments Dump'!$C:$C,'Category Table'!Z$2,'Committments Dump'!$B:$B,'Category Table'!$A34) | AA34: =SUMIFS('Committments Dump'!$S:$S,'Committments Dump'!$C:$C,'Category Table'!AA$2,'Committments Dump'!$B:$B,'Category Table'!$A34) | AB34: =SUMIFS('Committments Dump'!$S:$S,'Committments Dump'!$C:$C,'Category Table'!AB$2,'Committments Dump'!$B:$B,'Category Table'!$A34) | AC34: =SUMIFS('Committments Dump'!$S:$S,'Committments Dump'!$C:$C,'Category Table'!AC$2,'Committments Dump'!$B:$B,'Category Table'!$A34) | AD34: =U34+X34+AA34 | AE34: =V34+Y34+AB34 | AF34: =W34+Z34+AC34 | AG34: =R34+AD34 | AH34: =S34+AE34 | AI34: =T34+AF34 | AM34: =(O34-AG34)+AJ34 | AN34: =(P34-AH34)+AK34 | AO34: =(Q34-AI34)+AL34 | AP34: =IF(AM34>0, "Under",IF(AM34<0,"Over","")) | AQ34: =IF(AN34>0, "Under",IF(AN34<0,"Over","")) | AR34: =IF(AO34>0, "Under",IF(AO34<0,"Over",""))
A35: 0-4303 | B35: 0-4303-Pile QAQC | C35: 0 | D35: 0 | E35: 0 | F35: 0 | H35: 0 | I35: 0 | J35: 0 | K35: 0 | L35: 0 | M35: 0 | N35: 0 | O35: =L35+I35+F35+C35 | P35: =M35+J35+G35+D35 | Q35: =N35+K35+H35+E35 | R35: =SUMIFS('PO Log'!$E:$E,'PO Log'!$D:$D,'Category Table'!R$2,'PO Log'!$C:$C,'Category Table'!$A35) | S35: =SUMIFS('PO Log'!$E:$E,'PO Log'!$D:$D,'Category Table'!S$2,'PO Log'!$C:$C,'Category Table'!$A35) | T35: =SUMIFS('PO Log'!$E:$E,'PO Log'!$D:$D,'Category Table'!T$2,'PO Log'!$C:$C,'Category Table'!$A35) | U35: =SUMIFS('Committments Dump'!$Q:$Q,'Committments Dump'!$C:$C,'Category Table'!U$2,'Committments Dump'!$B:$B,'Category Table'!$A35) | V35: =SUMIFS('Committments Dump'!$Q:$Q,'Committments Dump'!$C:$C,'Category Table'!V$2,'Committments Dump'!$B:$B,'Category Table'!$A35) | W35: =SUMIFS('Committments Dump'!$Q:$Q,'Committments Dump'!$C:$C,'Category Table'!W$2,'Committments Dump'!$B:$B,'Category Table'!$A35) | X35: =SUMIFS('Committments Dump'!$R:$R,'Committments Dump'!$C:$C,'Category Table'!X$2,'Committments Dump'!$B:$B,'Category Table'!$A35) | Y35: =SUMIFS('Committments Dump'!$R:$R,'Committments Dump'!$C:$C,'Category Table'!Y$2,'Committments Dump'!$B:$B,'Category Table'!$A35) | Z35: =SUMIFS('Committments Dump'!$R:$R,'Committments Dump'!$C:$C,'Category Table'!Z$2,'Committments Dump'!$B:$B,'Category Table'!$A35) | AA35: =SUMIFS('Committments Dump'!$S:$S,'Committments Dump'!$C:$C,'Category Table'!AA$2,'Committments Dump'!$B:$B,'Category Table'!$A35) | AB35: =SUMIFS('Committments Dump'!$S:$S,'Committments Dump'!$C:$C,'Category Table'!AB$2,'Committments Dump'!$B:$B,'Category Table'!$A35) | AC35: =SUMIFS('Committments Dump'!$S:$S,'Committments Dump'!$C:$C,'Category Table'!AC$2,'Committments Dump'!$B:$B,'Category Table'!$A35) | AD35: =U35+X35+AA35 | AE35: =V35+Y35+AB35 | AF35: =W35+Z35+AC35 | AG35: =R35+AD35 | AH35: =S35+AE35 | AI35: =T35+AF35 | AM35: =(O35-AG35)+AJ35 | AN35: =(P35-AH35)+AK35 | AO35: =(Q35-AI35)+AL35 | AP35: =IF(AM35>0, "Under",IF(AM35<0,"Over","")) | AQ35: =IF(AN35>0, "Under",IF(AN35<0,"Over","")) | AR35: =IF(AO35>0, "Under",IF(AO35<0,"Over",""))
A36: 0-4304 | B36: 0-4304-Racking Layout | C36: 0 | D36: 0 | E36: 0 | F36: 0 | H36: 0 | I36: 0 | J36: 0 | K36: 0 | L36: 0 | M36: 0 | N36: 0 | O36: =L36+I36+F36+C36 | P36: =M36+J36+G36+D36 | Q36: =N36+K36+H36+E36 | R36: =SUMIFS('PO Log'!$E:$E,'PO Log'!$D:$D,'Category Table'!R$2,'PO Log'!$C:$C,'Category Table'!$A36) | S36: =SUMIFS('PO Log'!$E:$E,'PO Log'!$D:$D,'Category Table'!S$2,'PO Log'!$C:$C,'Category Table'!$A36) | T36: =SUMIFS('PO Log'!$E:$E,'PO Log'!$D:$D,'Category Table'!T$2,'PO Log'!$C:$C,'Category Table'!$A36) | U36: =SUMIFS('Committments Dump'!$Q:$Q,'Committments Dump'!$C:$C,'Category Table'!U$2,'Committments Dump'!$B:$B,'Category Table'!$A36) | V36: =SUMIFS('Committments Dump'!$Q:$Q,'Committments Dump'!$C:$C,'Category Table'!V$2,'Committments Dump'!$B:$B,'Category Table'!$A36) | W36: =SUMIFS('Committments Dump'!$Q:$Q,'Committments Dump'!$C:$C,'Category Table'!W$2,'Committments Dump'!$B:$B,'Category Table'!$A36) | X36: =SUMIFS('Committments Dump'!$R:$R,'Committments Dump'!$C:$C,'Category Table'!X$2,'Committments Dump'!$B:$B,'Category Table'!$A36) | Y36: =SUMIFS('Committments Dump'!$R:$R,'Committments Dump'!$C:$C,'Category Table'!Y$2,'Committments Dump'!$B:$B,'Category Table'!$A36) | Z36: =SUMIFS('Committments Dump'!$R:$R,'Committments Dump'!$C:$C,'Category Table'!Z$2,'Committments Dump'!$B:$B,'Category Table'!$A36) | AA36: =SUMIFS('Committments Dump'!$S:$S,'Committments Dump'!$C:$C,'Category Table'!AA$2,'Committments Dump'!$B:$B,'Category Table'!$A36) | AB36: =SUMIFS('Committments Dump'!$S:$S,'Committments Dump'!$C:$C,'Category Table'!AB$2,'Committments Dump'!$B:$B,'Category Table'!$A36) | AC36: =SUMIFS('Committments Dump'!$S:$S,'Committments Dump'!$C:$C,'Category Table'!AC$2,'Committments Dump'!$B:$B,'Category Table'!$A36) | AD36: =U36+X36+AA36 | AE36: =V36+Y36+AB36 | AF36: =W36+Z36+AC36 | AG36: =R36+AD36 | AH36: =S36+AE36 | AI36: =T36+AF36 | AM36: =(O36-AG36)+AJ36 | AN36: =(P36-AH36)+AK36 | AO36: =(Q36-AI36)+AL36 | AP36: =IF(AM36>0, "Under",IF(AM36<0,"Over","")) | AQ36: =IF(AN36>0, "Under",IF(AN36<0,"Over","")) | AR36: =IF(AO36>0, "Under",IF(AO36<0,"Over",""))
A37: 0-4305 | B37: 0-4305-Racking Install | C37: 0 | D37: 0 | E37: 0 | F37: 0 | H37: 0 | I37: 0 | J37: 0 | K37: 0 | L37: 0 | M37: 0 | N37: 0 | O37: =L37+I37+F37+C37 | P37: =M37+J37+G37+D37 | Q37: =N37+K37+H37+E37 | R37: =SUMIFS('PO Log'!$E:$E,'PO Log'!$D:$D,'Category Table'!R$2,'PO Log'!$C:$C,'Category Table'!$A37) | S37: =SUMIFS('PO Log'!$E:$E,'PO Log'!$D:$D,'Category Table'!S$2,'PO Log'!$C:$C,'Category Table'!$A37) | T37: =SUMIFS('PO Log'!$E:$E,'PO Log'!$D:$D,'Category Table'!T$2,'PO Log'!$C:$C,'Category Table'!$A37) | U37: =SUMIFS('Committments Dump'!$Q:$Q,'Committments Dump'!$C:$C,'Category Table'!U$2,'Committments Dump'!$B:$B,'Category Table'!$A37) | V37: =SUMIFS('Committments Dump'!$Q:$Q,'Committments Dump'!$C:$C,'Category Table'!V$2,'Committments Dump'!$B:$B,'Category Table'!$A37) | W37: =SUMIFS('Committments Dump'!$Q:$Q,'Committments Dump'!$C:$C,'Category Table'!W$2,'Committments Dump'!$B:$B,'Category Table'!$A37) | X37: =SUMIFS('Committments Dump'!$R:$R,'Committments Dump'!$C:$C,'Category Table'!X$2,'Committments Dump'!$B:$B,'Category Table'!$A37) | Y37: =SUMIFS('Committments Dump'!$R:$R,'Committments Dump'!$C:$C,'Category Table'!Y$2,'Committments Dump'!$B:$B,'Category Table'!$A37) | Z37: =SUMIFS('Committments Dump'!$R:$R,'Committments Dump'!$C:$C,'Category Table'!Z$2,'Committments Dump'!$B:$B,'Category Table'!$A37) | AA37: =SUMIFS('Committments Dump'!$S:$S,'Committments Dump'!$C:$C,'Category Table'!AA$2,'Committments Dump'!$B:$B,'Category Table'!$A37) | AB37: =SUMIFS('Committments Dump'!$S:$S,'Committments Dump'!$C:$C,'Category Table'!AB$2,'Committments Dump'!$B:$B,'Category Table'!$A37) | AC37: =SUMIFS('Committments Dump'!$S:$S,'Committments Dump'!$C:$C,'Category Table'!AC$2,'Committments Dump'!$B:$B,'Category Table'!$A37) | AD37: =U37+X37+AA37 | AE37: =V37+Y37+AB37 | AF37: =W37+Z37+AC37 | AG37: =R37+AD37 | AH37: =S37+AE37 | AI37: =T37+AF37 | AM37: =(O37-AG37)+AJ37 | AN37: =(P37-AH37)+AK37 | AO37: =(Q37-AI37)+AL37 | AP37: =IF(AM37>0, "Under",IF(AM37<0,"Over","")) | AQ37: =IF(AN37>0, "Under",IF(AN37<0,"Over","")) | AR37: =IF(AO37>0, "Under",IF(AO37<0,"Over",""))
A38: 0-4306 | B38: 0-4306-Racking QAQC | C38: 0 | D38: 0 | E38: 0 | F38: 0 | G38: 0 | H38: 0 | I38: 0 | J38: 0 | K38: 0 | L38: 0 | M38: 0 | N38: 0 | O38: =L38+I38+F38+C38 | P38: =M38+J38+G38+D38 | Q38: =N38+K38+H38+E38 | R38: =SUMIFS('PO Log'!$E:$E,'PO Log'!$D:$D,'Category Table'!R$2,'PO Log'!$C:$C,'Category Table'!$A38) | S38: =SUMIFS('PO Log'!$E:$E,'PO Log'!$D:$D,'Category Table'!S$2,'PO Log'!$C:$C,'Category Table'!$A38) | T38: =SUMIFS('PO Log'!$E:$E,'PO Log'!$D:$D,'Category Table'!T$2,'PO Log'!$C:$C,'Category Table'!$A38) | U38: =SUMIFS('Committments Dump'!$Q:$Q,'Committments Dump'!$C:$C,'Category Table'!U$2,'Committments Dump'!$B:$B,'Category Table'!$A38) | V38: =SUMIFS('Committments Dump'!$Q:$Q,'Committments Dump'!$C:$C,'Category Table'!V$2,'Committments Dump'!$B:$B,'Category Table'!$A38) | W38: =SUMIFS('Committments Dump'!$Q:$Q,'Committments Dump'!$C:$C,'Category Table'!W$2,'Committments Dump'!$B:$B,'Category Table'!$A38) | X38: =SUMIFS('Committments Dump'!$R:$R,'Committments Dump'!$C:$C,'Category Table'!X$2,'Committments Dump'!$B:$B,'Category Table'!$A38) | Y38: =SUMIFS('Committments Dump'!$R:$R,'Committments Dump'!$C:$C,'Category Table'!Y$2,'Committments Dump'!$B:$B,'Category Table'!$A38) | Z38: =SUMIFS('Committments Dump'!$R:$R,'Committments Dump'!$C:$C,'Category Table'!Z$2,'Committments Dump'!$B:$B,'Category Table'!$A38) | AA38: =SUMIFS('Committments Dump'!$S:$S,'Committments Dump'!$C:$C,'Category Table'!AA$2,'Committments Dump'!$B:$B,'Category Table'!$A38) | AB38: =SUMIFS('Committments Dump'!$S:$S,'Committments Dump'!$C:$C,'Category Table'!AB$2,'Committments Dump'!$B:$B,'Category Table'!$A38) | AC38: =SUMIFS('Committments Dump'!$S:$S,'Committments Dump'!$C:$C,'Category Table'!AC$2,'Committments Dump'!$B:$B,'Category Table'!$A38) | AD38: =U38+X38+AA38 | AE38: =V38+Y38+AB38 | AF38: =W38+Z38+AC38 | AG38: =R38+AD38 | AH38: =S38+AE38 | AI38: =T38+AF38 | AM38: =(O38-AG38)+AJ38 | AN38: =(P38-AH38)+AK38 | AO38: =(Q38-AI38)+AL38 | AP38: =IF(AM38>0, "Under",IF(AM38<0,"Over","")) | AQ38: =IF(AN38>0, "Under",IF(AN38<0,"Over","")) | AR38: =IF(AO38>0, "Under",IF(AO38<0,"Over",""))
A39: 0-4307 | B39: 0-4307-Modules Layout | C39: 0 | D39: 0 | E39: 0 | F39: 0 | H39: 0 | I39: 0 | J39: 0 | K39: 0 | L39: 0 | M39: 0 | N39: 0 | O39: =L39+I39+F39+C39 | P39: =M39+J39+G39+D39 | Q39: =N39+K39+H39+E39 | R39: =SUMIFS('PO Log'!$E:$E,'PO Log'!$D:$D,'Category Table'!R$2,'PO Log'!$C:$C,'Category Table'!$A39) | S39: =SUMIFS('PO Log'!$E:$E,'PO Log'!$D:$D,'Category Table'!S$2,'PO Log'!$C:$C,'Category Table'!$A39) | T39: =SUMIFS('PO Log'!$E:$E,'PO Log'!$D:$D,'Category Table'!T$2,'PO Log'!$C:$C,'Category Table'!$A39) | U39: =SUMIFS('Committments Dump'!$Q:$Q,'Committments Dump'!$C:$C,'Category Table'!U$2,'Committments Dump'!$B:$B,'Category Table'!$A39) | V39: =SUMIFS('Committments Dump'!$Q:$Q,'Committments Dump'!$C:$C,'Category Table'!V$2,'Committments Dump'!$B:$B,'Category Table'!$A39) | W39: =SUMIFS('Committments Dump'!$Q:$Q,'Committments Dump'!$C:$C,'Category Table'!W$2,'Committments Dump'!$B:$B,'Category Table'!$A39) | X39: =SUMIFS('Committments Dump'!$R:$R,'Committments Dump'!$C:$C,'Category Table'!X$2,'Committments Dump'!$B:$B,'Category Table'!$A39) | Y39: =SUMIFS('Committments Dump'!$R:$R,'Committments Dump'!$C:$C,'Category Table'!Y$2,'Committments Dump'!$B:$B,'Category Table'!$A39) | Z39: =SUMIFS('Committments Dump'!$R:$R,'Committments Dump'!$C:$C,'Category Table'!Z$2,'Committments Dump'!$B:$B,'Category Table'!$A39) | AA39: =SUMIFS('Committments Dump'!$S:$S,'Committments Dump'!$C:$C,'Category Table'!AA$2,'Committments Dump'!$B:$B,'Category Table'!$A39) | AB39: =SUMIFS('Committments Dump'!$S:$S,'Committments Dump'!$C:$C,'Category Table'!AB$2,'Committments Dump'!$B:$B,'Category Table'!$A39) | AC39: =SUMIFS('Committments Dump'!$S:$S,'Committments Dump'!$C:$C,'Category Table'!AC$2,'Committments Dump'!$B:$B,'Category Table'!$A39) | AD39: =U39+X39+AA39 | AE39: =V39+Y39+AB39 | AF39: =W39+Z39+AC39 | AG39: =R39+AD39 | AH39: =S39+AE39 | AI39: =T39+AF39 | AM39: =(O39-AG39)+AJ39 | AN39: =(P39-AH39)+AK39 | AO39: =(Q39-AI39)+AL39 | AP39: =IF(AM39>0, "Under",IF(AM39<0,"Over","")) | AQ39: =IF(AN39>0, "Under",IF(AN39<0,"Over","")) | AR39: =IF(AO39>0, "Under",IF(AO39<0,"Over",""))
A40: 0-4308 | B40: 0-4308-Modules Install | C40: 0 | D40: 0 | E40: 0 | F40: 0 | H40: 0 | I40: 0 | J40: 0 | K40: 0 | L40: 0 | M40: 0 | N40: 0 | O40: =L40+I40+F40+C40 | P40: =M40+J40+G40+D40 | Q40: =N40+K40+H40+E40 | R40: =SUMIFS('PO Log'!$E:$E,'PO Log'!$D:$D,'Category Table'!R$2,'PO Log'!$C:$C,'Category Table'!$A40) | S40: =SUMIFS('PO Log'!$E:$E,'PO Log'!$D:$D,'Category Table'!S$2,'PO Log'!$C:$C,'Category Table'!$A40) | T40: =SUMIFS('PO Log'!$E:$E,'PO Log'!$D:$D,'Category Table'!T$2,'PO Log'!$C:$C,'Category Table'!$A40) | U40: =SUMIFS('Committments Dump'!$Q:$Q,'Committments Dump'!$C:$C,'Category Table'!U$2,'Committments Dump'!$B:$B,'Category Table'!$A40) | V40: =SUMIFS('Committments Dump'!$Q:$Q,'Committments Dump'!$C:$C,'Category Table'!V$2,'Committments Dump'!$B:$B,'Category Table'!$A40) | W40: =SUMIFS('Committments Dump'!$Q:$Q,'Committments Dump'!$C:$C,'Category Table'!W$2,'Committments Dump'!$B:$B,'Category Table'!$A40) | X40: =SUMIFS('Committments Dump'!$R:$R,'Committments Dump'!$C:$C,'Category Table'!X$2,'Committments Dump'!$B:$B,'Category Table'!$A40) | Y40: =SUMIFS('Committments Dump'!$R:$R,'Committments Dump'!$C:$C,'Category Table'!Y$2,'Committments Dump'!$B:$B,'Category Table'!$A40) | Z40: =SUMIFS('Committments Dump'!$R:$R,'Committments Dump'!$C:$C,'Category Table'!Z$2,'Committments Dump'!$B:$B,'Category Table'!$A40) | AA40: =SUMIFS('Committments Dump'!$S:$S,'Committments Dump'!$C:$C,'Category Table'!AA$2,'Committments Dump'!$B:$B,'Category Table'!$A40) | AB40: =SUMIFS('Committments Dump'!$S:$S,'Committments Dump'!$C:$C,'Category Table'!AB$2,'Committments Dump'!$B:$B,'Category Table'!$A40) | AC40: =SUMIFS('Committments Dump'!$S:$S,'Committments Dump'!$C:$C,'Category Table'!AC$2,'Committments Dump'!$B:$B,'Category Table'!$A40) | AD40: =U40+X40+AA40 | AE40: =V40+Y40+AB40 | AF40: =W40+Z40+AC40 | AG40: =R40+AD40 | AH40: =S40+AE40 | AI40: =T40+AF40 | AM40: =(O40-AG40)+AJ40 | AN40: =(P40-AH40)+AK40 | AO40: =(Q40-AI40)+AL40 | AP40: =IF(AM40>0, "Under",IF(AM40<0,"Over","")) | AQ40: =IF(AN40>0, "Under",IF(AN40<0,"Over","")) | AR40: =IF(AO40>0, "Under",IF(AO40<0,"Over",""))
A41: 0-4309 | B41: 0-4309-Modules QAQC | C41: 0 | D41: 0 | E41: 0 | F41: 0 | H41: 0 | I41: 0 | J41: 0 | K41: 0 | L41: 0 | M41: 0 | N41: 0 | O41: =L41+I41+F41+C41 | P41: =M41+J41+G41+D41 | Q41: =N41+K41+H41+E41 | R41: =SUMIFS('PO Log'!$E:$E,'PO Log'!$D:$D,'Category Table'!R$2,'PO Log'!$C:$C,'Category Table'!$A41) | S41: =SUMIFS('PO Log'!$E:$E,'PO Log'!$D:$D,'Category Table'!S$2,'PO Log'!$C:$C,'Category Table'!$A41) | T41: =SUMIFS('PO Log'!$E:$E,'PO Log'!$D:$D,'Category Table'!T$2,'PO Log'!$C:$C,'Category Table'!$A41) | U41: =SUMIFS('Committments Dump'!$Q:$Q,'Committments Dump'!$C:$C,'Category Table'!U$2,'Committments Dump'!$B:$B,'Category Table'!$A41) | V41: =SUMIFS('Committments Dump'!$Q:$Q,'Committments Dump'!$C:$C,'Category Table'!V$2,'Committments Dump'!$B:$B,'Category Table'!$A41) | W41: =SUMIFS('Committments Dump'!$Q:$Q,'Committments Dump'!$C:$C,'Category Table'!W$2,'Committments Dump'!$B:$B,'Category Table'!$A41) | X41: =SUMIFS('Committments Dump'!$R:$R,'Committments Dump'!$C:$C,'Category Table'!X$2,'Committments Dump'!$B:$B,'Category Table'!$A41) | Y41: =SUMIFS('Committments Dump'!$R:$R,'Committments Dump'!$C:$C,'Category Table'!Y$2,'Committments Dump'!$B:$B,'Category Table'!$A41) | Z41: =SUMIFS('Committments Dump'!$R:$R,'Committments Dump'!$C:$C,'Category Table'!Z$2,'Committments Dump'!$B:$B,'Category Table'!$A41) | AA41: =SUMIFS('Committments Dump'!$S:$S,'Committments Dump'!$C:$C,'Category Table'!AA$2,'Committments Dump'!$B:$B,'Category Table'!$A41) | AB41: =SUMIFS('Committments Dump'!$S:$S,'Committments Dump'!$C:$C,'Category Table'!AB$2,'Committments Dump'!$B:$B,'Category Table'!$A41) | AC41: =SUMIFS('Committments Dump'!$S:$S,'Committments Dump'!$C:$C,'Category Table'!AC$2,'Committments Dump'!$B:$B,'Category Table'!$A41) | AD41: =U41+X41+AA41 | AE41: =V41+Y41+AB41 | AF41: =W41+Z41+AC41 | AG41: =R41+AD41 | AH41: =S41+AE41 | AI41: =T41+AF41 | AM41: =(O41-AG41)+AJ41 | AN41: =(P41-AH41)+AK41 | AO41: =(Q41-AI41)+AL41 | AP41: =IF(AM41>0, "Under",IF(AM41<0,"Over","")) | AQ41: =IF(AN41>0, "Under",IF(AN41<0,"Over","")) | AR41: =IF(AO41>0, "Under",IF(AO41<0,"Over",""))
A42: 0-4320 | B42: 0-4320-Mechanical Punch List | C42: 0 | D42: 0 | E42: 0 | F42: 0 | H42: 0 | I42: 0 | J42: 0 | K42: 0 | L42: 0 | M42: 0 | N42: 0 | O42: =L42+I42+F42+C42 | P42: =M42+J42+G42+D42 | Q42: =N42+K42+H42+E42 | R42: =SUMIFS('PO Log'!$E:$E,'PO Log'!$D:$D,'Category Table'!R$2,'PO Log'!$C:$C,'Category Table'!$A42) | S42: =SUMIFS('PO Log'!$E:$E,'PO Log'!$D:$D,'Category Table'!S$2,'PO Log'!$C:$C,'Category Table'!$A42) | T42: =SUMIFS('PO Log'!$E:$E,'PO Log'!$D:$D,'Category Table'!T$2,'PO Log'!$C:$C,'Category Table'!$A42) | U42: =SUMIFS('Committments Dump'!$Q:$Q,'Committments Dump'!$C:$C,'Category Table'!U$2,'Committments Dump'!$B:$B,'Category Table'!$A42) | V42: =SUMIFS('Committments Dump'!$Q:$Q,'Committments Dump'!$C:$C,'Category Table'!V$2,'Committments Dump'!$B:$B,'Category Table'!$A42) | W42: =SUMIFS('Committments Dump'!$Q:$Q,'Committments Dump'!$C:$C,'Category Table'!W$2,'Committments Dump'!$B:$B,'Category Table'!$A42) | X42: =SUMIFS('Committments Dump'!$R:$R,'Committments Dump'!$C:$C,'Category Table'!X$2,'Committments Dump'!$B:$B,'Category Table'!$A42) | Y42: =SUMIFS('Committments Dump'!$R:$R,'Committments Dump'!$C:$C,'Category Table'!Y$2,'Committments Dump'!$B:$B,'Category Table'!$A42) | Z42: =SUMIFS('Committments Dump'!$R:$R,'Committments Dump'!$C:$C,'Category Table'!Z$2,'Committments Dump'!$B:$B,'Category Table'!$A42) | AA42: =SUMIFS('Committments Dump'!$S:$S,'Committments Dump'!$C:$C,'Category Table'!AA$2,'Committments Dump'!$B:$B,'Category Table'!$A42) | AB42: =SUMIFS('Committments Dump'!$S:$S,'Committments Dump'!$C:$C,'Category Table'!AB$2,'Committments Dump'!$B:$B,'Category Table'!$A42) | AC42: =SUMIFS('Committments Dump'!$S:$S,'Committments Dump'!$C:$C,'Category Table'!AC$2,'Committments Dump'!$B:$B,'Category Table'!$A42) | AD42: =U42+X42+AA42 | AE42: =V42+Y42+AB42 | AF42: =W42+Z42+AC42 | AG42: =R42+AD42 | AH42: =S42+AE42 | AI42: =T42+AF42 | AM42: =(O42-AG42)+AJ42 | AN42: =(P42-AH42)+AK42 | AO42: =(Q42-AI42)+AL42 | AP42: =IF(AM42>0, "Under",IF(AM42<0,"Over","")) | AQ42: =IF(AN42>0, "Under",IF(AN42<0,"Over","")) | AR42: =IF(AO42>0, "Under",IF(AO42<0,"Over",""))
A43: 0-4400 | B43: 0-4400-Electrical Receiving | C43: 0 | D43: 0 | E43: 0 | F43: 0 | G43: 389.51133 | H43: 32475 | I43: 0 | J43: 0 | K43: 0 | L43: 0 | M43: 0 | N43: 0 | O43: =L43+I43+F43+C43 | P43: =M43+J43+G43+D43 | Q43: =N43+K43+H43+E43 | R43: =SUMIFS('PO Log'!$E:$E,'PO Log'!$D:$D,'Category Table'!R$2,'PO Log'!$C:$C,'Category Table'!$A43) | S43: =SUMIFS('PO Log'!$E:$E,'PO Log'!$D:$D,'Category Table'!S$2,'PO Log'!$C:$C,'Category Table'!$A43) | T43: =SUMIFS('PO Log'!$E:$E,'PO Log'!$D:$D,'Category Table'!T$2,'PO Log'!$C:$C,'Category Table'!$A43) | U43: =SUMIFS('Committments Dump'!$Q:$Q,'Committments Dump'!$C:$C,'Category Table'!U$2,'Committments Dump'!$B:$B,'Category Table'!$A43) | V43: =SUMIFS('Committments Dump'!$Q:$Q,'Committments Dump'!$C:$C,'Category Table'!V$2,'Committments Dump'!$B:$B,'Category Table'!$A43) | W43: =SUMIFS('Committments Dump'!$Q:$Q,'Committments Dump'!$C:$C,'Category Table'!W$2,'Committments Dump'!$B:$B,'Category Table'!$A43) | X43: =SUMIFS('Committments Dump'!$R:$R,'Committments Dump'!$C:$C,'Category Table'!X$2,'Committments Dump'!$B:$B,'Category Table'!$A43) | Y43: =SUMIFS('Committments Dump'!$R:$R,'Committments Dump'!$C:$C,'Category Table'!Y$2,'Committments Dump'!$B:$B,'Category Table'!$A43) | Z43: =SUMIFS('Committments Dump'!$R:$R,'Committments Dump'!$C:$C,'Category Table'!Z$2,'Committments Dump'!$B:$B,'Category Table'!$A43) | AA43: =SUMIFS('Committments Dump'!$S:$S,'Committments Dump'!$C:$C,'Category Table'!AA$2,'Committments Dump'!$B:$B,'Category Table'!$A43) | AB43: =SUMIFS('Committments Dump'!$S:$S,'Committments Dump'!$C:$C,'Category Table'!AB$2,'Committments Dump'!$B:$B,'Category Table'!$A43) | AC43: =SUMIFS('Committments Dump'!$S:$S,'Committments Dump'!$C:$C,'Category Table'!AC$2,'Committments Dump'!$B:$B,'Category Table'!$A43) | AD43: =U43+X43+AA43 | AE43: =V43+Y43+AB43 | AF43: =W43+Z43+AC43 | AG43: =R43+AD43 | AH43: =S43+AE43 | AI43: =T43+AF43 | AM43: =(O43-AG43)+AJ43 | AN43: =(P43-AH43)+AK43 | AO43: =(Q43-AI43)+AL43 | AP43: =IF(AM43>0, "Under",IF(AM43<0,"Over","")) | AQ43: =IF(AN43>0, "Under",IF(AN43<0,"Over","")) | AR43: =IF(AO43>0, "Under",IF(AO43<0,"Over",""))
A44: 0-4401 | B44: 0-4401-DC Trenching & Boring | C44: 0 | D44: 0 | E44: 0 | F44: 0 | G44: 0 | H44: 0 | I44: 0 | J44: 0 | K44: 0 | L44: 0 | M44: 0 | N44: 0 | O44: =L44+I44+F44+C44 | P44: =M44+J44+G44+D44 | Q44: =N44+K44+H44+E44 | R44: =SUMIFS('PO Log'!$E:$E,'PO Log'!$D:$D,'Category Table'!R$2,'PO Log'!$C:$C,'Category Table'!$A44) | S44: =SUMIFS('PO Log'!$E:$E,'PO Log'!$D:$D,'Category Table'!S$2,'PO Log'!$C:$C,'Category Table'!$A44) | T44: =SUMIFS('PO Log'!$E:$E,'PO Log'!$D:$D,'Category Table'!T$2,'PO Log'!$C:$C,'Category Table'!$A44) | U44: =SUMIFS('Committments Dump'!$Q:$Q,'Committments Dump'!$C:$C,'Category Table'!U$2,'Committments Dump'!$B:$B,'Category Table'!$A44) | V44: =SUMIFS('Committments Dump'!$Q:$Q,'Committments Dump'!$C:$C,'Category Table'!V$2,'Committments Dump'!$B:$B,'Category Table'!$A44) | W44: =SUMIFS('Committments Dump'!$Q:$Q,'Committments Dump'!$C:$C,'Category Table'!W$2,'Committments Dump'!$B:$B,'Category Table'!$A44) | X44: =SUMIFS('Committments Dump'!$R:$R,'Committments Dump'!$C:$C,'Category Table'!X$2,'Committments Dump'!$B:$B,'Category Table'!$A44) | Y44: =SUMIFS('Committments Dump'!$R:$R,'Committments Dump'!$C:$C,'Category Table'!Y$2,'Committments Dump'!$B:$B,'Category Table'!$A44) | Z44: =SUMIFS('Committments Dump'!$R:$R,'Committments Dump'!$C:$C,'Category Table'!Z$2,'Committments Dump'!$B:$B,'Category Table'!$A44) | AA44: =SUMIFS('Committments Dump'!$S:$S,'Committments Dump'!$C:$C,'Category Table'!AA$2,'Committments Dump'!$B:$B,'Category Table'!$A44) | AB44: =SUMIFS('Committments Dump'!$S:$S,'Committments Dump'!$C:$C,'Category Table'!AB$2,'Committments Dump'!$B:$B,'Category Table'!$A44) | AC44: =SUMIFS('Committments Dump'!$S:$S,'Committments Dump'!$C:$C,'Category Table'!AC$2,'Committments Dump'!$B:$B,'Category Table'!$A44) | AD44: =U44+X44+AA44 | AE44: =V44+Y44+AB44 | AF44: =W44+Z44+AC44 | AG44: =R44+AD44 | AH44: =S44+AE44 | AI44: =T44+AF44 | AM44: =(O44-AG44)+AJ44 | AN44: =(P44-AH44)+AK44 | AO44: =(Q44-AI44)+AL44 | AP44: =IF(AM44>0, "Under",IF(AM44<0,"Over","")) | AQ44: =IF(AN44>0, "Under",IF(AN44<0,"Over","")) | AR44: =IF(AO44>0, "Under",IF(AO44<0,"Over",""))
A45: 0-4402 | B45: 0-4402-Transitions Pre-Fab | C45: 0 | D45: 0 | E45: 0 | F45: 0 | G45: 0 | H45: 0 | I45: 0 | J45: 0 | K45: 0 | L45: 0 | M45: 0 | N45: 0 | O45: =L45+I45+F45+C45 | P45: =M45+J45+G45+D45 | Q45: =N45+K45+H45+E45 | R45: =SUMIFS('PO Log'!$E:$E,'PO Log'!$D:$D,'Category Table'!R$2,'PO Log'!$C:$C,'Category Table'!$A45) | S45: =SUMIFS('PO Log'!$E:$E,'PO Log'!$D:$D,'Category Table'!S$2,'PO Log'!$C:$C,'Category Table'!$A45) | T45: =SUMIFS('PO Log'!$E:$E,'PO Log'!$D:$D,'Category Table'!T$2,'PO Log'!$C:$C,'Category Table'!$A45) | U45: =SUMIFS('Committments Dump'!$Q:$Q,'Committments Dump'!$C:$C,'Category Table'!U$2,'Committments Dump'!$B:$B,'Category Table'!$A45) | V45: =SUMIFS('Committments Dump'!$Q:$Q,'Committments Dump'!$C:$C,'Category Table'!V$2,'Committments Dump'!$B:$B,'Category Table'!$A45) | W45: =SUMIFS('Committments Dump'!$Q:$Q,'Committments Dump'!$C:$C,'Category Table'!W$2,'Committments Dump'!$B:$B,'Category Table'!$A45) | X45: =SUMIFS('Committments Dump'!$R:$R,'Committments Dump'!$C:$C,'Category Table'!X$2,'Committments Dump'!$B:$B,'Category Table'!$A45) | Y45: =SUMIFS('Committments Dump'!$R:$R,'Committments Dump'!$C:$C,'Category Table'!Y$2,'Committments Dump'!$B:$B,'Category Table'!$A45) | Z45: =SUMIFS('Committments Dump'!$R:$R,'Committments Dump'!$C:$C,'Category Table'!Z$2,'Committments Dump'!$B:$B,'Category Table'!$A45) | AA45: =SUMIFS('Committments Dump'!$S:$S,'Committments Dump'!$C:$C,'Category Table'!AA$2,'Committments Dump'!$B:$B,'Category Table'!$A45) | AB45: =SUMIFS('Committments Dump'!$S:$S,'Committments Dump'!$C:$C,'Category Table'!AB$2,'Committments Dump'!$B:$B,'Category Table'!$A45) | AC45: =SUMIFS('Committments Dump'!$S:$S,'Committments Dump'!$C:$C,'Category Table'!AC$2,'Committments Dump'!$B:$B,'Category Table'!$A45) | AD45: =U45+X45+AA45 | AE45: =V45+Y45+AB45 | AF45: =W45+Z45+AC45 | AG45: =R45+AD45 | AH45: =S45+AE45 | AI45: =T45+AF45 | AM45: =(O45-AG45)+AJ45 | AN45: =(P45-AH45)+AK45 | AO45: =(Q45-AI45)+AL45 | AP45: =IF(AM45>0, "Under",IF(AM45<0,"Over","")) | AQ45: =IF(AN45>0, "Under",IF(AN45<0,"Over","")) | AR45: =IF(AO45>0, "Under",IF(AO45<0,"Over",""))
A46: 0-4403 | B46: 0-4403-DC Transitions Install | C46: 0 | D46: 0 | E46: 0 | F46: 0 | G46: 0 | H46: 0 | I46: 0 | J46: 0 | K46: 0 | L46: 0 | M46: 0 | N46: 0 | O46: =L46+I46+F46+C46 | P46: =M46+J46+G46+D46 | Q46: =N46+K46+H46+E46 | R46: =SUMIFS('PO Log'!$E:$E,'PO Log'!$D:$D,'Category Table'!R$2,'PO Log'!$C:$C,'Category Table'!$A46) | S46: =SUMIFS('PO Log'!$E:$E,'PO Log'!$D:$D,'Category Table'!S$2,'PO Log'!$C:$C,'Category Table'!$A46) | T46: =SUMIFS('PO Log'!$E:$E,'PO Log'!$D:$D,'Category Table'!T$2,'PO Log'!$C:$C,'Category Table'!$A46) | U46: =SUMIFS('Committments Dump'!$Q:$Q,'Committments Dump'!$C:$C,'Category Table'!U$2,'Committments Dump'!$B:$B,'Category Table'!$A46) | V46: =SUMIFS('Committments Dump'!$Q:$Q,'Committments Dump'!$C:$C,'Category Table'!V$2,'Committments Dump'!$B:$B,'Category Table'!$A46) | W46: =SUMIFS('Committments Dump'!$Q:$Q,'Committments Dump'!$C:$C,'Category Table'!W$2,'Committments Dump'!$B:$B,'Category Table'!$A46) | X46: =SUMIFS('Committments Dump'!$R:$R,'Committments Dump'!$C:$C,'Category Table'!X$2,'Committments Dump'!$B:$B,'Category Table'!$A46) | Y46: =SUMIFS('Committments Dump'!$R:$R,'Committments Dump'!$C:$C,'Category Table'!Y$2,'Committments Dump'!$B:$B,'Category Table'!$A46) | Z46: =SUMIFS('Committments Dump'!$R:$R,'Committments Dump'!$C:$C,'Category Table'!Z$2,'Committments Dump'!$B:$B,'Category Table'!$A46) | AA46: =SUMIFS('Committments Dump'!$S:$S,'Committments Dump'!$C:$C,'Category Table'!AA$2,'Committments Dump'!$B:$B,'Category Table'!$A46) | AB46: =SUMIFS('Committments Dump'!$S:$S,'Committments Dump'!$C:$C,'Category Table'!AB$2,'Committments Dump'!$B:$B,'Category Table'!$A46) | AC46: =SUMIFS('Committments Dump'!$S:$S,'Committments Dump'!$C:$C,'Category Table'!AC$2,'Committments Dump'!$B:$B,'Category Table'!$A46) | AD46: =U46+X46+AA46 | AE46: =V46+Y46+AB46 | AF46: =W46+Z46+AC46 | AG46: =R46+AD46 | AH46: =S46+AE46 | AI46: =T46+AF46 | AM46: =(O46-AG46)+AJ46 | AN46: =(P46-AH46)+AK46 | AO46: =(Q46-AI46)+AL46 | AP46: =IF(AM46>0, "Under",IF(AM46<0,"Over","")) | AQ46: =IF(AN46>0, "Under",IF(AN46<0,"Over","")) | AR46: =IF(AO46>0, "Under",IF(AO46<0,"Over",""))
A47: 0-4405 | B47: 0-4405-DC Homerun | C47: 0 | D47: 0 | E47: 0 | F47: 0 | G47: 0 | H47: 0 | I47: 0 | J47: 0 | K47: 0 | L47: 0 | M47: 0 | N47: 0 | O47: =L47+I47+F47+C47 | P47: =M47+J47+G47+D47 | Q47: =N47+K47+H47+E47 | R47: =SUMIFS('PO Log'!$E:$E,'PO Log'!$D:$D,'Category Table'!R$2,'PO Log'!$C:$C,'Category Table'!$A47) | S47: =SUMIFS('PO Log'!$E:$E,'PO Log'!$D:$D,'Category Table'!S$2,'PO Log'!$C:$C,'Category Table'!$A47) | T47: =SUMIFS('PO Log'!$E:$E,'PO Log'!$D:$D,'Category Table'!T$2,'PO Log'!$C:$C,'Category Table'!$A47) | U47: =SUMIFS('Committments Dump'!$Q:$Q,'Committments Dump'!$C:$C,'Category Table'!U$2,'Committments Dump'!$B:$B,'Category Table'!$A47) | V47: =SUMIFS('Committments Dump'!$Q:$Q,'Committments Dump'!$C:$C,'Category Table'!V$2,'Committments Dump'!$B:$B,'Category Table'!$A47) | W47: =SUMIFS('Committments Dump'!$Q:$Q,'Committments Dump'!$C:$C,'Category Table'!W$2,'Committments Dump'!$B:$B,'Category Table'!$A47) | X47: =SUMIFS('Committments Dump'!$R:$R,'Committments Dump'!$C:$C,'Category Table'!X$2,'Committments Dump'!$B:$B,'Category Table'!$A47) | Y47: =SUMIFS('Committments Dump'!$R:$R,'Committments Dump'!$C:$C,'Category Table'!Y$2,'Committments Dump'!$B:$B,'Category Table'!$A47) | Z47: =SUMIFS('Committments Dump'!$R:$R,'Committments Dump'!$C:$C,'Category Table'!Z$2,'Committments Dump'!$B:$B,'Category Table'!$A47) | AA47: =SUMIFS('Committments Dump'!$S:$S,'Committments Dump'!$C:$C,'Category Table'!AA$2,'Committments Dump'!$B:$B,'Category Table'!$A47) | AB47: =SUMIFS('Committments Dump'!$S:$S,'Committments Dump'!$C:$C,'Category Table'!AB$2,'Committments Dump'!$B:$B,'Category Table'!$A47) | AC47: =SUMIFS('Committments Dump'!$S:$S,'Committments Dump'!$C:$C,'Category Table'!AC$2,'Committments Dump'!$B:$B,'Category Table'!$A47) | AD47: =U47+X47+AA47 | AE47: =V47+Y47+AB47 | AF47: =W47+Z47+AC47 | AG47: =R47+AD47 | AH47: =S47+AE47 | AI47: =T47+AF47 | AM47: =(O47-AG47)+AJ47 | AN47: =(P47-AH47)+AK47 | AO47: =(Q47-AI47)+AL47 | AP47: =IF(AM47>0, "Under",IF(AM47<0,"Over","")) | AQ47: =IF(AN47>0, "Under",IF(AN47<0,"Over","")) | AR47: =IF(AO47>0, "Under",IF(AO47<0,"Over",""))
A48: 0-4407 | B48: 0-4407-Module Wiring | C48: 0 | D48: 0 | E48: 0 | F48: 0 | G48: 0 | H48: 0 | I48: 0 | J48: 0 | K48: 0 | L48: 0 | M48: 0 | N48: 0 | O48: =L48+I48+F48+C48 | P48: =M48+J48+G48+D48 | Q48: =N48+K48+H48+E48 | R48: =SUMIFS('PO Log'!$E:$E,'PO Log'!$D:$D,'Category Table'!R$2,'PO Log'!$C:$C,'Category Table'!$A48) | S48: =SUMIFS('PO Log'!$E:$E,'PO Log'!$D:$D,'Category Table'!S$2,'PO Log'!$C:$C,'Category Table'!$A48) | T48: =SUMIFS('PO Log'!$E:$E,'PO Log'!$D:$D,'Category Table'!T$2,'PO Log'!$C:$C,'Category Table'!$A48) | U48: =SUMIFS('Committments Dump'!$Q:$Q,'Committments Dump'!$C:$C,'Category Table'!U$2,'Committments Dump'!$B:$B,'Category Table'!$A48) | V48: =SUMIFS('Committments Dump'!$Q:$Q,'Committments Dump'!$C:$C,'Category Table'!V$2,'Committments Dump'!$B:$B,'Category Table'!$A48) | W48: =SUMIFS('Committments Dump'!$Q:$Q,'Committments Dump'!$C:$C,'Category Table'!W$2,'Committments Dump'!$B:$B,'Category Table'!$A48) | X48: =SUMIFS('Committments Dump'!$R:$R,'Committments Dump'!$C:$C,'Category Table'!X$2,'Committments Dump'!$B:$B,'Category Table'!$A48) | Y48: =SUMIFS('Committments Dump'!$R:$R,'Committments Dump'!$C:$C,'Category Table'!Y$2,'Committments Dump'!$B:$B,'Category Table'!$A48) | Z48: =SUMIFS('Committments Dump'!$R:$R,'Committments Dump'!$C:$C,'Category Table'!Z$2,'Committments Dump'!$B:$B,'Category Table'!$A48) | AA48: =SUMIFS('Committments Dump'!$S:$S,'Committments Dump'!$C:$C,'Category Table'!AA$2,'Committments Dump'!$B:$B,'Category Table'!$A48) | AB48: =SUMIFS('Committments Dump'!$S:$S,'Committments Dump'!$C:$C,'Category Table'!AB$2,'Committments Dump'!$B:$B,'Category Table'!$A48) | AC48: =SUMIFS('Committments Dump'!$S:$S,'Committments Dump'!$C:$C,'Category Table'!AC$2,'Committments Dump'!$B:$B,'Category Table'!$A48) | AD48: =U48+X48+AA48 | AE48: =V48+Y48+AB48 | AF48: =W48+Z48+AC48 | AG48: =R48+AD48 | AH48: =S48+AE48 | AI48: =T48+AF48 | AM48: =(O48-AG48)+AJ48 | AN48: =(P48-AH48)+AK48 | AO48: =(Q48-AI48)+AL48 | AP48: =IF(AM48>0, "Under",IF(AM48<0,"Over","")) | AQ48: =IF(AN48>0, "Under",IF(AN48<0,"Over","")) | AR48: =IF(AO48>0, "Under",IF(AO48<0,"Over",""))
A49: 0-4408 | B49: 0-4408-Harness Install | C49: 0 | D49: 0 | E49: 0 | F49: 0 | G49: 0 | H49: 0 | I49: 0 | J49: 0 | K49: 0 | L49: 0 | M49: 0 | N49: 0 | O49: =L49+I49+F49+C49 | P49: =M49+J49+G49+D49 | Q49: =N49+K49+H49+E49 | R49: =SUMIFS('PO Log'!$E:$E,'PO Log'!$D:$D,'Category Table'!R$2,'PO Log'!$C:$C,'Category Table'!$A49) | S49: =SUMIFS('PO Log'!$E:$E,'PO Log'!$D:$D,'Category Table'!S$2,'PO Log'!$C:$C,'Category Table'!$A49) | T49: =SUMIFS('PO Log'!$E:$E,'PO Log'!$D:$D,'Category Table'!T$2,'PO Log'!$C:$C,'Category Table'!$A49) | U49: =SUMIFS('Committments Dump'!$Q:$Q,'Committments Dump'!$C:$C,'Category Table'!U$2,'Committments Dump'!$B:$B,'Category Table'!$A49) | V49: =SUMIFS('Committments Dump'!$Q:$Q,'Committments Dump'!$C:$C,'Category Table'!V$2,'Committments Dump'!$B:$B,'Category Table'!$A49) | W49: =SUMIFS('Committments Dump'!$Q:$Q,'Committments Dump'!$C:$C,'Category Table'!W$2,'Committments Dump'!$B:$B,'Category Table'!$A49) | X49: =SUMIFS('Committments Dump'!$R:$R,'Committments Dump'!$C:$C,'Category Table'!X$2,'Committments Dump'!$B:$B,'Category Table'!$A49) | Y49: =SUMIFS('Committments Dump'!$R:$R,'Committments Dump'!$C:$C,'Category Table'!Y$2,'Committments Dump'!$B:$B,'Category Table'!$A49) | Z49: =SUMIFS('Committments Dump'!$R:$R,'Committments Dump'!$C:$C,'Category Table'!Z$2,'Committments Dump'!$B:$B,'Category Table'!$A49) | AA49: =SUMIFS('Committments Dump'!$S:$S,'Committments Dump'!$C:$C,'Category Table'!AA$2,'Committments Dump'!$B:$B,'Category Table'!$A49) | AB49: =SUMIFS('Committments Dump'!$S:$S,'Committments Dump'!$C:$C,'Category Table'!AB$2,'Committments Dump'!$B:$B,'Category Table'!$A49) | AC49: =SUMIFS('Committments Dump'!$S:$S,'Committments Dump'!$C:$C,'Category Table'!AC$2,'Committments Dump'!$B:$B,'Category Table'!$A49) | AD49: =U49+X49+AA49 | AE49: =V49+Y49+AB49 | AF49: =W49+Z49+AC49 | AG49: =R49+AD49 | AH49: =S49+AE49 | AI49: =T49+AF49 | AM49: =(O49-AG49)+AJ49 | AN49: =(P49-AH49)+AK49 | AO49: =(Q49-AI49)+AL49 | AP49: =IF(AM49>0, "Under",IF(AM49<0,"Over","")) | AQ49: =IF(AN49>0, "Under",IF(AN49<0,"Over","")) | AR49: =IF(AO49>0, "Under",IF(AO49<0,"Over",""))
A50: 0-4410 | B50: 0-4410-DC Terminations | C50: 0 | D50: 0 | E50: 0 | F50: 0 | G50: 0 | H50: 0 | I50: 0 | J50: 0 | K50: 0 | L50: 0 | M50: 0 | N50: 0 | O50: =L50+I50+F50+C50 | P50: =M50+J50+G50+D50 | Q50: =N50+K50+H50+E50 | R50: =SUMIFS('PO Log'!$E:$E,'PO Log'!$D:$D,'Category Table'!R$2,'PO Log'!$C:$C,'Category Table'!$A50) | S50: =SUMIFS('PO Log'!$E:$E,'PO Log'!$D:$D,'Category Table'!S$2,'PO Log'!$C:$C,'Category Table'!$A50) | T50: =SUMIFS('PO Log'!$E:$E,'PO Log'!$D:$D,'Category Table'!T$2,'PO Log'!$C:$C,'Category Table'!$A50) | U50: =SUMIFS('Committments Dump'!$Q:$Q,'Committments Dump'!$C:$C,'Category Table'!U$2,'Committments Dump'!$B:$B,'Category Table'!$A50) | V50: =SUMIFS('Committments Dump'!$Q:$Q,'Committments Dump'!$C:$C,'Category Table'!V$2,'Committments Dump'!$B:$B,'Category Table'!$A50) | W50: =SUMIFS('Committments Dump'!$Q:$Q,'Committments Dump'!$C:$C,'Category Table'!W$2,'Committments Dump'!$B:$B,'Category Table'!$A50) | X50: =SUMIFS('Committments Dump'!$R:$R,'Committments Dump'!$C:$C,'Category Table'!X$2,'Committments Dump'!$B:$B,'Category Table'!$A50) | Y50: =SUMIFS('Committments Dump'!$R:$R,'Committments Dump'!$C:$C,'Category Table'!Y$2,'Committments Dump'!$B:$B,'Category Table'!$A50) | Z50: =SUMIFS('Committments Dump'!$R:$R,'Committments Dump'!$C:$C,'Category Table'!Z$2,'Committments Dump'!$B:$B,'Category Table'!$A50) | AA50: =SUMIFS('Committments Dump'!$S:$S,'Committments Dump'!$C:$C,'Category Table'!AA$2,'Committments Dump'!$B:$B,'Category Table'!$A50) | AB50: =SUMIFS('Committments Dump'!$S:$S,'Committments Dump'!$C:$C,'Category Table'!AB$2,'Committments Dump'!$B:$B,'Category Table'!$A50) | AC50: =SUMIFS('Committments Dump'!$S:$S,'Committments Dump'!$C:$C,'Category Table'!AC$2,'Committments Dump'!$B:$B,'Category Table'!$A50) | AD50: =U50+X50+AA50 | AE50: =V50+Y50+AB50 | AF50: =W50+Z50+AC50 | AG50: =R50+AD50 | AH50: =S50+AE50 | AI50: =T50+AF50 | AM50: =(O50-AG50)+AJ50 | AN50: =(P50-AH50)+AK50 | AO50: =(Q50-AI50)+AL50 | AP50: =IF(AM50>0, "Under",IF(AM50<0,"Over","")) | AQ50: =IF(AN50>0, "Under",IF(AN50<0,"Over","")) | AR50: =IF(AO50>0, "Under",IF(AO50<0,"Over",""))
A51: 0-4411 | B51: 0-4411-LDB Install | C51: 0 | D51: 0 | E51: 0 | F51: 0 | G51: 0 | H51: 0 | I51: 0 | J51: 0 | K51: 0 | L51: 0 | M51: 0 | N51: 0 | O51: =L51+I51+F51+C51 | P51: =M51+J51+G51+D51 | Q51: =N51+K51+H51+E51 | R51: =SUMIFS('PO Log'!$E:$E,'PO Log'!$D:$D,'Category Table'!R$2,'PO Log'!$C:$C,'Category Table'!$A51) | S51: =SUMIFS('PO Log'!$E:$E,'PO Log'!$D:$D,'Category Table'!S$2,'PO Log'!$C:$C,'Category Table'!$A51) | T51: =SUMIFS('PO Log'!$E:$E,'PO Log'!$D:$D,'Category Table'!T$2,'PO Log'!$C:$C,'Category Table'!$A51) | U51: =SUMIFS('Committments Dump'!$Q:$Q,'Committments Dump'!$C:$C,'Category Table'!U$2,'Committments Dump'!$B:$B,'Category Table'!$A51) | V51: =SUMIFS('Committments Dump'!$Q:$Q,'Committments Dump'!$C:$C,'Category Table'!V$2,'Committments Dump'!$B:$B,'Category Table'!$A51) | W51: =SUMIFS('Committments Dump'!$Q:$Q,'Committments Dump'!$C:$C,'Category Table'!W$2,'Committments Dump'!$B:$B,'Category Table'!$A51) | X51: =SUMIFS('Committments Dump'!$R:$R,'Committments Dump'!$C:$C,'Category Table'!X$2,'Committments Dump'!$B:$B,'Category Table'!$A51) | Y51: =SUMIFS('Committments Dump'!$R:$R,'Committments Dump'!$C:$C,'Category Table'!Y$2,'Committments Dump'!$B:$B,'Category Table'!$A51) | Z51: =SUMIFS('Committments Dump'!$R:$R,'Committments Dump'!$C:$C,'Category Table'!Z$2,'Committments Dump'!$B:$B,'Category Table'!$A51) | AA51: =SUMIFS('Committments Dump'!$S:$S,'Committments Dump'!$C:$C,'Category Table'!AA$2,'Committments Dump'!$B:$B,'Category Table'!$A51) | AB51: =SUMIFS('Committments Dump'!$S:$S,'Committments Dump'!$C:$C,'Category Table'!AB$2,'Committments Dump'!$B:$B,'Category Table'!$A51) | AC51: =SUMIFS('Committments Dump'!$S:$S,'Committments Dump'!$C:$C,'Category Table'!AC$2,'Committments Dump'!$B:$B,'Category Table'!$A51) | AD51: =U51+X51+AA51 | AE51: =V51+Y51+AB51 | AF51: =W51+Z51+AC51 | AG51: =R51+AD51 | AH51: =S51+AE51 | AI51: =T51+AF51 | AM51: =(O51-AG51)+AJ51 | AN51: =(P51-AH51)+AK51 | AO51: =(Q51-AI51)+AL51 | AP51: =IF(AM51>0, "Under",IF(AM51<0,"Over","")) | AQ51: =IF(AN51>0, "Under",IF(AN51<0,"Over","")) | AR51: =IF(AO51>0, "Under",IF(AO51<0,"Over",""))
A52: 0-4412 | B52: 0-4412-CAB System Install | C52: 0 | D52: 0 | E52: 0 | F52: 0 | G52: 0 | H52: 0 | I52: 0 | J52: 0 | K52: 0 | L52: 0 | M52: 0 | N52: 0 | O52: =L52+I52+F52+C52 | P52: =M52+J52+G52+D52 | Q52: =N52+K52+H52+E52 | R52: =SUMIFS('PO Log'!$E:$E,'PO Log'!$D:$D,'Category Table'!R$2,'PO Log'!$C:$C,'Category Table'!$A52) | S52: =SUMIFS('PO Log'!$E:$E,'PO Log'!$D:$D,'Category Table'!S$2,'PO Log'!$C:$C,'Category Table'!$A52) | T52: =SUMIFS('PO Log'!$E:$E,'PO Log'!$D:$D,'Category Table'!T$2,'PO Log'!$C:$C,'Category Table'!$A52) | U52: =SUMIFS('Committments Dump'!$Q:$Q,'Committments Dump'!$C:$C,'Category Table'!U$2,'Committments Dump'!$B:$B,'Category Table'!$A52) | V52: =SUMIFS('Committments Dump'!$Q:$Q,'Committments Dump'!$C:$C,'Category Table'!V$2,'Committments Dump'!$B:$B,'Category Table'!$A52) | W52: =SUMIFS('Committments Dump'!$Q:$Q,'Committments Dump'!$C:$C,'Category Table'!W$2,'Committments Dump'!$B:$B,'Category Table'!$A52) | X52: =SUMIFS('Committments Dump'!$R:$R,'Committments Dump'!$C:$C,'Category Table'!X$2,'Committments Dump'!$B:$B,'Category Table'!$A52) | Y52: =SUMIFS('Committments Dump'!$R:$R,'Committments Dump'!$C:$C,'Category Table'!Y$2,'Committments Dump'!$B:$B,'Category Table'!$A52) | Z52: =SUMIFS('Committments Dump'!$R:$R,'Committments Dump'!$C:$C,'Category Table'!Z$2,'Committments Dump'!$B:$B,'Category Table'!$A52) | AA52: =SUMIFS('Committments Dump'!$S:$S,'Committments Dump'!$C:$C,'Category Table'!AA$2,'Committments Dump'!$B:$B,'Category Table'!$A52) | AB52: =SUMIFS('Committments Dump'!$S:$S,'Committments Dump'!$C:$C,'Category Table'!AB$2,'Committments Dump'!$B:$B,'Category Table'!$A52) | AC52: =SUMIFS('Committments Dump'!$S:$S,'Committments Dump'!$C:$C,'Category Table'!AC$2,'Committments Dump'!$B:$B,'Category Table'!$A52) | AD52: =U52+X52+AA52 | AE52: =V52+Y52+AB52 | AF52: =W52+Z52+AC52 | AG52: =R52+AD52 | AH52: =S52+AE52 | AI52: =T52+AF52 | AM52: =(O52-AG52)+AJ52 | AN52: =(P52-AH52)+AK52 | AO52: =(Q52-AI52)+AL52 | AP52: =IF(AM52>0, "Under",IF(AM52<0,"Over","")) | AQ52: =IF(AN52>0, "Under",IF(AN52<0,"Over","")) | AR52: =IF(AO52>0, "Under",IF(AO52<0,"Over",""))
A53: 0-4413 | B53: 0-4413-DC Testing | C53: 0 | D53: 0 | E53: 0 | F53: 0 | G53: 0 | H53: 59537.5 | I53: 0 | J53: 0 | K53: 0 | L53: 0 | M53: 0 | N53: 0 | O53: =L53+I53+F53+C53 | P53: =M53+J53+G53+D53 | Q53: =N53+K53+H53+E53 | R53: =SUMIFS('PO Log'!$E:$E,'PO Log'!$D:$D,'Category Table'!R$2,'PO Log'!$C:$C,'Category Table'!$A53) | S53: =SUMIFS('PO Log'!$E:$E,'PO Log'!$D:$D,'Category Table'!S$2,'PO Log'!$C:$C,'Category Table'!$A53) | T53: =SUMIFS('PO Log'!$E:$E,'PO Log'!$D:$D,'Category Table'!T$2,'PO Log'!$C:$C,'Category Table'!$A53) | U53: =SUMIFS('Committments Dump'!$Q:$Q,'Committments Dump'!$C:$C,'Category Table'!U$2,'Committments Dump'!$B:$B,'Category Table'!$A53) | V53: =SUMIFS('Committments Dump'!$Q:$Q,'Committments Dump'!$C:$C,'Category Table'!V$2,'Committments Dump'!$B:$B,'Category Table'!$A53) | W53: =SUMIFS('Committments Dump'!$Q:$Q,'Committments Dump'!$C:$C,'Category Table'!W$2,'Committments Dump'!$B:$B,'Category Table'!$A53) | X53: =SUMIFS('Committments Dump'!$R:$R,'Committments Dump'!$C:$C,'Category Table'!X$2,'Committments Dump'!$B:$B,'Category Table'!$A53) | Y53: =SUMIFS('Committments Dump'!$R:$R,'Committments Dump'!$C:$C,'Category Table'!Y$2,'Committments Dump'!$B:$B,'Category Table'!$A53) | Z53: =SUMIFS('Committments Dump'!$R:$R,'Committments Dump'!$C:$C,'Category Table'!Z$2,'Committments Dump'!$B:$B,'Category Table'!$A53) | AA53: =SUMIFS('Committments Dump'!$S:$S,'Committments Dump'!$C:$C,'Category Table'!AA$2,'Committments Dump'!$B:$B,'Category Table'!$A53) | AB53: =SUMIFS('Committments Dump'!$S:$S,'Committments Dump'!$C:$C,'Category Table'!AB$2,'Committments Dump'!$B:$B,'Category Table'!$A53) | AC53: =SUMIFS('Committments Dump'!$S:$S,'Committments Dump'!$C:$C,'Category Table'!AC$2,'Committments Dump'!$B:$B,'Category Table'!$A53) | AD53: =U53+X53+AA53 | AE53: =V53+Y53+AB53 | AF53: =W53+Z53+AC53 | AG53: =R53+AD53 | AH53: =S53+AE53 | AI53: =T53+AF53 | AM53: =(O53-AG53)+AJ53 | AN53: =(P53-AH53)+AK53 | AO53: =(Q53-AI53)+AL53 | AP53: =IF(AM53>0, "Under",IF(AM53<0,"Over","")) | AQ53: =IF(AN53>0, "Under",IF(AN53<0,"Over","")) | AR53: =IF(AO53>0, "Under",IF(AO53<0,"Over",""))
A54: 0-4414 | B54: 0-4414- Commisioning | C54: 0 | D54: 0 | E54: 0 | F54: 0 | G54: 3621.9884 | H54: 0 | I54: 0 | J54: 0 | K54: 0 | L54: 0 | M54: 0 | N54: 0 | O54: =L54+I54+F54+C54 | P54: =M54+J54+G54+D54 | Q54: =N54+K54+H54+E54 | R54: =SUMIFS('PO Log'!$E:$E,'PO Log'!$D:$D,'Category Table'!R$2,'PO Log'!$C:$C,'Category Table'!$A54) | S54: =SUMIFS('PO Log'!$E:$E,'PO Log'!$D:$D,'Category Table'!S$2,'PO Log'!$C:$C,'Category Table'!$A54) | T54: =SUMIFS('PO Log'!$E:$E,'PO Log'!$D:$D,'Category Table'!T$2,'PO Log'!$C:$C,'Category Table'!$A54) | U54: =SUMIFS('Committments Dump'!$Q:$Q,'Committments Dump'!$C:$C,'Category Table'!U$2,'Committments Dump'!$B:$B,'Category Table'!$A54) | V54: =SUMIFS('Committments Dump'!$Q:$Q,'Committments Dump'!$C:$C,'Category Table'!V$2,'Committments Dump'!$B:$B,'Category Table'!$A54) | W54: =SUMIFS('Committments Dump'!$Q:$Q,'Committments Dump'!$C:$C,'Category Table'!W$2,'Committments Dump'!$B:$B,'Category Table'!$A54) | X54: =SUMIFS('Committments Dump'!$R:$R,'Committments Dump'!$C:$C,'Category Table'!X$2,'Committments Dump'!$B:$B,'Category Table'!$A54) | Y54: =SUMIFS('Committments Dump'!$R:$R,'Committments Dump'!$C:$C,'Category Table'!Y$2,'Committments Dump'!$B:$B,'Category Table'!$A54) | Z54: =SUMIFS('Committments Dump'!$R:$R,'Committments Dump'!$C:$C,'Category Table'!Z$2,'Committments Dump'!$B:$B,'Category Table'!$A54) | AA54: =SUMIFS('Committments Dump'!$S:$S,'Committments Dump'!$C:$C,'Category Table'!AA$2,'Committments Dump'!$B:$B,'Category Table'!$A54) | AB54: =SUMIFS('Committments Dump'!$S:$S,'Committments Dump'!$C:$C,'Category Table'!AB$2,'Committments Dump'!$B:$B,'Category Table'!$A54) | AC54: =SUMIFS('Committments Dump'!$S:$S,'Committments Dump'!$C:$C,'Category Table'!AC$2,'Committments Dump'!$B:$B,'Category Table'!$A54) | AD54: =U54+X54+AA54 | AE54: =V54+Y54+AB54 | AF54: =W54+Z54+AC54 | AG54: =R54+AD54 | AH54: =S54+AE54 | AI54: =T54+AF54 | AM54: =(O54-AG54)+AJ54 | AN54: =(P54-AH54)+AK54 | AO54: =(Q54-AI54)+AL54 | AP54: =IF(AM54>0, "Under",IF(AM54<0,"Over","")) | AQ54: =IF(AN54>0, "Under",IF(AN54<0,"Over","")) | AR54: =IF(AO54>0, "Under",IF(AO54<0,"Over",""))
... A58: 0-4418 | B58: 0-4418 - Electrical QAQC | C58: 0 | D58: 0 | E58: 0 | F58: 0 | G58: 108.61316 | H58: 0 | I58: 0 | J58: 0 | K58: 0 | L58: 0 | M58: 0 | N58: 0 | O58: =L58+I58+F58+C58 | P58: =M58+J58+G58+D58 | Q58: =N58+K58+H58+E58 | R58: =SUMIFS('PO Log'!$E:$E,'PO Log'!$D:$D,'Category Table'!R$2,'PO Log'!$C:$C,'Category Table'!$A58) | S58: =SUMIFS('PO Log'!$E:$E,'PO Log'!$D:$D,'Category Table'!S$2,'PO Log'!$C:$C,'Category Table'!$A58) | T58: =SUMIFS('PO Log'!$E:$E,'PO Log'!$D:$D,'Category Table'!T$2,'PO Log'!$C:$C,'Category Table'!$A58) | U58: =SUMIFS('Committments Dump'!$Q:$Q,'Committments Dump'!$C:$C,'Category Table'!U$2,'Committments Dump'!$B:$B,'Category Table'!$A58) | V58: =SUMIFS('Committments Dump'!$Q:$Q,'Committments Dump'!$C:$C,'Category Table'!V$2,'Committments Dump'!$B:$B,'Category Table'!$A58) | W58: =SUMIFS('Committments Dump'!$Q:$Q,'Committments Dump'!$C:$C,'Category Table'!W$2,'Committments Dump'!$B:$B,'Category Table'!$A58) | X58: =SUMIFS('Committments Dump'!$R:$R,'Committments Dump'!$C:$C,'Category Table'!X$2,'Committments Dump'!$B:$B,'Category Table'!$A58) | Y58: =SUMIFS('Committments Dump'!$R:$R,'Committments Dump'!$C:$C,'Category Table'!Y$2,'Committments Dump'!$B:$B,'Category Table'!$A58) | Z58: =SUMIFS('Committments Dump'!$R:$R,'Committments Dump'!$C:$C,'Category Table'!Z$2,'Committments Dump'!$B:$B,'Category Table'!$A58) | AA58: =SUMIFS('Committments Dump'!$S:$S,'Committments Dump'!$C:$C,'Category Table'!AA$2,'Committments Dump'!$B:$B,'Category Table'!$A58) | AB58: =SUMIFS('Committments Dump'!$S:$S,'Committments Dump'!$C:$C,'Category Table'!AB$2,'Committments Dump'!$B:$B,'Category Table'!$A58) | AC58: =SUMIFS('Committments Dump'!$S:$S,'Committments Dump'!$C:$C,'Category Table'!AC$2,'Committments Dump'!$B:$B,'Category Table'!$A58) | AD58: =U58+X58+AA58 | AE58: =V58+Y58+AB58 | AF58: =W58+Z58+AC58 | AG58: =R58+AD58 | AH58: =S58+AE58 | AI58: =T58+AF58 | AM58: =(O58-AG58)+AJ58 | AN58: =(P58-AH58)+AK58 | AO58: =(Q58-AI58)+AL58 | AP58: =IF(AM58>0, "Under",IF(AM58<0,"Over","")) | AQ58: =IF(AN58>0, "Under",IF(AN58<0,"Over","")) | AR58: =IF(AO58>0, "Under",IF(AO58<0,"Over",""))
A59: 0-4420 | B59: 0-4420-Electrical DC Punch List | C59: 0 | D59: 0 | E59: 0 | F59: 0 | H59: 0 | I59: 0 | J59: 0 | K59: 0 | L59: 0 | M59: 0 | N59: 0 | O59: =L59+I59+F59+C59 | P59: =M59+J59+G59+D59 | Q59: =N59+K59+H59+E59 | R59: =SUMIFS('PO Log'!$E:$E,'PO Log'!$D:$D,'Category Table'!R$2,'PO Log'!$C:$C,'Category Table'!$A59) | S59: =SUMIFS('PO Log'!$E:$E,'PO Log'!$D:$D,'Category Table'!S$2,'PO Log'!$C:$C,'Category Table'!$A59) | T59: =SUMIFS('PO Log'!$E:$E,'PO Log'!$D:$D,'Category Table'!T$2,'PO Log'!$C:$C,'Category Table'!$A59) | U59: =SUMIFS('Committments Dump'!$Q:$Q,'Committments Dump'!$C:$C,'Category Table'!U$2,'Committments Dump'!$B:$B,'Category Table'!$A59) | V59: =SUMIFS('Committments Dump'!$Q:$Q,'Committments Dump'!$C:$C,'Category Table'!V$2,'Committments Dump'!$B:$B,'Category Table'!$A59) | W59: =SUMIFS('Committments Dump'!$Q:$Q,'Committments Dump'!$C:$C,'Category Table'!W$2,'Committments Dump'!$B:$B,'Category Table'!$A59) | X59: =SUMIFS('Committments Dump'!$R:$R,'Committments Dump'!$C:$C,'Category Table'!X$2,'Committments Dump'!$B:$B,'Category Table'!$A59) | Y59: =SUMIFS('Committments Dump'!$R:$R,'Committments Dump'!$C:$C,'Category Table'!Y$2,'Committments Dump'!$B:$B,'Category Table'!$A59) | Z59: =SUMIFS('Committments Dump'!$R:$R,'Committments Dump'!$C:$C,'Category Table'!Z$2,'Committments Dump'!$B:$B,'Category Table'!$A59) | AA59: =SUMIFS('Committments Dump'!$S:$S,'Committments Dump'!$C:$C,'Category Table'!AA$2,'Committments Dump'!$B:$B,'Category Table'!$A59) | AB59: =SUMIFS('Committments Dump'!$S:$S,'Committments Dump'!$C:$C,'Category Table'!AB$2,'Committments Dump'!$B:$B,'Category Table'!$A59) | AC59: =SUMIFS('Committments Dump'!$S:$S,'Committments Dump'!$C:$C,'Category Table'!AC$2,'Committments Dump'!$B:$B,'Category Table'!$A59) | AD59: =U59+X59+AA59 | AE59: =V59+Y59+AB59 | AF59: =W59+Z59+AC59 | AG59: =R59+AD59 | AH59: =S59+AE59 | AI59: =T59+AF59 | AM59: =(O59-AG59)+AJ59 | AN59: =(P59-AH59)+AK59 | AO59: =(Q59-AI59)+AL59 | AP59: =IF(AM59>0, "Under",IF(AM59<0,"Over","")) | AQ59: =IF(AN59>0, "Under",IF(AN59<0,"Over","")) | AR59: =IF(AO59>0, "Under",IF(AO59<0,"Over",""))
A60: 0-4500 | B60: 0-4500-AC-MV Plowing | C60: 0 | D60: 0 | E60: 0 | F60: 0 | H60: 147627.24 | I60: 0 | J60: 0 | K60: 0 | L60: 0 | M60: 0 | N60: 0 | O60: =L60+I60+F60+C60 | P60: =M60+J60+G60+D60 | Q60: =N60+K60+H60+E60 | R60: =SUMIFS('PO Log'!$E:$E,'PO Log'!$D:$D,'Category Table'!R$2,'PO Log'!$C:$C,'Category Table'!$A60) | S60: =SUMIFS('PO Log'!$E:$E,'PO Log'!$D:$D,'Category Table'!S$2,'PO Log'!$C:$C,'Category Table'!$A60) | T60: =SUMIFS('PO Log'!$E:$E,'PO Log'!$D:$D,'Category Table'!T$2,'PO Log'!$C:$C,'Category Table'!$A60) | U60: =SUMIFS('Committments Dump'!$Q:$Q,'Committments Dump'!$C:$C,'Category Table'!U$2,'Committments Dump'!$B:$B,'Category Table'!$A60) | V60: =SUMIFS('Committments Dump'!$Q:$Q,'Committments Dump'!$C:$C,'Category Table'!V$2,'Committments Dump'!$B:$B,'Category Table'!$A60) | W60: =SUMIFS('Committments Dump'!$Q:$Q,'Committments Dump'!$C:$C,'Category Table'!W$2,'Committments Dump'!$B:$B,'Category Table'!$A60) | X60: =SUMIFS('Committments Dump'!$R:$R,'Committments Dump'!$C:$C,'Category Table'!X$2,'Committments Dump'!$B:$B,'Category Table'!$A60) | Y60: =SUMIFS('Committments Dump'!$R:$R,'Committments Dump'!$C:$C,'Category Table'!Y$2,'Committments Dump'!$B:$B,'Category Table'!$A60) | Z60: =SUMIFS('Committments Dump'!$R:$R,'Committments Dump'!$C:$C,'Category Table'!Z$2,'Committments Dump'!$B:$B,'Category Table'!$A60) | AA60: =SUMIFS('Committments Dump'!$S:$S,'Committments Dump'!$C:$C,'Category Table'!AA$2,'Committments Dump'!$B:$B,'Category Table'!$A60) | AB60: =SUMIFS('Committments Dump'!$S:$S,'Committments Dump'!$C:$C,'Category Table'!AB$2,'Committments Dump'!$B:$B,'Category Table'!$A60) | AC60: =SUMIFS('Committments Dump'!$S:$S,'Committments Dump'!$C:$C,'Category Table'!AC$2,'Committments Dump'!$B:$B,'Category Table'!$A60) | AD60: =U60+X60+AA60 | AE60: =V60+Y60+AB60 | AF60: =W60+Z60+AC60 | AG60: =R60+AD60 | AH60: =S60+AE60 | AI60: =T60+AF60 | AM60: =(O60-AG60)+AJ60 | AN60: =(P60-AH60)+AK60 | AO60: =(Q60-AI60)+AL60 | AP60: =IF(AM60>0, "Under",IF(AM60<0,"Over","")) | AQ60: =IF(AN60>0, "Under",IF(AN60<0,"Over","")) | AR60: =IF(AO60>0, "Under",IF(AO60<0,"Over",""))
A61: 0-4501 | B61: 0-4501-AC-MV Terminations | C61: 0 | D61: 0 | E61: 0 | F61: 0 | G61: 0 | H61: 0 | I61: 0 | J61: 0 | K61: 0 | L61: 0 | M61: 0 | N61: 0 | O61: =L61+I61+F61+C61 | P61: =M61+J61+G61+D61 | Q61: =N61+K61+H61+E61 | R61: =SUMIFS('PO Log'!$E:$E,'PO Log'!$D:$D,'Category Table'!R$2,'PO Log'!$C:$C,'Category Table'!$A61) | S61: =SUMIFS('PO Log'!$E:$E,'PO Log'!$D:$D,'Category Table'!S$2,'PO Log'!$C:$C,'Category Table'!$A61) | T61: =SUMIFS('PO Log'!$E:$E,'PO Log'!$D:$D,'Category Table'!T$2,'PO Log'!$C:$C,'Category Table'!$A61) | U61: =SUMIFS('Committments Dump'!$Q:$Q,'Committments Dump'!$C:$C,'Category Table'!U$2,'Committments Dump'!$B:$B,'Category Table'!$A61) | V61: =SUMIFS('Committments Dump'!$Q:$Q,'Committments Dump'!$C:$C,'Category Table'!V$2,'Committments Dump'!$B:$B,'Category Table'!$A61) | W61: =SUMIFS('Committments Dump'!$Q:$Q,'Committments Dump'!$C:$C,'Category Table'!W$2,'Committments Dump'!$B:$B,'Category Table'!$A61) | X61: =SUMIFS('Committments Dump'!$R:$R,'Committments Dump'!$C:$C,'Category Table'!X$2,'Committments Dump'!$B:$B,'Category Table'!$A61) | Y61: =SUMIFS('Committments Dump'!$R:$R,'Committments Dump'!$C:$C,'Category Table'!Y$2,'Committments Dump'!$B:$B,'Category Table'!$A61) | Z61: =SUMIFS('Committments Dump'!$R:$R,'Committments Dump'!$C:$C,'Category Table'!Z$2,'Committments Dump'!$B:$B,'Category Table'!$A61) | AA61: =SUMIFS('Committments Dump'!$S:$S,'Committments Dump'!$C:$C,'Category Table'!AA$2,'Committments Dump'!$B:$B,'Category Table'!$A61) | AB61: =SUMIFS('Committments Dump'!$S:$S,'Committments Dump'!$C:$C,'Category Table'!AB$2,'Committments Dump'!$B:$B,'Category Table'!$A61) | AC61: =SUMIFS('Committments Dump'!$S:$S,'Committments Dump'!$C:$C,'Category Table'!AC$2,'Committments Dump'!$B:$B,'Category Table'!$A61) | AD61: =U61+X61+AA61 | AE61: =V61+Y61+AB61 | AF61: =W61+Z61+AC61 | AG61: =R61+AD61 | AH61: =S61+AE61 | AI61: =T61+AF61 | AM61: =(O61-AG61)+AJ61 | AN61: =(P61-AH61)+AK61 | AO61: =(Q61-AI61)+AL61 | AP61: =IF(AM61>0, "Under",IF(AM61<0,"Over","")) | AQ61: =IF(AN61>0, "Under",IF(AN61<0,"Over","")) | AR61: =IF(AO61>0, "Under",IF(AO61<0,"Over",""))
A62: 0-4502 | B62: 0-4502-AC-MV Splices | C62: 0 | D62: 0 | E62: 0 | F62: 0 | G62: 0 | H62: 0 | I62: 0 | J62: 0 | K62: 0 | L62: 0 | M62: 0 | N62: 0 | O62: =L62+I62+F62+C62 | P62: =M62+J62+G62+D62 | Q62: =N62+K62+H62+E62 | R62: =SUMIFS('PO Log'!$E:$E,'PO Log'!$D:$D,'Category Table'!R$2,'PO Log'!$C:$C,'Category Table'!$A62) | S62: =SUMIFS('PO Log'!$E:$E,'PO Log'!$D:$D,'Category Table'!S$2,'PO Log'!$C:$C,'Category Table'!$A62) | T62: =SUMIFS('PO Log'!$E:$E,'PO Log'!$D:$D,'Category Table'!T$2,'PO Log'!$C:$C,'Category Table'!$A62) | U62: =SUMIFS('Committments Dump'!$Q:$Q,'Committments Dump'!$C:$C,'Category Table'!U$2,'Committments Dump'!$B:$B,'Category Table'!$A62) | V62: =SUMIFS('Committments Dump'!$Q:$Q,'Committments Dump'!$C:$C,'Category Table'!V$2,'Committments Dump'!$B:$B,'Category Table'!$A62) | W62: =SUMIFS('Committments Dump'!$Q:$Q,'Committments Dump'!$C:$C,'Category Table'!W$2,'Committments Dump'!$B:$B,'Category Table'!$A62) | X62: =SUMIFS('Committments Dump'!$R:$R,'Committments Dump'!$C:$C,'Category Table'!X$2,'Committments Dump'!$B:$B,'Category Table'!$A62) | Y62: =SUMIFS('Committments Dump'!$R:$R,'Committments Dump'!$C:$C,'Category Table'!Y$2,'Committments Dump'!$B:$B,'Category Table'!$A62) | Z62: =SUMIFS('Committments Dump'!$R:$R,'Committments Dump'!$C:$C,'Category Table'!Z$2,'Committments Dump'!$B:$B,'Category Table'!$A62) | AA62: =SUMIFS('Committments Dump'!$S:$S,'Committments Dump'!$C:$C,'Category Table'!AA$2,'Committments Dump'!$B:$B,'Category Table'!$A62) | AB62: =SUMIFS('Committments Dump'!$S:$S,'Committments Dump'!$C:$C,'Category Table'!AB$2,'Committments Dump'!$B:$B,'Category Table'!$A62) | AC62: =SUMIFS('Committments Dump'!$S:$S,'Committments Dump'!$C:$C,'Category Table'!AC$2,'Committments Dump'!$B:$B,'Category Table'!$A62) | AD62: =U62+X62+AA62 | AE62: =V62+Y62+AB62 | AF62: =W62+Z62+AC62 | AG62: =R62+AD62 | AH62: =S62+AE62 | AI62: =T62+AF62 | AM62: =(O62-AG62)+AJ62 | AN62: =(P62-AH62)+AK62 | AO62: =(Q62-AI62)+AL62 | AP62: =IF(AM62>0, "Under",IF(AM62<0,"Over","")) | AQ62: =IF(AN62>0, "Under",IF(AN62<0,"Over","")) | AR62: =IF(AO62>0, "Under",IF(AO62<0,"Over",""))
A63: 0-4503 | B63: 0-4503-AC-MV Cable Tie-ins | C63: 0 | D63: 0 | E63: 0 | F63: 0 | G63: 0 | H63: 2877.54 | I63: 0 | J63: 0 | K63: 0 | L63: 0 | M63: 0 | N63: 0 | O63: =L63+I63+F63+C63 | P63: =M63+J63+G63+D63 | Q63: =N63+K63+H63+E63 | R63: =SUMIFS('PO Log'!$E:$E,'PO Log'!$D:$D,'Category Table'!R$2,'PO Log'!$C:$C,'Category Table'!$A63) | S63: =SUMIFS('PO Log'!$E:$E,'PO Log'!$D:$D,'Category Table'!S$2,'PO Log'!$C:$C,'Category Table'!$A63) | T63: =SUMIFS('PO Log'!$E:$E,'PO Log'!$D:$D,'Category Table'!T$2,'PO Log'!$C:$C,'Category Table'!$A63) | U63: =SUMIFS('Committments Dump'!$Q:$Q,'Committments Dump'!$C:$C,'Category Table'!U$2,'Committments Dump'!$B:$B,'Category Table'!$A63) | V63: =SUMIFS('Committments Dump'!$Q:$Q,'Committments Dump'!$C:$C,'Category Table'!V$2,'Committments Dump'!$B:$B,'Category Table'!$A63) | W63: =SUMIFS('Committments Dump'!$Q:$Q,'Committments Dump'!$C:$C,'Category Table'!W$2,'Committments Dump'!$B:$B,'Category Table'!$A63) | X63: =SUMIFS('Committments Dump'!$R:$R,'Committments Dump'!$C:$C,'Category Table'!X$2,'Committments Dump'!$B:$B,'Category Table'!$A63) | Y63: =SUMIFS('Committments Dump'!$R:$R,'Committments Dump'!$C:$C,'Category Table'!Y$2,'Committments Dump'!$B:$B,'Category Table'!$A63) | Z63: =SUMIFS('Committments Dump'!$R:$R,'Committments Dump'!$C:$C,'Category Table'!Z$2,'Committments Dump'!$B:$B,'Category Table'!$A63) | AA63: =SUMIFS('Committments Dump'!$S:$S,'Committments Dump'!$C:$C,'Category Table'!AA$2,'Committments Dump'!$B:$B,'Category Table'!$A63) | AB63: =SUMIFS('Committments Dump'!$S:$S,'Committments Dump'!$C:$C,'Category Table'!AB$2,'Committments Dump'!$B:$B,'Category Table'!$A63) | AC63: =SUMIFS('Committments Dump'!$S:$S,'Committments Dump'!$C:$C,'Category Table'!AC$2,'Committments Dump'!$B:$B,'Category Table'!$A63) | AD63: =U63+X63+AA63 | AE63: =V63+Y63+AB63 | AF63: =W63+Z63+AC63 | AG63: =R63+AD63 | AH63: =S63+AE63 | AI63: =T63+AF63 | AM63: =(O63-AG63)+AJ63 | AN63: =(P63-AH63)+AK63 | AO63: =(Q63-AI63)+AL63 | AP63: =IF(AM63>0, "Under",IF(AM63<0,"Over","")) | AQ63: =IF(AN63>0, "Under",IF(AN63<0,"Over","")) | AR63: =IF(AO63>0, "Under",IF(AO63<0,"Over",""))
A64: 0-4505 | B64: 0-4505-AC-MV Boring | C64: 0 | D64: 0 | E64: 0 | F64: 22500 | G64: 200836.63 | H64: 1735000 | I64: 0 | J64: 0 | K64: 0 | L64: 0 | M64: 0 | N64: 0 | O64: =L64+I64+F64+C64 | P64: =M64+J64+G64+D64 | Q64: =N64+K64+H64+E64 | R64: =SUMIFS('PO Log'!$E:$E,'PO Log'!$D:$D,'Category Table'!R$2,'PO Log'!$C:$C,'Category Table'!$A64) | S64: =SUMIFS('PO Log'!$E:$E,'PO Log'!$D:$D,'Category Table'!S$2,'PO Log'!$C:$C,'Category Table'!$A64) | T64: =SUMIFS('PO Log'!$E:$E,'PO Log'!$D:$D,'Category Table'!T$2,'PO Log'!$C:$C,'Category Table'!$A64) | U64: =SUMIFS('Committments Dump'!$Q:$Q,'Committments Dump'!$C:$C,'Category Table'!U$2,'Committments Dump'!$B:$B,'Category Table'!$A64) | V64: =SUMIFS('Committments Dump'!$Q:$Q,'Committments Dump'!$C:$C,'Category Table'!V$2,'Committments Dump'!$B:$B,'Category Table'!$A64) | W64: =SUMIFS('Committments Dump'!$Q:$Q,'Committments Dump'!$C:$C,'Category Table'!W$2,'Committments Dump'!$B:$B,'Category Table'!$A64) | X64: =SUMIFS('Committments Dump'!$R:$R,'Committments Dump'!$C:$C,'Category Table'!X$2,'Committments Dump'!$B:$B,'Category Table'!$A64) | Y64: =SUMIFS('Committments Dump'!$R:$R,'Committments Dump'!$C:$C,'Category Table'!Y$2,'Committments Dump'!$B:$B,'Category Table'!$A64) | Z64: =SUMIFS('Committments Dump'!$R:$R,'Committments Dump'!$C:$C,'Category Table'!Z$2,'Committments Dump'!$B:$B,'Category Table'!$A64) | AA64: =SUMIFS('Committments Dump'!$S:$S,'Committments Dump'!$C:$C,'Category Table'!AA$2,'Committments Dump'!$B:$B,'Category Table'!$A64) | AB64: =SUMIFS('Committments Dump'!$S:$S,'Committments Dump'!$C:$C,'Category Table'!AB$2,'Committments Dump'!$B:$B,'Category Table'!$A64) | AC64: =SUMIFS('Committments Dump'!$S:$S,'Committments Dump'!$C:$C,'Category Table'!AC$2,'Committments Dump'!$B:$B,'Category Table'!$A64) | AD64: =U64+X64+AA64 | AE64: =V64+Y64+AB64 | AF64: =W64+Z64+AC64 | AG64: =R64+AD64 | AH64: =S64+AE64 | AI64: =T64+AF64 | AM64: =(O64-AG64)+AJ64 | AN64: =(P64-AH64)+AK64 | AO64: =(Q64-AI64)+AL64 | AP64: =IF(AM64>0, "Under",IF(AM64<0,"Over","")) | AQ64: =IF(AN64>0, "Under",IF(AN64<0,"Over","")) | AR64: =IF(AO64>0, "Under",IF(AO64<0,"Over",""))
A65: 0-4508 | B65: 0-4508-AC-MV Trenching & BackFill | C65: 0 | D65: 0 | E65: 0 | F65: 0 | G65: 0 | H65: 150000 | I65: 0 | J65: 0 | K65: 0 | L65: 0 | M65: 0 | N65: 0 | O65: =L65+I65+F65+C65 | P65: =M65+J65+G65+D65 | Q65: =N65+K65+H65+E65 | R65: =SUMIFS('PO Log'!$E:$E,'PO Log'!$D:$D,'Category Table'!R$2,'PO Log'!$C:$C,'Category Table'!$A65) | S65: =SUMIFS('PO Log'!$E:$E,'PO Log'!$D:$D,'Category Table'!S$2,'PO Log'!$C:$C,'Category Table'!$A65) | T65: =SUMIFS('PO Log'!$E:$E,'PO Log'!$D:$D,'Category Table'!T$2,'PO Log'!$C:$C,'Category Table'!$A65) | U65: =SUMIFS('Committments Dump'!$Q:$Q,'Committments Dump'!$C:$C,'Category Table'!U$2,'Committments Dump'!$B:$B,'Category Table'!$A65) | V65: =SUMIFS('Committments Dump'!$Q:$Q,'Committments Dump'!$C:$C,'Category Table'!V$2,'Committments Dump'!$B:$B,'Category Table'!$A65) | W65: =SUMIFS('Committments Dump'!$Q:$Q,'Committments Dump'!$C:$C,'Category Table'!W$2,'Committments Dump'!$B:$B,'Category Table'!$A65) | X65: =SUMIFS('Committments Dump'!$R:$R,'Committments Dump'!$C:$C,'Category Table'!X$2,'Committments Dump'!$B:$B,'Category Table'!$A65) | Y65: =SUMIFS('Committments Dump'!$R:$R,'Committments Dump'!$C:$C,'Category Table'!Y$2,'Committments Dump'!$B:$B,'Category Table'!$A65) | Z65: =SUMIFS('Committments Dump'!$R:$R,'Committments Dump'!$C:$C,'Category Table'!Z$2,'Committments Dump'!$B:$B,'Category Table'!$A65) | AA65: =SUMIFS('Committments Dump'!$S:$S,'Committments Dump'!$C:$C,'Category Table'!AA$2,'Committments Dump'!$B:$B,'Category Table'!$A65) | AB65: =SUMIFS('Committments Dump'!$S:$S,'Committments Dump'!$C:$C,'Category Table'!AB$2,'Committments Dump'!$B:$B,'Category Table'!$A65) | AC65: =SUMIFS('Committments Dump'!$S:$S,'Committments Dump'!$C:$C,'Category Table'!AC$2,'Committments Dump'!$B:$B,'Category Table'!$A65) | AD65: =U65+X65+AA65 | AE65: =V65+Y65+AB65 | AF65: =W65+Z65+AC65 | AG65: =R65+AD65 | AH65: =S65+AE65 | AI65: =T65+AF65 | AM65: =(O65-AG65)+AJ65 | AN65: =(P65-AH65)+AK65 | AO65: =(Q65-AI65)+AL65 | AP65: =IF(AM65>0, "Under",IF(AM65<0,"Over","")) | AQ65: =IF(AN65>0, "Under",IF(AN65<0,"Over","")) | AR65: =IF(AO65>0, "Under",IF(AO65<0,"Over",""))
A66: 0-4510 | B66: 0-4510-AC-MV Cable Pull | C66: 0 | D66: 274.5 | E66: 0 | F66: 0 | G66: 0 | H66: 70000 | I66: 0 | J66: -304.7 | K66: 54063.48 | L66: 0 | M66: 609.71 | N66: 119487.57 | O66: =L66+I66+F66+C66 | P66: =M66+J66+G66+D66 | Q66: =N66+K66+H66+E66 | R66: =SUMIFS('PO Log'!$E:$E,'PO Log'!$D:$D,'Category Table'!R$2,'PO Log'!$C:$C,'Category Table'!$A66) | S66: =SUMIFS('PO Log'!$E:$E,'PO Log'!$D:$D,'Category Table'!S$2,'PO Log'!$C:$C,'Category Table'!$A66) | T66: =SUMIFS('PO Log'!$E:$E,'PO Log'!$D:$D,'Category Table'!T$2,'PO Log'!$C:$C,'Category Table'!$A66) | U66: =SUMIFS('Committments Dump'!$Q:$Q,'Committments Dump'!$C:$C,'Category Table'!U$2,'Committments Dump'!$B:$B,'Category Table'!$A66) | V66: =SUMIFS('Committments Dump'!$Q:$Q,'Committments Dump'!$C:$C,'Category Table'!V$2,'Committments Dump'!$B:$B,'Category Table'!$A66) | W66: =SUMIFS('Committments Dump'!$Q:$Q,'Committments Dump'!$C:$C,'Category Table'!W$2,'Committments Dump'!$B:$B,'Category Table'!$A66) | X66: =SUMIFS('Committments Dump'!$R:$R,'Committments Dump'!$C:$C,'Category Table'!X$2,'Committments Dump'!$B:$B,'Category Table'!$A66) | Y66: =SUMIFS('Committments Dump'!$R:$R,'Committments Dump'!$C:$C,'Category Table'!Y$2,'Committments Dump'!$B:$B,'Category Table'!$A66) | Z66: =SUMIFS('Committments Dump'!$R:$R,'Committments Dump'!$C:$C,'Category Table'!Z$2,'Committments Dump'!$B:$B,'Category Table'!$A66) | AA66: =SUMIFS('Committments Dump'!$S:$S,'Committments Dump'!$C:$C,'Category Table'!AA$2,'Committments Dump'!$B:$B,'Category Table'!$A66) | AB66: =SUMIFS('Committments Dump'!$S:$S,'Committments Dump'!$C:$C,'Category Table'!AB$2,'Committments Dump'!$B:$B,'Category Table'!$A66) | AC66: =SUMIFS('Committments Dump'!$S:$S,'Committments Dump'!$C:$C,'Category Table'!AC$2,'Committments Dump'!$B:$B,'Category Table'!$A66) | AD66: =U66+X66+AA66 | AE66: =V66+Y66+AB66 | AF66: =W66+Z66+AC66 | AG66: =R66+AD66 | AH66: =S66+AE66 | AI66: =T66+AF66 | AM66: =(O66-AG66)+AJ66 | AN66: =(P66-AH66)+AK66 | AO66: =(Q66-AI66)+AL66 | AP66: =IF(AM66>0, "Under",IF(AM66<0,"Over","")) | AQ66: =IF(AN66>0, "Under",IF(AN66<0,"Over","")) | AR66: =IF(AO66>0, "Under",IF(AO66<0,"Over",""))
A67: 0-4512 | B67: 0-4512-AC Testing | C67: 0 | D67: 0 | E67: 0 | F67: 231000 | G67: 0 | H67: 0 | I67: 0 | J67: 0 | K67: 0 | L67: 0 | M67: 0 | N67: 0 | O67: =L67+I67+F67+C67 | P67: =M67+J67+G67+D67 | Q67: =N67+K67+H67+E67 | R67: =SUMIFS('PO Log'!$E:$E,'PO Log'!$D:$D,'Category Table'!R$2,'PO Log'!$C:$C,'Category Table'!$A67) | S67: =SUMIFS('PO Log'!$E:$E,'PO Log'!$D:$D,'Category Table'!S$2,'PO Log'!$C:$C,'Category Table'!$A67) | T67: =SUMIFS('PO Log'!$E:$E,'PO Log'!$D:$D,'Category Table'!T$2,'PO Log'!$C:$C,'Category Table'!$A67) | U67: =SUMIFS('Committments Dump'!$Q:$Q,'Committments Dump'!$C:$C,'Category Table'!U$2,'Committments Dump'!$B:$B,'Category Table'!$A67) | V67: =SUMIFS('Committments Dump'!$Q:$Q,'Committments Dump'!$C:$C,'Category Table'!V$2,'Committments Dump'!$B:$B,'Category Table'!$A67) | W67: =SUMIFS('Committments Dump'!$Q:$Q,'Committments Dump'!$C:$C,'Category Table'!W$2,'Committments Dump'!$B:$B,'Category Table'!$A67) | X67: =SUMIFS('Committments Dump'!$R:$R,'Committments Dump'!$C:$C,'Category Table'!X$2,'Committments Dump'!$B:$B,'Category Table'!$A67) | Y67: =SUMIFS('Committments Dump'!$R:$R,'Committments Dump'!$C:$C,'Category Table'!Y$2,'Committments Dump'!$B:$B,'Category Table'!$A67) | Z67: =SUMIFS('Committments Dump'!$R:$R,'Committments Dump'!$C:$C,'Category Table'!Z$2,'Committments Dump'!$B:$B,'Category Table'!$A67) | AA67: =SUMIFS('Committments Dump'!$S:$S,'Committments Dump'!$C:$C,'Category Table'!AA$2,'Committments Dump'!$B:$B,'Category Table'!$A67) | AB67: =SUMIFS('Committments Dump'!$S:$S,'Committments Dump'!$C:$C,'Category Table'!AB$2,'Committments Dump'!$B:$B,'Category Table'!$A67) | AC67: =SUMIFS('Committments Dump'!$S:$S,'Committments Dump'!$C:$C,'Category Table'!AC$2,'Committments Dump'!$B:$B,'Category Table'!$A67) | AD67: =U67+X67+AA67 | AE67: =V67+Y67+AB67 | AF67: =W67+Z67+AC67 | AG67: =R67+AD67 | AH67: =S67+AE67 | AI67: =T67+AF67 | AM67: =(O67-AG67)+AJ67 | AN67: =(P67-AH67)+AK67 | AO67: =(Q67-AI67)+AL67 | AP67: =IF(AM67>0, "Under",IF(AM67<0,"Over","")) | AQ67: =IF(AN67>0, "Under",IF(AN67<0,"Over","")) | AR67: =IF(AO67>0, "Under",IF(AO67<0,"Over",""))
A68: 0-4520 | B68: 0-4520-Electrical MV Punch List | C68: 0 | D68: 0 | E68: 0 | F68: 0 | G68: 8004.85 | H68: 0 | I68: 0 | J68: 0 | K68: 0 | L68: 0 | M68: 0 | N68: 0 | O68: =L68+I68+F68+C68 | P68: =M68+J68+G68+D68 | Q68: =N68+K68+H68+E68 | R68: =SUMIFS('PO Log'!$E:$E,'PO Log'!$D:$D,'Category Table'!R$2,'PO Log'!$C:$C,'Category Table'!$A68) | S68: =SUMIFS('PO Log'!$E:$E,'PO Log'!$D:$D,'Category Table'!S$2,'PO Log'!$C:$C,'Category Table'!$A68) | T68: =SUMIFS('PO Log'!$E:$E,'PO Log'!$D:$D,'Category Table'!T$2,'PO Log'!$C:$C,'Category Table'!$A68) | U68: =SUMIFS('Committments Dump'!$Q:$Q,'Committments Dump'!$C:$C,'Category Table'!U$2,'Committments Dump'!$B:$B,'Category Table'!$A68) | V68: =SUMIFS('Committments Dump'!$Q:$Q,'Committments Dump'!$C:$C,'Category Table'!V$2,'Committments Dump'!$B:$B,'Category Table'!$A68) | W68: =SUMIFS('Committments Dump'!$Q:$Q,'Committments Dump'!$C:$C,'Category Table'!W$2,'Committments Dump'!$B:$B,'Category Table'!$A68) | X68: =SUMIFS('Committments Dump'!$R:$R,'Committments Dump'!$C:$C,'Category Table'!X$2,'Committments Dump'!$B:$B,'Category Table'!$A68) | Y68: =SUMIFS('Committments Dump'!$R:$R,'Committments Dump'!$C:$C,'Category Table'!Y$2,'Committments Dump'!$B:$B,'Category Table'!$A68) | Z68: =SUMIFS('Committments Dump'!$R:$R,'Committments Dump'!$C:$C,'Category Table'!Z$2,'Committments Dump'!$B:$B,'Category Table'!$A68) | AA68: =SUMIFS('Committments Dump'!$S:$S,'Committments Dump'!$C:$C,'Category Table'!AA$2,'Committments Dump'!$B:$B,'Category Table'!$A68) | AB68: =SUMIFS('Committments Dump'!$S:$S,'Committments Dump'!$C:$C,'Category Table'!AB$2,'Committments Dump'!$B:$B,'Category Table'!$A68) | AC68: =SUMIFS('Committments Dump'!$S:$S,'Committments Dump'!$C:$C,'Category Table'!AC$2,'Committments Dump'!$B:$B,'Category Table'!$A68) | AD68: =U68+X68+AA68 | AE68: =V68+Y68+AB68 | AF68: =W68+Z68+AC68 | AG68: =R68+AD68 | AH68: =S68+AE68 | AI68: =T68+AF68 | AM68: =(O68-AG68)+AJ68 | AN68: =(P68-AH68)+AK68 | AO68: =(Q68-AI68)+AL68 | AP68: =IF(AM68>0, "Under",IF(AM68<0,"Over","")) | AQ68: =IF(AN68>0, "Under",IF(AN68<0,"Over","")) | AR68: =IF(AO68>0, "Under",IF(AO68<0,"Over",""))
A69: 0-4700 | B69: 0-4700-Inv Skid Excavation | C69: 0 | D69: 0 | E69: 0 | F69: 0 | G69: 0 | H69: 0 | I69: 0 | J69: 0 | K69: 0 | L69: 0 | M69: 0 | N69: 0 | O69: =L69+I69+F69+C69 | P69: =M69+J69+G69+D69 | Q69: =N69+K69+H69+E69 | R69: =SUMIFS('PO Log'!$E:$E,'PO Log'!$D:$D,'Category Table'!R$2,'PO Log'!$C:$C,'Category Table'!$A69) | S69: =SUMIFS('PO Log'!$E:$E,'PO Log'!$D:$D,'Category Table'!S$2,'PO Log'!$C:$C,'Category Table'!$A69) | T69: =SUMIFS('PO Log'!$E:$E,'PO Log'!$D:$D,'Category Table'!T$2,'PO Log'!$C:$C,'Category Table'!$A69) | U69: =SUMIFS('Committments Dump'!$Q:$Q,'Committments Dump'!$C:$C,'Category Table'!U$2,'Committments Dump'!$B:$B,'Category Table'!$A69) | V69: =SUMIFS('Committments Dump'!$Q:$Q,'Committments Dump'!$C:$C,'Category Table'!V$2,'Committments Dump'!$B:$B,'Category Table'!$A69) | W69: =SUMIFS('Committments Dump'!$Q:$Q,'Committments Dump'!$C:$C,'Category Table'!W$2,'Committments Dump'!$B:$B,'Category Table'!$A69) | X69: =SUMIFS('Committments Dump'!$R:$R,'Committments Dump'!$C:$C,'Category Table'!X$2,'Committments Dump'!$B:$B,'Category Table'!$A69) | Y69: =SUMIFS('Committments Dump'!$R:$R,'Committments Dump'!$C:$C,'Category Table'!Y$2,'Committments Dump'!$B:$B,'Category Table'!$A69) | Z69: =SUMIFS('Committments Dump'!$R:$R,'Committments Dump'!$C:$C,'Category Table'!Z$2,'Committments Dump'!$B:$B,'Category Table'!$A69) | AA69: =SUMIFS('Committments Dump'!$S:$S,'Committments Dump'!$C:$C,'Category Table'!AA$2,'Committments Dump'!$B:$B,'Category Table'!$A69) | AB69: =SUMIFS('Committments Dump'!$S:$S,'Committments Dump'!$C:$C,'Category Table'!AB$2,'Committments Dump'!$B:$B,'Category Table'!$A69) | AC69: =SUMIFS('Committments Dump'!$S:$S,'Committments Dump'!$C:$C,'Category Table'!AC$2,'Committments Dump'!$B:$B,'Category Table'!$A69) | AD69: =U69+X69+AA69 | AE69: =V69+Y69+AB69 | AF69: =W69+Z69+AC69 | AG69: =R69+AD69 | AH69: =S69+AE69 | AI69: =T69+AF69 | AM69: =(O69-AG69)+AJ69 | AN69: =(P69-AH69)+AK69 | AO69: =(Q69-AI69)+AL69 | AP69: =IF(AM69>0, "Under",IF(AM69<0,"Over","")) | AQ69: =IF(AN69>0, "Under",IF(AN69<0,"Over","")) | AR69: =IF(AO69>0, "Under",IF(AO69<0,"Over",""))
A70: 0-4701 | B70: 0-4701-Inv Skid Conduit | C70: 0 | D70: 0 | E70: 0 | F70: 0 | G70: 3096.4138 | H70: 0 | I70: 0 | J70: 0 | K70: 0 | L70: 0 | M70: 0 | N70: 0 | O70: =L70+I70+F70+C70 | P70: =M70+J70+G70+D70 | Q70: =N70+K70+H70+E70 | R70: =SUMIFS('PO Log'!$E:$E,'PO Log'!$D:$D,'Category Table'!R$2,'PO Log'!$C:$C,'Category Table'!$A70) | S70: =SUMIFS('PO Log'!$E:$E,'PO Log'!$D:$D,'Category Table'!S$2,'PO Log'!$C:$C,'Category Table'!$A70) | T70: =SUMIFS('PO Log'!$E:$E,'PO Log'!$D:$D,'Category Table'!T$2,'PO Log'!$C:$C,'Category Table'!$A70) | U70: =SUMIFS('Committments Dump'!$Q:$Q,'Committments Dump'!$C:$C,'Category Table'!U$2,'Committments Dump'!$B:$B,'Category Table'!$A70) | V70: =SUMIFS('Committments Dump'!$Q:$Q,'Committments Dump'!$C:$C,'Category Table'!V$2,'Committments Dump'!$B:$B,'Category Table'!$A70) | W70: =SUMIFS('Committments Dump'!$Q:$Q,'Committments Dump'!$C:$C,'Category Table'!W$2,'Committments Dump'!$B:$B,'Category Table'!$A70) | X70: =SUMIFS('Committments Dump'!$R:$R,'Committments Dump'!$C:$C,'Category Table'!X$2,'Committments Dump'!$B:$B,'Category Table'!$A70) | Y70: =SUMIFS('Committments Dump'!$R:$R,'Committments Dump'!$C:$C,'Category Table'!Y$2,'Committments Dump'!$B:$B,'Category Table'!$A70) | Z70: =SUMIFS('Committments Dump'!$R:$R,'Committments Dump'!$C:$C,'Category Table'!Z$2,'Committments Dump'!$B:$B,'Category Table'!$A70) | AA70: =SUMIFS('Committments Dump'!$S:$S,'Committments Dump'!$C:$C,'Category Table'!AA$2,'Committments Dump'!$B:$B,'Category Table'!$A70) | AB70: =SUMIFS('Committments Dump'!$S:$S,'Committments Dump'!$C:$C,'Category Table'!AB$2,'Committments Dump'!$B:$B,'Category Table'!$A70) | AC70: =SUMIFS('Committments Dump'!$S:$S,'Committments Dump'!$C:$C,'Category Table'!AC$2,'Committments Dump'!$B:$B,'Category Table'!$A70) | AD70: =U70+X70+AA70 | AE70: =V70+Y70+AB70 | AF70: =W70+Z70+AC70 | AG70: =R70+AD70 | AH70: =S70+AE70 | AI70: =T70+AF70 | AM70: =(O70-AG70)+AJ70 | AN70: =(P70-AH70)+AK70 | AO70: =(Q70-AI70)+AL70 | AP70: =IF(AM70>0, "Under",IF(AM70<0,"Over","")) | AQ70: =IF(AN70>0, "Under",IF(AN70<0,"Over","")) | AR70: =IF(AO70>0, "Under",IF(AO70<0,"Over",""))
A71: 0-4702 | B71: 0-4702-Inv Skid Backfill | C71: 0 | D71: 0 | E71: 0 | F71: 0 | G71: 0 | H71: 59537.5 | I71: 0 | J71: 0 | K71: 0 | L71: 0 | M71: 0 | N71: 0 | O71: =L71+I71+F71+C71 | P71: =M71+J71+G71+D71 | Q71: =N71+K71+H71+E71 | R71: =SUMIFS('PO Log'!$E:$E,'PO Log'!$D:$D,'Category Table'!R$2,'PO Log'!$C:$C,'Category Table'!$A71) | S71: =SUMIFS('PO Log'!$E:$E,'PO Log'!$D:$D,'Category Table'!S$2,'PO Log'!$C:$C,'Category Table'!$A71) | T71: =SUMIFS('PO Log'!$E:$E,'PO Log'!$D:$D,'Category Table'!T$2,'PO Log'!$C:$C,'Category Table'!$A71) | U71: =SUMIFS('Committments Dump'!$Q:$Q,'Committments Dump'!$C:$C,'Category Table'!U$2,'Committments Dump'!$B:$B,'Category Table'!$A71) | V71: =SUMIFS('Committments Dump'!$Q:$Q,'Committments Dump'!$C:$C,'Category Table'!V$2,'Committments Dump'!$B:$B,'Category Table'!$A71) | W71: =SUMIFS('Committments Dump'!$Q:$Q,'Committments Dump'!$C:$C,'Category Table'!W$2,'Committments Dump'!$B:$B,'Category Table'!$A71) | X71: =SUMIFS('Committments Dump'!$R:$R,'Committments Dump'!$C:$C,'Category Table'!X$2,'Committments Dump'!$B:$B,'Category Table'!$A71) | Y71: =SUMIFS('Committments Dump'!$R:$R,'Committments Dump'!$C:$C,'Category Table'!Y$2,'Committments Dump'!$B:$B,'Category Table'!$A71) | Z71: =SUMIFS('Committments Dump'!$R:$R,'Committments Dump'!$C:$C,'Category Table'!Z$2,'Committments Dump'!$B:$B,'Category Table'!$A71) | AA71: =SUMIFS('Committments Dump'!$S:$S,'Committments Dump'!$C:$C,'Category Table'!AA$2,'Committments Dump'!$B:$B,'Category Table'!$A71) | AB71: =SUMIFS('Committments Dump'!$S:$S,'Committments Dump'!$C:$C,'Category Table'!AB$2,'Committments Dump'!$B:$B,'Category Table'!$A71) | AC71: =SUMIFS('Committments Dump'!$S:$S,'Committments Dump'!$C:$C,'Category Table'!AC$2,'Committments Dump'!$B:$B,'Category Table'!$A71) | AD71: =U71+X71+AA71 | AE71: =V71+Y71+AB71 | AF71: =W71+Z71+AC71 | AG71: =R71+AD71 | AH71: =S71+AE71 | AI71: =T71+AF71 | AM71: =(O71-AG71)+AJ71 | AN71: =(P71-AH71)+AK71 | AO71: =(Q71-AI71)+AL71 | AP71: =IF(AM71>0, "Under",IF(AM71<0,"Over","")) | AQ71: =IF(AN71>0, "Under",IF(AN71<0,"Over","")) | AR71: =IF(AO71>0, "Under",IF(AO71<0,"Over",""))
A72: 0-4703 | B72: 0-4703-Inv Pile Caps | C72: 0 | D72: 0 | E72: 0 | F72: 0 | G72: 0 | H72: 8182.95 | I72: 0 | J72: 0 | K72: 0 | L72: 0 | M72: 0 | N72: 0 | O72: =L72+I72+F72+C72 | P72: =M72+J72+G72+D72 | Q72: =N72+K72+H72+E72 | R72: =SUMIFS('PO Log'!$E:$E,'PO Log'!$D:$D,'Category Table'!R$2,'PO Log'!$C:$C,'Category Table'!$A72) | S72: =SUMIFS('PO Log'!$E:$E,'PO Log'!$D:$D,'Category Table'!S$2,'PO Log'!$C:$C,'Category Table'!$A72) | T72: =SUMIFS('PO Log'!$E:$E,'PO Log'!$D:$D,'Category Table'!T$2,'PO Log'!$C:$C,'Category Table'!$A72) | U72: =SUMIFS('Committments Dump'!$Q:$Q,'Committments Dump'!$C:$C,'Category Table'!U$2,'Committments Dump'!$B:$B,'Category Table'!$A72) | V72: =SUMIFS('Committments Dump'!$Q:$Q,'Committments Dump'!$C:$C,'Category Table'!V$2,'Committments Dump'!$B:$B,'Category Table'!$A72) | W72: =SUMIFS('Committments Dump'!$Q:$Q,'Committments Dump'!$C:$C,'Category Table'!W$2,'Committments Dump'!$B:$B,'Category Table'!$A72) | X72: =SUMIFS('Committments Dump'!$R:$R,'Committments Dump'!$C:$C,'Category Table'!X$2,'Committments Dump'!$B:$B,'Category Table'!$A72) | Y72: =SUMIFS('Committments Dump'!$R:$R,'Committments Dump'!$C:$C,'Category Table'!Y$2,'Committments Dump'!$B:$B,'Category Table'!$A72) | Z72: =SUMIFS('Committments Dump'!$R:$R,'Committments Dump'!$C:$C,'Category Table'!Z$2,'Committments Dump'!$B:$B,'Category Table'!$A72) | AA72: =SUMIFS('Committments Dump'!$S:$S,'Committments Dump'!$C:$C,'Category Table'!AA$2,'Committments Dump'!$B:$B,'Category Table'!$A72) | AB72: =SUMIFS('Committments Dump'!$S:$S,'Committments Dump'!$C:$C,'Category Table'!AB$2,'Committments Dump'!$B:$B,'Category Table'!$A72) | AC72: =SUMIFS('Committments Dump'!$S:$S,'Committments Dump'!$C:$C,'Category Table'!AC$2,'Committments Dump'!$B:$B,'Category Table'!$A72) | AD72: =U72+X72+AA72 | AE72: =V72+Y72+AB72 | AF72: =W72+Z72+AC72 | AG72: =R72+AD72 | AH72: =S72+AE72 | AI72: =T72+AF72 | AM72: =(O72-AG72)+AJ72 | AN72: =(P72-AH72)+AK72 | AO72: =(Q72-AI72)+AL72 | AP72: =IF(AM72>0, "Under",IF(AM72<0,"Over","")) | AQ72: =IF(AN72>0, "Under",IF(AN72<0,"Over","")) | AR72: =IF(AO72>0, "Under",IF(AO72<0,"Over",""))
... A87: 0-4109 | B87: 0-4109-Site Roadways | C87: 0 | D87: 0 | E87: 0 | F87: 0 | G87: 0 | H87: 1256921.1 | I87: 0 | J87: 0 | K87: 0 | L87: 0 | M87: 0 | N87: 1993005 | O87: =L87+I87+F87+C87 | P87: =M87+J87+G87+D87 | Q87: =N87+K87+H87+E87 | R87: =SUMIFS('PO Log'!$E:$E,'PO Log'!$D:$D,'Category Table'!R$2,'PO Log'!$C:$C,'Category Table'!$A87) | S87: =SUMIFS('PO Log'!$E:$E,'PO Log'!$D:$D,'Category Table'!S$2,'PO Log'!$C:$C,'Category Table'!$A87) | T87: =SUMIFS('PO Log'!$E:$E,'PO Log'!$D:$D,'Category Table'!T$2,'PO Log'!$C:$C,'Category Table'!$A87) | U87: =SUMIFS('Committments Dump'!$Q:$Q,'Committments Dump'!$C:$C,'Category Table'!U$2,'Committments Dump'!$B:$B,'Category Table'!$A87) | V87: =SUMIFS('Committments Dump'!$Q:$Q,'Committments Dump'!$C:$C,'Category Table'!V$2,'Committments Dump'!$B:$B,'Category Table'!$A87) | W87: =SUMIFS('Committments Dump'!$Q:$Q,'Committments Dump'!$C:$C,'Category Table'!W$2,'Committments Dump'!$B:$B,'Category Table'!$A87) | X87: =SUMIFS('Committments Dump'!$R:$R,'Committments Dump'!$C:$C,'Category Table'!X$2,'Committments Dump'!$B:$B,'Category Table'!$A87) | Y87: =SUMIFS('Committments Dump'!$R:$R,'Committments Dump'!$C:$C,'Category Table'!Y$2,'Committments Dump'!$B:$B,'Category Table'!$A87) | Z87: =SUMIFS('Committments Dump'!$R:$R,'Committments Dump'!$C:$C,'Category Table'!Z$2,'Committments Dump'!$B:$B,'Category Table'!$A87) | AA87: =SUMIFS('Committments Dump'!$S:$S,'Committments Dump'!$C:$C,'Category Table'!AA$2,'Committments Dump'!$B:$B,'Category Table'!$A87) | AB87: =SUMIFS('Committments Dump'!$S:$S,'Committments Dump'!$C:$C,'Category Table'!AB$2,'Committments Dump'!$B:$B,'Category Table'!$A87) | AC87: =SUMIFS('Committments Dump'!$S:$S,'Committments Dump'!$C:$C,'Category Table'!AC$2,'Committments Dump'!$B:$B,'Category Table'!$A87) | AD87: =U87+X87+AA87 | AE87: =V87+Y87+AB87 | AF87: =W87+Z87+AC87 | AG87: =R87+AD87 | AH87: =S87+AE87 | AI87: =T87+AF87 | AM87: =(O87-AG87)+AJ87 | AN87: =(P87-AH87)+AK87 | AO87: =(Q87-AI87)+AL87 | AP87: =IF(AM87>0, "Under",IF(AM87<0,"Over","")) | AQ87: =IF(AN87>0, "Under",IF(AN87<0,"Over","")) | AR87: =IF(AO87>0, "Under",IF(AO87<0,"Over",""))
A88: 0-4015-01 | B88: 0-4015-01-Survey | C88: 0 | D88: 1196.88 | E88: 0 | G88: 9755.8065 | H88: 5412.5 | I88: 0 | J88: 0 | K88: 0 | L88: 0 | M88: -8.5265128e-14 | N88: 0 | O88: =L88+I88+F88+C88 | P88: =M88+J88+G88+D88 | Q88: =N88+K88+H88+E88 | R88: =SUMIFS('PO Log'!$E:$E,'PO Log'!$D:$D,'Category Table'!R$2,'PO Log'!$C:$C,'Category Table'!$A88) | S88: =SUMIFS('PO Log'!$E:$E,'PO Log'!$D:$D,'Category Table'!S$2,'PO Log'!$C:$C,'Category Table'!$A88) | T88: =SUMIFS('PO Log'!$E:$E,'PO Log'!$D:$D,'Category Table'!T$2,'PO Log'!$C:$C,'Category Table'!$A88) | U88: =SUMIFS('Committments Dump'!$Q:$Q,'Committments Dump'!$C:$C,'Category Table'!U$2,'Committments Dump'!$B:$B,'Category Table'!$A88) | V88: =SUMIFS('Committments Dump'!$Q:$Q,'Committments Dump'!$C:$C,'Category Table'!V$2,'Committments Dump'!$B:$B,'Category Table'!$A88) | W88: =SUMIFS('Committments Dump'!$Q:$Q,'Committments Dump'!$C:$C,'Category Table'!W$2,'Committments Dump'!$B:$B,'Category Table'!$A88) | X88: =SUMIFS('Committments Dump'!$R:$R,'Committments Dump'!$C:$C,'Category Table'!X$2,'Committments Dump'!$B:$B,'Category Table'!$A88) | Y88: =SUMIFS('Committments Dump'!$R:$R,'Committments Dump'!$C:$C,'Category Table'!Y$2,'Committments Dump'!$B:$B,'Category Table'!$A88) | Z88: =SUMIFS('Committments Dump'!$R:$R,'Committments Dump'!$C:$C,'Category Table'!Z$2,'Committments Dump'!$B:$B,'Category Table'!$A88) | AA88: =SUMIFS('Committments Dump'!$S:$S,'Committments Dump'!$C:$C,'Category Table'!AA$2,'Committments Dump'!$B:$B,'Category Table'!$A88) | AB88: =SUMIFS('Committments Dump'!$S:$S,'Committments Dump'!$C:$C,'Category Table'!AB$2,'Committments Dump'!$B:$B,'Category Table'!$A88) | AC88: =SUMIFS('Committments Dump'!$S:$S,'Committments Dump'!$C:$C,'Category Table'!AC$2,'Committments Dump'!$B:$B,'Category Table'!$A88) | AD88: =U88+X88+AA88 | AE88: =V88+Y88+AB88 | AF88: =W88+Z88+AC88 | AG88: =R88+AD88 | AH88: =S88+AE88 | AI88: =T88+AF88 | AM88: =(O88-AG88)+AJ88 | AN88: =(P88-AH88)+AK88 | AO88: =(Q88-AI88)+AL88 | AP88: =IF(AM88>0, "Under",IF(AM88<0,"Over","")) | AQ88: =IF(AN88>0, "Under",IF(AN88<0,"Over","")) | AR88: =IF(AO88>0, "Under",IF(AO88<0,"Over",""))
A89: 0-4110 | B89: 0-4110-Ditches | C89: 0 | D89: 0 | E89: 0 | F89: 0 | G89: 361.68802 | H89: 86810.01 | I89: 0 | J89: 0 | K89: 0 | L89: 0 | M89: 0 | N89: 0 | O89: =L89+I89+F89+C89 | P89: =M89+J89+G89+D89 | Q89: =N89+K89+H89+E89 | R89: =SUMIFS('PO Log'!$E:$E,'PO Log'!$D:$D,'Category Table'!R$2,'PO Log'!$C:$C,'Category Table'!$A89) | S89: =SUMIFS('PO Log'!$E:$E,'PO Log'!$D:$D,'Category Table'!S$2,'PO Log'!$C:$C,'Category Table'!$A89) | T89: =SUMIFS('PO Log'!$E:$E,'PO Log'!$D:$D,'Category Table'!T$2,'PO Log'!$C:$C,'Category Table'!$A89) | U89: =SUMIFS('Committments Dump'!$Q:$Q,'Committments Dump'!$C:$C,'Category Table'!U$2,'Committments Dump'!$B:$B,'Category Table'!$A89) | V89: =SUMIFS('Committments Dump'!$Q:$Q,'Committments Dump'!$C:$C,'Category Table'!V$2,'Committments Dump'!$B:$B,'Category Table'!$A89) | W89: =SUMIFS('Committments Dump'!$Q:$Q,'Committments Dump'!$C:$C,'Category Table'!W$2,'Committments Dump'!$B:$B,'Category Table'!$A89) | X89: =SUMIFS('Committments Dump'!$R:$R,'Committments Dump'!$C:$C,'Category Table'!X$2,'Committments Dump'!$B:$B,'Category Table'!$A89) | Y89: =SUMIFS('Committments Dump'!$R:$R,'Committments Dump'!$C:$C,'Category Table'!Y$2,'Committments Dump'!$B:$B,'Category Table'!$A89) | Z89: =SUMIFS('Committments Dump'!$R:$R,'Committments Dump'!$C:$C,'Category Table'!Z$2,'Committments Dump'!$B:$B,'Category Table'!$A89) | AA89: =SUMIFS('Committments Dump'!$S:$S,'Committments Dump'!$C:$C,'Category Table'!AA$2,'Committments Dump'!$B:$B,'Category Table'!$A89) | AB89: =SUMIFS('Committments Dump'!$S:$S,'Committments Dump'!$C:$C,'Category Table'!AB$2,'Committments Dump'!$B:$B,'Category Table'!$A89) | AC89: =SUMIFS('Committments Dump'!$S:$S,'Committments Dump'!$C:$C,'Category Table'!AC$2,'Committments Dump'!$B:$B,'Category Table'!$A89) | AD89: =U89+X89+AA89 | AE89: =V89+Y89+AB89 | AF89: =W89+Z89+AC89 | AG89: =R89+AD89 | AH89: =S89+AE89 | AI89: =T89+AF89 | AM89: =(O89-AG89)+AJ89 | AN89: =(P89-AH89)+AK89 | AO89: =(Q89-AI89)+AL89 | AP89: =IF(AM89>0, "Under",IF(AM89<0,"Over","")) | AQ89: =IF(AN89>0, "Under",IF(AN89<0,"Over","")) | AR89: =IF(AO89>0, "Under",IF(AO89<0,"Over",""))
A90: 0-4110-01 | B90: 0-4110-01-Canal Bridge Repair | C90: 0 | D90: 0 | E90: 0 | F90: 70000 | G90: 0 | H90: 0 | I90: 0 | J90: 0 | K90: 0 | L90: 0 | M90: 0 | N90: 0 | O90: =L90+I90+F90+C90 | P90: =M90+J90+G90+D90 | Q90: =N90+K90+H90+E90 | R90: =SUMIFS('PO Log'!$E:$E,'PO Log'!$D:$D,'Category Table'!R$2,'PO Log'!$C:$C,'Category Table'!$A90) | S90: =SUMIFS('PO Log'!$E:$E,'PO Log'!$D:$D,'Category Table'!S$2,'PO Log'!$C:$C,'Category Table'!$A90) | T90: =SUMIFS('PO Log'!$E:$E,'PO Log'!$D:$D,'Category Table'!T$2,'PO Log'!$C:$C,'Category Table'!$A90) | U90: =SUMIFS('Committments Dump'!$Q:$Q,'Committments Dump'!$C:$C,'Category Table'!U$2,'Committments Dump'!$B:$B,'Category Table'!$A90) | V90: =SUMIFS('Committments Dump'!$Q:$Q,'Committments Dump'!$C:$C,'Category Table'!V$2,'Committments Dump'!$B:$B,'Category Table'!$A90) | W90: =SUMIFS('Committments Dump'!$Q:$Q,'Committments Dump'!$C:$C,'Category Table'!W$2,'Committments Dump'!$B:$B,'Category Table'!$A90) | X90: =SUMIFS('Committments Dump'!$R:$R,'Committments Dump'!$C:$C,'Category Table'!X$2,'Committments Dump'!$B:$B,'Category Table'!$A90) | Y90: =SUMIFS('Committments Dump'!$R:$R,'Committments Dump'!$C:$C,'Category Table'!Y$2,'Committments Dump'!$B:$B,'Category Table'!$A90) | Z90: =SUMIFS('Committments Dump'!$R:$R,'Committments Dump'!$C:$C,'Category Table'!Z$2,'Committments Dump'!$B:$B,'Category Table'!$A90) | AA90: =SUMIFS('Committments Dump'!$S:$S,'Committments Dump'!$C:$C,'Category Table'!AA$2,'Committments Dump'!$B:$B,'Category Table'!$A90) | AB90: =SUMIFS('Committments Dump'!$S:$S,'Committments Dump'!$C:$C,'Category Table'!AB$2,'Committments Dump'!$B:$B,'Category Table'!$A90) | AC90: =SUMIFS('Committments Dump'!$S:$S,'Committments Dump'!$C:$C,'Category Table'!AC$2,'Committments Dump'!$B:$B,'Category Table'!$A90) | AD90: =U90+X90+AA90 | AE90: =V90+Y90+AB90 | AF90: =W90+Z90+AC90 | AG90: =R90+AD90 | AH90: =S90+AE90 | AI90: =T90+AF90 | AM90: =(O90-AG90)+AJ90 | AN90: =(P90-AH90)+AK90 | AO90: =(Q90-AI90)+AL90 | AP90: =IF(AM90>0, "Under",IF(AM90<0,"Over","")) | AQ90: =IF(AN90>0, "Under",IF(AN90<0,"Over","")) | AR90: =IF(AO90>0, "Under",IF(AO90<0,"Over",""))
A91: 0-4111 | B91: 0-4111-Compaction Testing | C91: 0 | D91: 0 | E91: 0 | F91: 166284 | G91: 0 | H91: 0 | I91: 0 | J91: 0 | K91: 0 | L91: 0 | M91: 55500 | N91: 0 | O91: =L91+I91+F91+C91 | P91: =M91+J91+G91+D91 | Q91: =N91+K91+H91+E91 | R91: =SUMIFS('PO Log'!$E:$E,'PO Log'!$D:$D,'Category Table'!R$2,'PO Log'!$C:$C,'Category Table'!$A91) | S91: =SUMIFS('PO Log'!$E:$E,'PO Log'!$D:$D,'Category Table'!S$2,'PO Log'!$C:$C,'Category Table'!$A91) | T91: =SUMIFS('PO Log'!$E:$E,'PO Log'!$D:$D,'Category Table'!T$2,'PO Log'!$C:$C,'Category Table'!$A91) | U91: =SUMIFS('Committments Dump'!$Q:$Q,'Committments Dump'!$C:$C,'Category Table'!U$2,'Committments Dump'!$B:$B,'Category Table'!$A91) | V91: =SUMIFS('Committments Dump'!$Q:$Q,'Committments Dump'!$C:$C,'Category Table'!V$2,'Committments Dump'!$B:$B,'Category Table'!$A91) | W91: =SUMIFS('Committments Dump'!$Q:$Q,'Committments Dump'!$C:$C,'Category Table'!W$2,'Committments Dump'!$B:$B,'Category Table'!$A91) | X91: =SUMIFS('Committments Dump'!$R:$R,'Committments Dump'!$C:$C,'Category Table'!X$2,'Committments Dump'!$B:$B,'Category Table'!$A91) | Y91: =SUMIFS('Committments Dump'!$R:$R,'Committments Dump'!$C:$C,'Category Table'!Y$2,'Committments Dump'!$B:$B,'Category Table'!$A91) | Z91: =SUMIFS('Committments Dump'!$R:$R,'Committments Dump'!$C:$C,'Category Table'!Z$2,'Committments Dump'!$B:$B,'Category Table'!$A91) | AA91: =SUMIFS('Committments Dump'!$S:$S,'Committments Dump'!$C:$C,'Category Table'!AA$2,'Committments Dump'!$B:$B,'Category Table'!$A91) | AB91: =SUMIFS('Committments Dump'!$S:$S,'Committments Dump'!$C:$C,'Category Table'!AB$2,'Committments Dump'!$B:$B,'Category Table'!$A91) | AC91: =SUMIFS('Committments Dump'!$S:$S,'Committments Dump'!$C:$C,'Category Table'!AC$2,'Committments Dump'!$B:$B,'Category Table'!$A91) | AD91: =U91+X91+AA91 | AE91: =V91+Y91+AB91 | AF91: =W91+Z91+AC91 | AG91: =R91+AD91 | AH91: =S91+AE91 | AI91: =T91+AF91 | AM91: =(O91-AG91)+AJ91 | AN91: =(P91-AH91)+AK91 | AO91: =(Q91-AI91)+AL91 | AP91: =IF(AM91>0, "Under",IF(AM91<0,"Over","")) | AQ91: =IF(AN91>0, "Under",IF(AN91<0,"Over","")) | AR91: =IF(AO91>0, "Under",IF(AO91<0,"Over",""))
A92: 0-4113 | B92: 0-4113-Construction Entrance | C92: 0 | D92: 0 | E92: 0 | F92: 0 | G92: 0 | H92: 114993.97 | I92: 0 | J92: 0 | K92: 0 | L92: 0 | M92: 0 | N92: 0 | O92: =L92+I92+F92+C92 | P92: =M92+J92+G92+D92 | Q92: =N92+K92+H92+E92 | R92: =SUMIFS('PO Log'!$E:$E,'PO Log'!$D:$D,'Category Table'!R$2,'PO Log'!$C:$C,'Category Table'!$A92) | S92: =SUMIFS('PO Log'!$E:$E,'PO Log'!$D:$D,'Category Table'!S$2,'PO Log'!$C:$C,'Category Table'!$A92) | T92: =SUMIFS('PO Log'!$E:$E,'PO Log'!$D:$D,'Category Table'!T$2,'PO Log'!$C:$C,'Category Table'!$A92) | U92: =SUMIFS('Committments Dump'!$Q:$Q,'Committments Dump'!$C:$C,'Category Table'!U$2,'Committments Dump'!$B:$B,'Category Table'!$A92) | V92: =SUMIFS('Committments Dump'!$Q:$Q,'Committments Dump'!$C:$C,'Category Table'!V$2,'Committments Dump'!$B:$B,'Category Table'!$A92) | W92: =SUMIFS('Committments Dump'!$Q:$Q,'Committments Dump'!$C:$C,'Category Table'!W$2,'Committments Dump'!$B:$B,'Category Table'!$A92) | X92: =SUMIFS('Committments Dump'!$R:$R,'Committments Dump'!$C:$C,'Category Table'!X$2,'Committments Dump'!$B:$B,'Category Table'!$A92) | Y92: =SUMIFS('Committments Dump'!$R:$R,'Committments Dump'!$C:$C,'Category Table'!Y$2,'Committments Dump'!$B:$B,'Category Table'!$A92) | Z92: =SUMIFS('Committments Dump'!$R:$R,'Committments Dump'!$C:$C,'Category Table'!Z$2,'Committments Dump'!$B:$B,'Category Table'!$A92) | AA92: =SUMIFS('Committments Dump'!$S:$S,'Committments Dump'!$C:$C,'Category Table'!AA$2,'Committments Dump'!$B:$B,'Category Table'!$A92) | AB92: =SUMIFS('Committments Dump'!$S:$S,'Committments Dump'!$C:$C,'Category Table'!AB$2,'Committments Dump'!$B:$B,'Category Table'!$A92) | AC92: =SUMIFS('Committments Dump'!$S:$S,'Committments Dump'!$C:$C,'Category Table'!AC$2,'Committments Dump'!$B:$B,'Category Table'!$A92) | AD92: =U92+X92+AA92 | AE92: =V92+Y92+AB92 | AF92: =W92+Z92+AC92 | AG92: =R92+AD92 | AH92: =S92+AE92 | AI92: =T92+AF92 | AM92: =(O92-AG92)+AJ92 | AN92: =(P92-AH92)+AK92 | AO92: =(Q92-AI92)+AL92 | AP92: =IF(AM92>0, "Under",IF(AM92<0,"Over","")) | AQ92: =IF(AN92>0, "Under",IF(AN92<0,"Over","")) | AR92: =IF(AO92>0, "Under",IF(AO92<0,"Over",""))
A93: 0-4115-01 | B93: 0-4115-01-Clean Up | C93: 0 | D93: 0 | E93: 0 | F93: 1200 | G93: 0 | H93: 0 | I93: 0 | J93: 0 | K93: 0 | L93: 0 | M93: 0 | N93: 0 | O93: =L93+I93+F93+C93 | P93: =M93+J93+G93+D93 | Q93: =N93+K93+H93+E93 | R93: =SUMIFS('PO Log'!$E:$E,'PO Log'!$D:$D,'Category Table'!R$2,'PO Log'!$C:$C,'Category Table'!$A93) | S93: =SUMIFS('PO Log'!$E:$E,'PO Log'!$D:$D,'Category Table'!S$2,'PO Log'!$C:$C,'Category Table'!$A93) | T93: =SUMIFS('PO Log'!$E:$E,'PO Log'!$D:$D,'Category Table'!T$2,'PO Log'!$C:$C,'Category Table'!$A93) | U93: =SUMIFS('Committments Dump'!$Q:$Q,'Committments Dump'!$C:$C,'Category Table'!U$2,'Committments Dump'!$B:$B,'Category Table'!$A93) | V93: =SUMIFS('Committments Dump'!$Q:$Q,'Committments Dump'!$C:$C,'Category Table'!V$2,'Committments Dump'!$B:$B,'Category Table'!$A93) | W93: =SUMIFS('Committments Dump'!$Q:$Q,'Committments Dump'!$C:$C,'Category Table'!W$2,'Committments Dump'!$B:$B,'Category Table'!$A93) | X93: =SUMIFS('Committments Dump'!$R:$R,'Committments Dump'!$C:$C,'Category Table'!X$2,'Committments Dump'!$B:$B,'Category Table'!$A93) | Y93: =SUMIFS('Committments Dump'!$R:$R,'Committments Dump'!$C:$C,'Category Table'!Y$2,'Committments Dump'!$B:$B,'Category Table'!$A93) | Z93: =SUMIFS('Committments Dump'!$R:$R,'Committments Dump'!$C:$C,'Category Table'!Z$2,'Committments Dump'!$B:$B,'Category Table'!$A93) | AA93: =SUMIFS('Committments Dump'!$S:$S,'Committments Dump'!$C:$C,'Category Table'!AA$2,'Committments Dump'!$B:$B,'Category Table'!$A93) | AB93: =SUMIFS('Committments Dump'!$S:$S,'Committments Dump'!$C:$C,'Category Table'!AB$2,'Committments Dump'!$B:$B,'Category Table'!$A93) | AC93: =SUMIFS('Committments Dump'!$S:$S,'Committments Dump'!$C:$C,'Category Table'!AC$2,'Committments Dump'!$B:$B,'Category Table'!$A93) | AD93: =U93+X93+AA93 | AE93: =V93+Y93+AB93 | AF93: =W93+Z93+AC93 | AG93: =R93+AD93 | AH93: =S93+AE93 | AI93: =T93+AF93 | AM93: =(O93-AG93)+AJ93 | AN93: =(P93-AH93)+AK93 | AO93: =(Q93-AI93)+AL93 | AP93: =IF(AM93>0, "Under",IF(AM93<0,"Over","")) | AQ93: =IF(AN93>0, "Under",IF(AN93<0,"Over","")) | AR93: =IF(AO93>0, "Under",IF(AO93<0,"Over",""))
A94: 0-4116 | B94: 0-4116-Bush Hog | C94: 0 | D94: 0 | E94: 0 | F94: 0 | G94: 0 | H94: 53177.5 | I94: 0 | J94: 0 | K94: 0 | L94: 0 | M94: 0 | N94: 0 | O94: =L94+I94+F94+C94 | P94: =M94+J94+G94+D94 | Q94: =N94+K94+H94+E94 | R94: =SUMIFS('PO Log'!$E:$E,'PO Log'!$D:$D,'Category Table'!R$2,'PO Log'!$C:$C,'Category Table'!$A94) | S94: =SUMIFS('PO Log'!$E:$E,'PO Log'!$D:$D,'Category Table'!S$2,'PO Log'!$C:$C,'Category Table'!$A94) | T94: =SUMIFS('PO Log'!$E:$E,'PO Log'!$D:$D,'Category Table'!T$2,'PO Log'!$C:$C,'Category Table'!$A94) | U94: =SUMIFS('Committments Dump'!$Q:$Q,'Committments Dump'!$C:$C,'Category Table'!U$2,'Committments Dump'!$B:$B,'Category Table'!$A94) | V94: =SUMIFS('Committments Dump'!$Q:$Q,'Committments Dump'!$C:$C,'Category Table'!V$2,'Committments Dump'!$B:$B,'Category Table'!$A94) | W94: =SUMIFS('Committments Dump'!$Q:$Q,'Committments Dump'!$C:$C,'Category Table'!W$2,'Committments Dump'!$B:$B,'Category Table'!$A94) | X94: =SUMIFS('Committments Dump'!$R:$R,'Committments Dump'!$C:$C,'Category Table'!X$2,'Committments Dump'!$B:$B,'Category Table'!$A94) | Y94: =SUMIFS('Committments Dump'!$R:$R,'Committments Dump'!$C:$C,'Category Table'!Y$2,'Committments Dump'!$B:$B,'Category Table'!$A94) | Z94: =SUMIFS('Committments Dump'!$R:$R,'Committments Dump'!$C:$C,'Category Table'!Z$2,'Committments Dump'!$B:$B,'Category Table'!$A94) | AA94: =SUMIFS('Committments Dump'!$S:$S,'Committments Dump'!$C:$C,'Category Table'!AA$2,'Committments Dump'!$B:$B,'Category Table'!$A94) | AB94: =SUMIFS('Committments Dump'!$S:$S,'Committments Dump'!$C:$C,'Category Table'!AB$2,'Committments Dump'!$B:$B,'Category Table'!$A94) | AC94: =SUMIFS('Committments Dump'!$S:$S,'Committments Dump'!$C:$C,'Category Table'!AC$2,'Committments Dump'!$B:$B,'Category Table'!$A94) | AD94: =U94+X94+AA94 | AE94: =V94+Y94+AB94 | AF94: =W94+Z94+AC94 | AG94: =R94+AD94 | AH94: =S94+AE94 | AI94: =T94+AF94 | AM94: =(O94-AG94)+AJ94 | AN94: =(P94-AH94)+AK94 | AO94: =(Q94-AI94)+AL94 | AP94: =IF(AM94>0, "Under",IF(AM94<0,"Over","")) | AQ94: =IF(AN94>0, "Under",IF(AN94<0,"Over","")) | AR94: =IF(AO94>0, "Under",IF(AO94<0,"Over",""))
A95: 0-4121 | B95: 0-4121-Laydown Areas | C95: 0 | D95: 0 | E95: 156147.77 | F95: 29000 | G95: 0 | H95: 153564.58 | I95: 0 | J95: 832.5 | K95: 1057.94 | L95: 0 | M95: 0 | N95: 596875.57 | O95: =L95+I95+F95+C95 | P95: =M95+J95+G95+D95 | Q95: =N95+K95+H95+E95 | R95: =SUMIFS('PO Log'!$E:$E,'PO Log'!$D:$D,'Category Table'!R$2,'PO Log'!$C:$C,'Category Table'!$A95) | S95: =SUMIFS('PO Log'!$E:$E,'PO Log'!$D:$D,'Category Table'!S$2,'PO Log'!$C:$C,'Category Table'!$A95) | T95: =SUMIFS('PO Log'!$E:$E,'PO Log'!$D:$D,'Category Table'!T$2,'PO Log'!$C:$C,'Category Table'!$A95) | U95: =SUMIFS('Committments Dump'!$Q:$Q,'Committments Dump'!$C:$C,'Category Table'!U$2,'Committments Dump'!$B:$B,'Category Table'!$A95) | V95: =SUMIFS('Committments Dump'!$Q:$Q,'Committments Dump'!$C:$C,'Category Table'!V$2,'Committments Dump'!$B:$B,'Category Table'!$A95) | W95: =SUMIFS('Committments Dump'!$Q:$Q,'Committments Dump'!$C:$C,'Category Table'!W$2,'Committments Dump'!$B:$B,'Category Table'!$A95) | X95: =SUMIFS('Committments Dump'!$R:$R,'Committments Dump'!$C:$C,'Category Table'!X$2,'Committments Dump'!$B:$B,'Category Table'!$A95) | Y95: =SUMIFS('Committments Dump'!$R:$R,'Committments Dump'!$C:$C,'Category Table'!Y$2,'Committments Dump'!$B:$B,'Category Table'!$A95) | Z95: =SUMIFS('Committments Dump'!$R:$R,'Committments Dump'!$C:$C,'Category Table'!Z$2,'Committments Dump'!$B:$B,'Category Table'!$A95) | AA95: =SUMIFS('Committments Dump'!$S:$S,'Committments Dump'!$C:$C,'Category Table'!AA$2,'Committments Dump'!$B:$B,'Category Table'!$A95) | AB95: =SUMIFS('Committments Dump'!$S:$S,'Committments Dump'!$C:$C,'Category Table'!AB$2,'Committments Dump'!$B:$B,'Category Table'!$A95) | AC95: =SUMIFS('Committments Dump'!$S:$S,'Committments Dump'!$C:$C,'Category Table'!AC$2,'Committments Dump'!$B:$B,'Category Table'!$A95) | AD95: =U95+X95+AA95 | AE95: =V95+Y95+AB95 | AF95: =W95+Z95+AC95 | AG95: =R95+AD95 | AH95: =S95+AE95 | AI95: =T95+AF95 | AM95: =(O95-AG95)+AJ95 | AN95: =(P95-AH95)+AK95 | AO95: =(Q95-AI95)+AL95 | AP95: =IF(AM95>0, "Under",IF(AM95<0,"Over","")) | AQ95: =IF(AN95>0, "Under",IF(AN95<0,"Over","")) | AR95: =IF(AO95>0, "Under",IF(AO95<0,"Over",""))
A96: 0-4122 | B96: 0-4122-Road Maintenance | C96: 0 | D96: 0 | E96: 0 | F96: 0 | G96: 0 | H96: 0 | I96: 0 | J96: 0 | K96: 0 | L96: 0 | M96: 0 | N96: 0 | O96: =L96+I96+F96+C96 | P96: =M96+J96+G96+D96 | Q96: =N96+K96+H96+E96 | R96: =SUMIFS('PO Log'!$E:$E,'PO Log'!$D:$D,'Category Table'!R$2,'PO Log'!$C:$C,'Category Table'!$A96) | S96: =SUMIFS('PO Log'!$E:$E,'PO Log'!$D:$D,'Category Table'!S$2,'PO Log'!$C:$C,'Category Table'!$A96) | T96: =SUMIFS('PO Log'!$E:$E,'PO Log'!$D:$D,'Category Table'!T$2,'PO Log'!$C:$C,'Category Table'!$A96) | U96: =SUMIFS('Committments Dump'!$Q:$Q,'Committments Dump'!$C:$C,'Category Table'!U$2,'Committments Dump'!$B:$B,'Category Table'!$A96) | V96: =SUMIFS('Committments Dump'!$Q:$Q,'Committments Dump'!$C:$C,'Category Table'!V$2,'Committments Dump'!$B:$B,'Category Table'!$A96) | W96: =SUMIFS('Committments Dump'!$Q:$Q,'Committments Dump'!$C:$C,'Category Table'!W$2,'Committments Dump'!$B:$B,'Category Table'!$A96) | X96: =SUMIFS('Committments Dump'!$R:$R,'Committments Dump'!$C:$C,'Category Table'!X$2,'Committments Dump'!$B:$B,'Category Table'!$A96) | Y96: =SUMIFS('Committments Dump'!$R:$R,'Committments Dump'!$C:$C,'Category Table'!Y$2,'Committments Dump'!$B:$B,'Category Table'!$A96) | Z96: =SUMIFS('Committments Dump'!$R:$R,'Committments Dump'!$C:$C,'Category Table'!Z$2,'Committments Dump'!$B:$B,'Category Table'!$A96) | AA96: =SUMIFS('Committments Dump'!$S:$S,'Committments Dump'!$C:$C,'Category Table'!AA$2,'Committments Dump'!$B:$B,'Category Table'!$A96) | AB96: =SUMIFS('Committments Dump'!$S:$S,'Committments Dump'!$C:$C,'Category Table'!AB$2,'Committments Dump'!$B:$B,'Category Table'!$A96) | AC96: =SUMIFS('Committments Dump'!$S:$S,'Committments Dump'!$C:$C,'Category Table'!AC$2,'Committments Dump'!$B:$B,'Category Table'!$A96) | AD96: =U96+X96+AA96 | AE96: =V96+Y96+AB96 | AF96: =W96+Z96+AC96 | AG96: =R96+AD96 | AH96: =S96+AE96 | AI96: =T96+AF96 | AM96: =(O96-AG96)+AJ96 | AN96: =(P96-AH96)+AK96 | AO96: =(Q96-AI96)+AL96 | AP96: =IF(AM96>0, "Under",IF(AM96<0,"Over","")) | AQ96: =IF(AN96>0, "Under",IF(AN96<0,"Over","")) | AR96: =IF(AO96>0, "Under",IF(AO96<0,"Over",""))
A97: 0-4123 | B97: 0-4123-Dust Control | C97: 0 | D97: 0 | E97: 0 | F97: 0 | G97: 0 | H97: 95877.254 | I97: 0 | J97: 0 | K97: 0 | L97: 0 | M97: 0 | N97: 0 | O97: =L97+I97+F97+C97 | P97: =M97+J97+G97+D97 | Q97: =N97+K97+H97+E97 | R97: =SUMIFS('PO Log'!$E:$E,'PO Log'!$D:$D,'Category Table'!R$2,'PO Log'!$C:$C,'Category Table'!$A97) | S97: =SUMIFS('PO Log'!$E:$E,'PO Log'!$D:$D,'Category Table'!S$2,'PO Log'!$C:$C,'Category Table'!$A97) | T97: =SUMIFS('PO Log'!$E:$E,'PO Log'!$D:$D,'Category Table'!T$2,'PO Log'!$C:$C,'Category Table'!$A97) | U97: =SUMIFS('Committments Dump'!$Q:$Q,'Committments Dump'!$C:$C,'Category Table'!U$2,'Committments Dump'!$B:$B,'Category Table'!$A97) | V97: =SUMIFS('Committments Dump'!$Q:$Q,'Committments Dump'!$C:$C,'Category Table'!V$2,'Committments Dump'!$B:$B,'Category Table'!$A97) | W97: =SUMIFS('Committments Dump'!$Q:$Q,'Committments Dump'!$C:$C,'Category Table'!W$2,'Committments Dump'!$B:$B,'Category Table'!$A97) | X97: =SUMIFS('Committments Dump'!$R:$R,'Committments Dump'!$C:$C,'Category Table'!X$2,'Committments Dump'!$B:$B,'Category Table'!$A97) | Y97: =SUMIFS('Committments Dump'!$R:$R,'Committments Dump'!$C:$C,'Category Table'!Y$2,'Committments Dump'!$B:$B,'Category Table'!$A97) | Z97: =SUMIFS('Committments Dump'!$R:$R,'Committments Dump'!$C:$C,'Category Table'!Z$2,'Committments Dump'!$B:$B,'Category Table'!$A97) | AA97: =SUMIFS('Committments Dump'!$S:$S,'Committments Dump'!$C:$C,'Category Table'!AA$2,'Committments Dump'!$B:$B,'Category Table'!$A97) | AB97: =SUMIFS('Committments Dump'!$S:$S,'Committments Dump'!$C:$C,'Category Table'!AB$2,'Committments Dump'!$B:$B,'Category Table'!$A97) | AC97: =SUMIFS('Committments Dump'!$S:$S,'Committments Dump'!$C:$C,'Category Table'!AC$2,'Committments Dump'!$B:$B,'Category Table'!$A97) | AD97: =U97+X97+AA97 | AE97: =V97+Y97+AB97 | AF97: =W97+Z97+AC97 | AG97: =R97+AD97 | AH97: =S97+AE97 | AI97: =T97+AF97 | AM97: =(O97-AG97)+AJ97 | AN97: =(P97-AH97)+AK97 | AO97: =(Q97-AI97)+AL97 | AP97: =IF(AM97>0, "Under",IF(AM97<0,"Over","")) | AQ97: =IF(AN97>0, "Under",IF(AN97<0,"Over","")) | AR97: =IF(AO97>0, "Under",IF(AO97<0,"Over",""))
A98: 0-4124 | B98: 0-4124-Dewatering | C98: 0 | D98: 0 | E98: 0 | F98: 0 | G98: 0 | H98: 0 | I98: 0 | J98: 0 | K98: 0 | L98: 0 | M98: 0 | N98: 0 | O98: =L98+I98+F98+C98 | P98: =M98+J98+G98+D98 | Q98: =N98+K98+H98+E98 | R98: =SUMIFS('PO Log'!$E:$E,'PO Log'!$D:$D,'Category Table'!R$2,'PO Log'!$C:$C,'Category Table'!$A98) | S98: =SUMIFS('PO Log'!$E:$E,'PO Log'!$D:$D,'Category Table'!S$2,'PO Log'!$C:$C,'Category Table'!$A98) | T98: =SUMIFS('PO Log'!$E:$E,'PO Log'!$D:$D,'Category Table'!T$2,'PO Log'!$C:$C,'Category Table'!$A98) | U98: =SUMIFS('Committments Dump'!$Q:$Q,'Committments Dump'!$C:$C,'Category Table'!U$2,'Committments Dump'!$B:$B,'Category Table'!$A98) | V98: =SUMIFS('Committments Dump'!$Q:$Q,'Committments Dump'!$C:$C,'Category Table'!V$2,'Committments Dump'!$B:$B,'Category Table'!$A98) | W98: =SUMIFS('Committments Dump'!$Q:$Q,'Committments Dump'!$C:$C,'Category Table'!W$2,'Committments Dump'!$B:$B,'Category Table'!$A98) | X98: =SUMIFS('Committments Dump'!$R:$R,'Committments Dump'!$C:$C,'Category Table'!X$2,'Committments Dump'!$B:$B,'Category Table'!$A98) | Y98: =SUMIFS('Committments Dump'!$R:$R,'Committments Dump'!$C:$C,'Category Table'!Y$2,'Committments Dump'!$B:$B,'Category Table'!$A98) | Z98: =SUMIFS('Committments Dump'!$R:$R,'Committments Dump'!$C:$C,'Category Table'!Z$2,'Committments Dump'!$B:$B,'Category Table'!$A98) | AA98: =SUMIFS('Committments Dump'!$S:$S,'Committments Dump'!$C:$C,'Category Table'!AA$2,'Committments Dump'!$B:$B,'Category Table'!$A98) | AB98: =SUMIFS('Committments Dump'!$S:$S,'Committments Dump'!$C:$C,'Category Table'!AB$2,'Committments Dump'!$B:$B,'Category Table'!$A98) | AC98: =SUMIFS('Committments Dump'!$S:$S,'Committments Dump'!$C:$C,'Category Table'!AC$2,'Committments Dump'!$B:$B,'Category Table'!$A98) | AD98: =U98+X98+AA98 | AE98: =V98+Y98+AB98 | AF98: =W98+Z98+AC98 | AG98: =R98+AD98 | AH98: =S98+AE98 | AI98: =T98+AF98 | AM98: =(O98-AG98)+AJ98 | AN98: =(P98-AH98)+AK98 | AO98: =(Q98-AI98)+AL98 | AP98: =IF(AM98>0, "Under",IF(AM98<0,"Over","")) | AQ98: =IF(AN98>0, "Under",IF(AN98<0,"Over","")) | AR98: =IF(AO98>0, "Under",IF(AO98<0,"Over",""))
A99: 0-4125 | B99: 0-4125-SWPPP Maintenance | C99: 0 | D99: 0 | E99: 0 | F99: 0 | G99: 0 | H99: 13345.351 | I99: 0 | J99: 0 | K99: 0 | L99: 0 | M99: 0 | N99: 0 | O99: =L99+I99+F99+C99 | P99: =M99+J99+G99+D99 | Q99: =N99+K99+H99+E99 | R99: =SUMIFS('PO Log'!$E:$E,'PO Log'!$D:$D,'Category Table'!R$2,'PO Log'!$C:$C,'Category Table'!$A99) | S99: =SUMIFS('PO Log'!$E:$E,'PO Log'!$D:$D,'Category Table'!S$2,'PO Log'!$C:$C,'Category Table'!$A99) | T99: =SUMIFS('PO Log'!$E:$E,'PO Log'!$D:$D,'Category Table'!T$2,'PO Log'!$C:$C,'Category Table'!$A99) | U99: =SUMIFS('Committments Dump'!$Q:$Q,'Committments Dump'!$C:$C,'Category Table'!U$2,'Committments Dump'!$B:$B,'Category Table'!$A99) | V99: =SUMIFS('Committments Dump'!$Q:$Q,'Committments Dump'!$C:$C,'Category Table'!V$2,'Committments Dump'!$B:$B,'Category Table'!$A99) | W99: =SUMIFS('Committments Dump'!$Q:$Q,'Committments Dump'!$C:$C,'Category Table'!W$2,'Committments Dump'!$B:$B,'Category Table'!$A99) | X99: =SUMIFS('Committments Dump'!$R:$R,'Committments Dump'!$C:$C,'Category Table'!X$2,'Committments Dump'!$B:$B,'Category Table'!$A99) | Y99: =SUMIFS('Committments Dump'!$R:$R,'Committments Dump'!$C:$C,'Category Table'!Y$2,'Committments Dump'!$B:$B,'Category Table'!$A99) | Z99: =SUMIFS('Committments Dump'!$R:$R,'Committments Dump'!$C:$C,'Category Table'!Z$2,'Committments Dump'!$B:$B,'Category Table'!$A99) | AA99: =SUMIFS('Committments Dump'!$S:$S,'Committments Dump'!$C:$C,'Category Table'!AA$2,'Committments Dump'!$B:$B,'Category Table'!$A99) | AB99: =SUMIFS('Committments Dump'!$S:$S,'Committments Dump'!$C:$C,'Category Table'!AB$2,'Committments Dump'!$B:$B,'Category Table'!$A99) | AC99: =SUMIFS('Committments Dump'!$S:$S,'Committments Dump'!$C:$C,'Category Table'!AC$2,'Committments Dump'!$B:$B,'Category Table'!$A99) | AD99: =U99+X99+AA99 | AE99: =V99+Y99+AB99 | AF99: =W99+Z99+AC99 | AG99: =R99+AD99 | AH99: =S99+AE99 | AI99: =T99+AF99 | AM99: =(O99-AG99)+AJ99 | AN99: =(P99-AH99)+AK99 | AO99: =(Q99-AI99)+AL99 | AP99: =IF(AM99>0, "Under",IF(AM99<0,"Over","")) | AQ99: =IF(AN99>0, "Under",IF(AN99<0,"Over","")) | AR99: =IF(AO99>0, "Under",IF(AO99<0,"Over",""))
A100: 0-4128 | B100: 0-4128-Basin Installation | C100: 0 | D100: 0 | E100: 0 | F100: 0 | G100: 0 | H100: 154560.43 | I100: 0 | J100: 0 | K100: 0 | L100: 0 | M100: 0 | N100: 0 | O100: =L100+I100+F100+C100 | P100: =M100+J100+G100+D100 | Q100: =N100+K100+H100+E100 | R100: =SUMIFS('PO Log'!$E:$E,'PO Log'!$D:$D,'Category Table'!R$2,'PO Log'!$C:$C,'Category Table'!$A100) | S100: =SUMIFS('PO Log'!$E:$E,'PO Log'!$D:$D,'Category Table'!S$2,'PO Log'!$C:$C,'Category Table'!$A100) | T100: =SUMIFS('PO Log'!$E:$E,'PO Log'!$D:$D,'Category Table'!T$2,'PO Log'!$C:$C,'Category Table'!$A100) | U100: =SUMIFS('Committments Dump'!$Q:$Q,'Committments Dump'!$C:$C,'Category Table'!U$2,'Committments Dump'!$B:$B,'Category Table'!$A100) | V100: =SUMIFS('Committments Dump'!$Q:$Q,'Committments Dump'!$C:$C,'Category Table'!V$2,'Committments Dump'!$B:$B,'Category Table'!$A100) | W100: =SUMIFS('Committments Dump'!$Q:$Q,'Committments Dump'!$C:$C,'Category Table'!W$2,'Committments Dump'!$B:$B,'Category Table'!$A100) | X100: =SUMIFS('Committments Dump'!$R:$R,'Committments Dump'!$C:$C,'Category Table'!X$2,'Committments Dump'!$B:$B,'Category Table'!$A100) | Y100: =SUMIFS('Committments Dump'!$R:$R,'Committments Dump'!$C:$C,'Category Table'!Y$2,'Committments Dump'!$B:$B,'Category Table'!$A100) | Z100: =SUMIFS('Committments Dump'!$R:$R,'Committments Dump'!$C:$C,'Category Table'!Z$2,'Committments Dump'!$B:$B,'Category Table'!$A100) | AA100: =SUMIFS('Committments Dump'!$S:$S,'Committments Dump'!$C:$C,'Category Table'!AA$2,'Committments Dump'!$B:$B,'Category Table'!$A100) | AB100: =SUMIFS('Committments Dump'!$S:$S,'Committments Dump'!$C:$C,'Category Table'!AB$2,'Committments Dump'!$B:$B,'Category Table'!$A100) | AC100: =SUMIFS('Committments Dump'!$S:$S,'Committments Dump'!$C:$C,'Category Table'!AC$2,'Committments Dump'!$B:$B,'Category Table'!$A100) | AD100: =U100+X100+AA100 | AE100: =V100+Y100+AB100 | AF100: =W100+Z100+AC100 | AG100: =R100+AD100 | AH100: =S100+AE100 | AI100: =T100+AF100 | AM100: =(O100-AG100)+AJ100 | AN100: =(P100-AH100)+AK100 | AO100: =(Q100-AI100)+AL100 | AP100: =IF(AM100>0, "Under",IF(AM100<0,"Over","")) | AQ100: =IF(AN100>0, "Under",IF(AN100<0,"Over","")) | AR100: =IF(AO100>0, "Under",IF(AO100<0,"Over",""))
... A104: 2-4205 | B104: 2-4205-SS Pad | C104: 0 | D104: 0 | E104: 0 | F104: 0 | G104: 19492.488 | H104: 75000 | I104: 0 | J104: 0 | K104: 0 | L104: 0 | M104: 0 | N104: 477300 | O104: =L104+I104+F104+C104 | P104: =M104+J104+G104+D104 | Q104: =N104+K104+H104+E104 | R104: =SUMIFS('PO Log'!$E:$E,'PO Log'!$D:$D,'Category Table'!R$2,'PO Log'!$C:$C,'Category Table'!$A104) | S104: =SUMIFS('PO Log'!$E:$E,'PO Log'!$D:$D,'Category Table'!S$2,'PO Log'!$C:$C,'Category Table'!$A104) | T104: =SUMIFS('PO Log'!$E:$E,'PO Log'!$D:$D,'Category Table'!T$2,'PO Log'!$C:$C,'Category Table'!$A104) | U104: =SUMIFS('Committments Dump'!$Q:$Q,'Committments Dump'!$C:$C,'Category Table'!U$2,'Committments Dump'!$B:$B,'Category Table'!$A104) | V104: =SUMIFS('Committments Dump'!$Q:$Q,'Committments Dump'!$C:$C,'Category Table'!V$2,'Committments Dump'!$B:$B,'Category Table'!$A104) | W104: =SUMIFS('Committments Dump'!$Q:$Q,'Committments Dump'!$C:$C,'Category Table'!W$2,'Committments Dump'!$B:$B,'Category Table'!$A104) | X104: =SUMIFS('Committments Dump'!$R:$R,'Committments Dump'!$C:$C,'Category Table'!X$2,'Committments Dump'!$B:$B,'Category Table'!$A104) | Y104: =SUMIFS('Committments Dump'!$R:$R,'Committments Dump'!$C:$C,'Category Table'!Y$2,'Committments Dump'!$B:$B,'Category Table'!$A104) | Z104: =SUMIFS('Committments Dump'!$R:$R,'Committments Dump'!$C:$C,'Category Table'!Z$2,'Committments Dump'!$B:$B,'Category Table'!$A104) | AA104: =SUMIFS('Committments Dump'!$S:$S,'Committments Dump'!$C:$C,'Category Table'!AA$2,'Committments Dump'!$B:$B,'Category Table'!$A104) | AB104: =SUMIFS('Committments Dump'!$S:$S,'Committments Dump'!$C:$C,'Category Table'!AB$2,'Committments Dump'!$B:$B,'Category Table'!$A104) | AC104: =SUMIFS('Committments Dump'!$S:$S,'Committments Dump'!$C:$C,'Category Table'!AC$2,'Committments Dump'!$B:$B,'Category Table'!$A104) | AD104: =U104+X104+AA104 | AE104: =V104+Y104+AB104 | AF104: =W104+Z104+AC104 | AG104: =R104+AD104 | AH104: =S104+AE104 | AI104: =T104+AF104 | AM104: =(O104-AG104)+AJ104 | AN104: =(P104-AH104)+AK104 | AO104: =(Q104-AI104)+AL104 | AP104: =IF(AM104>0, "Under",IF(AM104<0,"Over","")) | AQ104: =IF(AN104>0, "Under",IF(AN104<0,"Over","")) | AR104: =IF(AO104>0, "Under",IF(AO104<0,"Over",""))
A105: 2-4209 | B105: 2-4209-SS Road | C105: 0 | D105: 500 | E105: 0 | G105: 9613.74 | H105: 370889.22 | I105: 0 | J105: 0 | K105: 0 | L105: 0 | M105: 666 | N105: 243373.05 | O105: =L105+I105+F105+C105 | P105: =M105+J105+G105+D105 | Q105: =N105+K105+H105+E105 | R105: =SUMIFS('PO Log'!$E:$E,'PO Log'!$D:$D,'Category Table'!R$2,'PO Log'!$C:$C,'Category Table'!$A105) | S105: =SUMIFS('PO Log'!$E:$E,'PO Log'!$D:$D,'Category Table'!S$2,'PO Log'!$C:$C,'Category Table'!$A105) | T105: =SUMIFS('PO Log'!$E:$E,'PO Log'!$D:$D,'Category Table'!T$2,'PO Log'!$C:$C,'Category Table'!$A105) | U105: =SUMIFS('Committments Dump'!$Q:$Q,'Committments Dump'!$C:$C,'Category Table'!U$2,'Committments Dump'!$B:$B,'Category Table'!$A105) | V105: =SUMIFS('Committments Dump'!$Q:$Q,'Committments Dump'!$C:$C,'Category Table'!V$2,'Committments Dump'!$B:$B,'Category Table'!$A105) | W105: =SUMIFS('Committments Dump'!$Q:$Q,'Committments Dump'!$C:$C,'Category Table'!W$2,'Committments Dump'!$B:$B,'Category Table'!$A105) | X105: =SUMIFS('Committments Dump'!$R:$R,'Committments Dump'!$C:$C,'Category Table'!X$2,'Committments Dump'!$B:$B,'Category Table'!$A105) | Y105: =SUMIFS('Committments Dump'!$R:$R,'Committments Dump'!$C:$C,'Category Table'!Y$2,'Committments Dump'!$B:$B,'Category Table'!$A105) | Z105: =SUMIFS('Committments Dump'!$R:$R,'Committments Dump'!$C:$C,'Category Table'!Z$2,'Committments Dump'!$B:$B,'Category Table'!$A105) | AA105: =SUMIFS('Committments Dump'!$S:$S,'Committments Dump'!$C:$C,'Category Table'!AA$2,'Committments Dump'!$B:$B,'Category Table'!$A105) | AB105: =SUMIFS('Committments Dump'!$S:$S,'Committments Dump'!$C:$C,'Category Table'!AB$2,'Committments Dump'!$B:$B,'Category Table'!$A105) | AC105: =SUMIFS('Committments Dump'!$S:$S,'Committments Dump'!$C:$C,'Category Table'!AC$2,'Committments Dump'!$B:$B,'Category Table'!$A105) | AD105: =U105+X105+AA105 | AE105: =V105+Y105+AB105 | AF105: =W105+Z105+AC105 | AG105: =R105+AD105 | AH105: =S105+AE105 | AI105: =T105+AF105 | AM105: =(O105-AG105)+AJ105 | AN105: =(P105-AH105)+AK105 | AO105: =(Q105-AI105)+AL105 | AP105: =IF(AM105>0, "Under",IF(AM105<0,"Over","")) | AQ105: =IF(AN105>0, "Under",IF(AN105<0,"Over","")) | AR105: =IF(AO105>0, "Under",IF(AO105<0,"Over",""))
A106: 0-4011 | B106: 0-4011 Taxas Conptroller Taxes | C106: 0 | D106: 0 | E106: 0 | F106: 0 | H106: 0 | I106: 0 | J106: 0 | K106: 0 | L106: 0 | M106: 0 | N106: 0 | O106: =L106+I106+F106+C106 | P106: =M106+J106+G106+D106 | Q106: =N106+K106+H106+E106 | R106: =SUMIFS('PO Log'!$E:$E,'PO Log'!$D:$D,'Category Table'!R$2,'PO Log'!$C:$C,'Category Table'!$A106) | S106: =SUMIFS('PO Log'!$E:$E,'PO Log'!$D:$D,'Category Table'!S$2,'PO Log'!$C:$C,'Category Table'!$A106) | T106: =SUMIFS('PO Log'!$E:$E,'PO Log'!$D:$D,'Category Table'!T$2,'PO Log'!$C:$C,'Category Table'!$A106) | U106: =SUMIFS('Committments Dump'!$Q:$Q,'Committments Dump'!$C:$C,'Category Table'!U$2,'Committments Dump'!$B:$B,'Category Table'!$A106) | V106: =SUMIFS('Committments Dump'!$Q:$Q,'Committments Dump'!$C:$C,'Category Table'!V$2,'Committments Dump'!$B:$B,'Category Table'!$A106) | W106: =SUMIFS('Committments Dump'!$Q:$Q,'Committments Dump'!$C:$C,'Category Table'!W$2,'Committments Dump'!$B:$B,'Category Table'!$A106) | X106: =SUMIFS('Committments Dump'!$R:$R,'Committments Dump'!$C:$C,'Category Table'!X$2,'Committments Dump'!$B:$B,'Category Table'!$A106) | Y106: =SUMIFS('Committments Dump'!$R:$R,'Committments Dump'!$C:$C,'Category Table'!Y$2,'Committments Dump'!$B:$B,'Category Table'!$A106) | Z106: =SUMIFS('Committments Dump'!$R:$R,'Committments Dump'!$C:$C,'Category Table'!Z$2,'Committments Dump'!$B:$B,'Category Table'!$A106) | AA106: =SUMIFS('Committments Dump'!$S:$S,'Committments Dump'!$C:$C,'Category Table'!AA$2,'Committments Dump'!$B:$B,'Category Table'!$A106) | AB106: =SUMIFS('Committments Dump'!$S:$S,'Committments Dump'!$C:$C,'Category Table'!AB$2,'Committments Dump'!$B:$B,'Category Table'!$A106) | AC106: =SUMIFS('Committments Dump'!$S:$S,'Committments Dump'!$C:$C,'Category Table'!AC$2,'Committments Dump'!$B:$B,'Category Table'!$A106) | AD106: =U106+X106+AA106 | AE106: =V106+Y106+AB106 | AF106: =W106+Z106+AC106 | AG106: =R106+AD106 | AH106: =S106+AE106 | AI106: =T106+AF106 | AM106: =(O106-AG106)+AJ106 | AN106: =(P106-AH106)+AK106 | AO106: =(Q106-AI106)+AL106 | AP106: =IF(AM106>0, "Under",IF(AM106<0,"Over","")) | AQ106: =IF(AN106>0, "Under",IF(AN106<0,"Over","")) | AR106: =IF(AO106>0, "Under",IF(AO106<0,"Over",""))
A107: 0-4999 | B107: 0-4999 Job Abuse | C107: 0 | D107: 1035.85 | E107: 0 | F107: 3278.64 | G107: 0 | H107: 0 | I107: 0 | J107: 0 | K107: 0 | L107: 0 | M107: 0 | N107: 0 | O107: =L107+I107+F107+C107 | P107: =M107+J107+G107+D107 | Q107: =N107+K107+H107+E107 | R107: =SUMIFS('PO Log'!$E:$E,'PO Log'!$D:$D,'Category Table'!R$2,'PO Log'!$C:$C,'Category Table'!$A107) | S107: =SUMIFS('PO Log'!$E:$E,'PO Log'!$D:$D,'Category Table'!S$2,'PO Log'!$C:$C,'Category Table'!$A107) | T107: =SUMIFS('PO Log'!$E:$E,'PO Log'!$D:$D,'Category Table'!T$2,'PO Log'!$C:$C,'Category Table'!$A107) | U107: =SUMIFS('Committments Dump'!$Q:$Q,'Committments Dump'!$C:$C,'Category Table'!U$2,'Committments Dump'!$B:$B,'Category Table'!$A107) | V107: =SUMIFS('Committments Dump'!$Q:$Q,'Committments Dump'!$C:$C,'Category Table'!V$2,'Committments Dump'!$B:$B,'Category Table'!$A107) | W107: =SUMIFS('Committments Dump'!$Q:$Q,'Committments Dump'!$C:$C,'Category Table'!W$2,'Committments Dump'!$B:$B,'Category Table'!$A107) | X107: =SUMIFS('Committments Dump'!$R:$R,'Committments Dump'!$C:$C,'Category Table'!X$2,'Committments Dump'!$B:$B,'Category Table'!$A107) | Y107: =SUMIFS('Committments Dump'!$R:$R,'Committments Dump'!$C:$C,'Category Table'!Y$2,'Committments Dump'!$B:$B,'Category Table'!$A107) | Z107: =SUMIFS('Committments Dump'!$R:$R,'Committments Dump'!$C:$C,'Category Table'!Z$2,'Committments Dump'!$B:$B,'Category Table'!$A107) | AA107: =SUMIFS('Committments Dump'!$S:$S,'Committments Dump'!$C:$C,'Category Table'!AA$2,'Committments Dump'!$B:$B,'Category Table'!$A107) | AB107: =SUMIFS('Committments Dump'!$S:$S,'Committments Dump'!$C:$C,'Category Table'!AB$2,'Committments Dump'!$B:$B,'Category Table'!$A107) | AC107: =SUMIFS('Committments Dump'!$S:$S,'Committments Dump'!$C:$C,'Category Table'!AC$2,'Committments Dump'!$B:$B,'Category Table'!$A107) | AD107: =U107+X107+AA107 | AE107: =V107+Y107+AB107 | AF107: =W107+Z107+AC107 | AG107: =R107+AD107 | AH107: =S107+AE107 | AI107: =T107+AF107 | AM107: =(O107-AG107)+AJ107 | AN107: =(P107-AH107)+AK107 | AO107: =(Q107-AI107)+AL107 | AP107: =IF(AM107>0, "Under",IF(AM107<0,"Over","")) | AQ107: =IF(AN107>0, "Under",IF(AN107<0,"Over","")) | AR107: =IF(AO107>0, "Under",IF(AO107<0,"Over",""))
A108: 0-4018 | B108: 0-4018 Travel | C108: 0 | D108: 36745.18 | E108: 0 | F108: 13254.82 | G108: 0 | H108: 0 | I108: 0 | J108: 0 | K108: 0 | L108: 0 | M108: 0 | N108: 0 | O108: =L108+I108+F108+C108 | P108: =M108+J108+G108+D108 | Q108: =N108+K108+H108+E108 | R108: =SUMIFS('PO Log'!$E:$E,'PO Log'!$D:$D,'Category Table'!R$2,'PO Log'!$C:$C,'Category Table'!$A108) | S108: =SUMIFS('PO Log'!$E:$E,'PO Log'!$D:$D,'Category Table'!S$2,'PO Log'!$C:$C,'Category Table'!$A108) | T108: =SUMIFS('PO Log'!$E:$E,'PO Log'!$D:$D,'Category Table'!T$2,'PO Log'!$C:$C,'Category Table'!$A108) | U108: =SUMIFS('Committments Dump'!$Q:$Q,'Committments Dump'!$C:$C,'Category Table'!U$2,'Committments Dump'!$B:$B,'Category Table'!$A108) | V108: =SUMIFS('Committments Dump'!$Q:$Q,'Committments Dump'!$C:$C,'Category Table'!V$2,'Committments Dump'!$B:$B,'Category Table'!$A108) | W108: =SUMIFS('Committments Dump'!$Q:$Q,'Committments Dump'!$C:$C,'Category Table'!W$2,'Committments Dump'!$B:$B,'Category Table'!$A108) | X108: =SUMIFS('Committments Dump'!$R:$R,'Committments Dump'!$C:$C,'Category Table'!X$2,'Committments Dump'!$B:$B,'Category Table'!$A108) | Y108: =SUMIFS('Committments Dump'!$R:$R,'Committments Dump'!$C:$C,'Category Table'!Y$2,'Committments Dump'!$B:$B,'Category Table'!$A108) | Z108: =SUMIFS('Committments Dump'!$R:$R,'Committments Dump'!$C:$C,'Category Table'!Z$2,'Committments Dump'!$B:$B,'Category Table'!$A108) | AA108: =SUMIFS('Committments Dump'!$S:$S,'Committments Dump'!$C:$C,'Category Table'!AA$2,'Committments Dump'!$B:$B,'Category Table'!$A108) | AB108: =SUMIFS('Committments Dump'!$S:$S,'Committments Dump'!$C:$C,'Category Table'!AB$2,'Committments Dump'!$B:$B,'Category Table'!$A108) | AC108: =SUMIFS('Committments Dump'!$S:$S,'Committments Dump'!$C:$C,'Category Table'!AC$2,'Committments Dump'!$B:$B,'Category Table'!$A108) | AD108: =U108+X108+AA108 | AE108: =V108+Y108+AB108 | AF108: =W108+Z108+AC108 | AG108: =R108+AD108 | AH108: =S108+AE108 | AI108: =T108+AF108 | AM108: =(O108-AG108)+AJ108 | AN108: =(P108-AH108)+AK108 | AO108: =(Q108-AI108)+AL108 | AP108: =IF(AM108>0, "Under",IF(AM108<0,"Over","")) | AQ108: =IF(AN108>0, "Under",IF(AN108<0,"Over","")) | AR108: =IF(AO108>0, "Under",IF(AO108<0,"Over",""))
A109: 0-4027 | B109: 0-4027 Early Work | C109: 0 | D109: 2274.82 | E109: 5745.54 | F109: 0 | G109: 0 | H109: 0 | I109: 0 | J109: 0 | K109: 0 | L109: 0 | M109: 0 | N109: 1190.51 | O109: =L109+I109+F109+C109 | P109: =M109+J109+G109+D109 | Q109: =N109+K109+H109+E109 | R109: =SUMIFS('PO Log'!$E:$E,'PO Log'!$D:$D,'Category Table'!R$2,'PO Log'!$C:$C,'Category Table'!$A109) | S109: =SUMIFS('PO Log'!$E:$E,'PO Log'!$D:$D,'Category Table'!S$2,'PO Log'!$C:$C,'Category Table'!$A109) | T109: =SUMIFS('PO Log'!$E:$E,'PO Log'!$D:$D,'Category Table'!T$2,'PO Log'!$C:$C,'Category Table'!$A109) | U109: =SUMIFS('Committments Dump'!$Q:$Q,'Committments Dump'!$C:$C,'Category Table'!U$2,'Committments Dump'!$B:$B,'Category Table'!$A109) | V109: =SUMIFS('Committments Dump'!$Q:$Q,'Committments Dump'!$C:$C,'Category Table'!V$2,'Committments Dump'!$B:$B,'Category Table'!$A109) | W109: =SUMIFS('Committments Dump'!$Q:$Q,'Committments Dump'!$C:$C,'Category Table'!W$2,'Committments Dump'!$B:$B,'Category Table'!$A109) | X109: =SUMIFS('Committments Dump'!$R:$R,'Committments Dump'!$C:$C,'Category Table'!X$2,'Committments Dump'!$B:$B,'Category Table'!$A109) | Y109: =SUMIFS('Committments Dump'!$R:$R,'Committments Dump'!$C:$C,'Category Table'!Y$2,'Committments Dump'!$B:$B,'Category Table'!$A109) | Z109: =SUMIFS('Committments Dump'!$R:$R,'Committments Dump'!$C:$C,'Category Table'!Z$2,'Committments Dump'!$B:$B,'Category Table'!$A109) | AA109: =SUMIFS('Committments Dump'!$S:$S,'Committments Dump'!$C:$C,'Category Table'!AA$2,'Committments Dump'!$B:$B,'Category Table'!$A109) | AB109: =SUMIFS('Committments Dump'!$S:$S,'Committments Dump'!$C:$C,'Category Table'!AB$2,'Committments Dump'!$B:$B,'Category Table'!$A109) | AC109: =SUMIFS('Committments Dump'!$S:$S,'Committments Dump'!$C:$C,'Category Table'!AC$2,'Committments Dump'!$B:$B,'Category Table'!$A109) | AD109: =U109+X109+AA109 | AE109: =V109+Y109+AB109 | AF109: =W109+Z109+AC109 | AG109: =R109+AD109 | AH109: =S109+AE109 | AI109: =T109+AF109 | AM109: =(O109-AG109)+AJ109 | AN109: =(P109-AH109)+AK109 | AO109: =(Q109-AI109)+AL109 | AP109: =IF(AM109>0, "Under",IF(AM109<0,"Over","")) | AQ109: =IF(AN109>0, "Under",IF(AN109<0,"Over","")) | AR109: =IF(AO109>0, "Under",IF(AO109<0,"Over",""))
A110: 0-4614 | B110: 0-4614 SCADA MET Install | C110: 0 | D110: 0 | E110: 0 | F110: 0 | G110: 6000 | H110: 36860.7 | I110: 0 | J110: 0 | K110: 0 | L110: 0 | M110: 0 | N110: 0 | O110: =L110+I110+F110+C110 | P110: =M110+J110+G110+D110 | Q110: =N110+K110+H110+E110 | R110: =SUMIFS('PO Log'!$E:$E,'PO Log'!$D:$D,'Category Table'!R$2,'PO Log'!$C:$C,'Category Table'!$A110) | S110: =SUMIFS('PO Log'!$E:$E,'PO Log'!$D:$D,'Category Table'!S$2,'PO Log'!$C:$C,'Category Table'!$A110) | T110: =SUMIFS('PO Log'!$E:$E,'PO Log'!$D:$D,'Category Table'!T$2,'PO Log'!$C:$C,'Category Table'!$A110) | U110: =SUMIFS('Committments Dump'!$Q:$Q,'Committments Dump'!$C:$C,'Category Table'!U$2,'Committments Dump'!$B:$B,'Category Table'!$A110) | V110: =SUMIFS('Committments Dump'!$Q:$Q,'Committments Dump'!$C:$C,'Category Table'!V$2,'Committments Dump'!$B:$B,'Category Table'!$A110) | W110: =SUMIFS('Committments Dump'!$Q:$Q,'Committments Dump'!$C:$C,'Category Table'!W$2,'Committments Dump'!$B:$B,'Category Table'!$A110) | X110: =SUMIFS('Committments Dump'!$R:$R,'Committments Dump'!$C:$C,'Category Table'!X$2,'Committments Dump'!$B:$B,'Category Table'!$A110) | Y110: =SUMIFS('Committments Dump'!$R:$R,'Committments Dump'!$C:$C,'Category Table'!Y$2,'Committments Dump'!$B:$B,'Category Table'!$A110) | Z110: =SUMIFS('Committments Dump'!$R:$R,'Committments Dump'!$C:$C,'Category Table'!Z$2,'Committments Dump'!$B:$B,'Category Table'!$A110) | AA110: =SUMIFS('Committments Dump'!$S:$S,'Committments Dump'!$C:$C,'Category Table'!AA$2,'Committments Dump'!$B:$B,'Category Table'!$A110) | AB110: =SUMIFS('Committments Dump'!$S:$S,'Committments Dump'!$C:$C,'Category Table'!AB$2,'Committments Dump'!$B:$B,'Category Table'!$A110) | AC110: =SUMIFS('Committments Dump'!$S:$S,'Committments Dump'!$C:$C,'Category Table'!AC$2,'Committments Dump'!$B:$B,'Category Table'!$A110) | AD110: =U110+X110+AA110 | AE110: =V110+Y110+AB110 | AF110: =W110+Z110+AC110 | AG110: =R110+AD110 | AH110: =S110+AE110 | AI110: =T110+AF110 | AM110: =(O110-AG110)+AJ110 | AN110: =(P110-AH110)+AK110 | AO110: =(Q110-AI110)+AL110 | AP110: =IF(AM110>0, "Under",IF(AM110<0,"Over","")) | AQ110: =IF(AN110>0, "Under",IF(AN110<0,"Over","")) | AR110: =IF(AO110>0, "Under",IF(AO110<0,"Over",""))
A111: 0-4602 | B111: Fiber Terms | C111: 0 | D111: 0 | E111: 0 | F111: 0 | G111: 0 | H111: 0 | I111: 0 | J111: 0 | K111: 0 | L111: 0 | M111: 0 | N111: 0 | O111: =L111+I111+F111+C111 | P111: =M111+J111+G111+D111 | Q111: =N111+K111+H111+E111 | R111: =SUMIFS('PO Log'!$E:$E,'PO Log'!$D:$D,'Category Table'!R$2,'PO Log'!$C:$C,'Category Table'!$A111) | S111: =SUMIFS('PO Log'!$E:$E,'PO Log'!$D:$D,'Category Table'!S$2,'PO Log'!$C:$C,'Category Table'!$A111) | T111: =SUMIFS('PO Log'!$E:$E,'PO Log'!$D:$D,'Category Table'!T$2,'PO Log'!$C:$C,'Category Table'!$A111) | U111: =SUMIFS('Committments Dump'!$Q:$Q,'Committments Dump'!$C:$C,'Category Table'!U$2,'Committments Dump'!$B:$B,'Category Table'!$A111) | V111: =SUMIFS('Committments Dump'!$Q:$Q,'Committments Dump'!$C:$C,'Category Table'!V$2,'Committments Dump'!$B:$B,'Category Table'!$A111) | W111: =SUMIFS('Committments Dump'!$Q:$Q,'Committments Dump'!$C:$C,'Category Table'!W$2,'Committments Dump'!$B:$B,'Category Table'!$A111) | X111: =SUMIFS('Committments Dump'!$R:$R,'Committments Dump'!$C:$C,'Category Table'!X$2,'Committments Dump'!$B:$B,'Category Table'!$A111) | Y111: =SUMIFS('Committments Dump'!$R:$R,'Committments Dump'!$C:$C,'Category Table'!Y$2,'Committments Dump'!$B:$B,'Category Table'!$A111) | Z111: =SUMIFS('Committments Dump'!$R:$R,'Committments Dump'!$C:$C,'Category Table'!Z$2,'Committments Dump'!$B:$B,'Category Table'!$A111) | AA111: =SUMIFS('Committments Dump'!$S:$S,'Committments Dump'!$C:$C,'Category Table'!AA$2,'Committments Dump'!$B:$B,'Category Table'!$A111) | AB111: =SUMIFS('Committments Dump'!$S:$S,'Committments Dump'!$C:$C,'Category Table'!AB$2,'Committments Dump'!$B:$B,'Category Table'!$A111) | AC111: =SUMIFS('Committments Dump'!$S:$S,'Committments Dump'!$C:$C,'Category Table'!AC$2,'Committments Dump'!$B:$B,'Category Table'!$A111) | AD111: =U111+X111+AA111 | AE111: =V111+Y111+AB111 | AF111: =W111+Z111+AC111 | AG111: =R111+AD111 | AH111: =S111+AE111 | AI111: =T111+AF111 | AM111: =(O111-AG111)+AJ111 | AN111: =(P111-AH111)+AK111 | AO111: =(Q111-AI111)+AL111 | AP111: =IF(AM111>0, "Under",IF(AM111<0,"Over","")) | AQ111: =IF(AN111>0, "Under",IF(AN111<0,"Over","")) | AR111: =IF(AO111>0, "Under",IF(AO111<0,"Over",""))
A112: 0-4xyy | B112: Risk | C112: 0 | D112: 0 | E112: 0 | F112: -2390722.8 | G112: 0 | H112: 0 | I112: 0 | J112: 0 | K112: 0 | L112: 0 | M112: 0 | N112: 0 | O112: =L112+I112+F112+C112 | P112: =M112+J112+G112+D112 | Q112: =N112+K112+H112+E112 | R112: =SUMIFS('PO Log'!$E:$E,'PO Log'!$D:$D,'Category Table'!R$2,'PO Log'!$C:$C,'Category Table'!$A112) | S112: =SUMIFS('PO Log'!$E:$E,'PO Log'!$D:$D,'Category Table'!S$2,'PO Log'!$C:$C,'Category Table'!$A112) | T112: =SUMIFS('PO Log'!$E:$E,'PO Log'!$D:$D,'Category Table'!T$2,'PO Log'!$C:$C,'Category Table'!$A112) | U112: =SUMIFS('Committments Dump'!$Q:$Q,'Committments Dump'!$C:$C,'Category Table'!U$2,'Committments Dump'!$B:$B,'Category Table'!$A112) | V112: =SUMIFS('Committments Dump'!$Q:$Q,'Committments Dump'!$C:$C,'Category Table'!V$2,'Committments Dump'!$B:$B,'Category Table'!$A112) | W112: =SUMIFS('Committments Dump'!$Q:$Q,'Committments Dump'!$C:$C,'Category Table'!W$2,'Committments Dump'!$B:$B,'Category Table'!$A112) | X112: =SUMIFS('Committments Dump'!$R:$R,'Committments Dump'!$C:$C,'Category Table'!X$2,'Committments Dump'!$B:$B,'Category Table'!$A112) | Y112: =SUMIFS('Committments Dump'!$R:$R,'Committments Dump'!$C:$C,'Category Table'!Y$2,'Committments Dump'!$B:$B,'Category Table'!$A112) | Z112: =SUMIFS('Committments Dump'!$R:$R,'Committments Dump'!$C:$C,'Category Table'!Z$2,'Committments Dump'!$B:$B,'Category Table'!$A112) | AA112: =SUMIFS('Committments Dump'!$S:$S,'Committments Dump'!$C:$C,'Category Table'!AA$2,'Committments Dump'!$B:$B,'Category Table'!$A112) | AB112: =SUMIFS('Committments Dump'!$S:$S,'Committments Dump'!$C:$C,'Category Table'!AB$2,'Committments Dump'!$B:$B,'Category Table'!$A112) | AC112: =SUMIFS('Committments Dump'!$S:$S,'Committments Dump'!$C:$C,'Category Table'!AC$2,'Committments Dump'!$B:$B,'Category Table'!$A112) | AD112: =U112+X112+AA112 | AE112: =V112+Y112+AB112 | AF112: =W112+Z112+AC112 | AG112: =R112+AD112 | AH112: =S112+AE112 | AI112: =T112+AF112 | AM112: =(O112-AG112)+AJ112 | AN112: =(P112-AH112)+AK112 | AO112: =(Q112-AI112)+AL112 | AP112: =IF(AM112>0, "Under",IF(AM112<0,"Over","")) | AQ112: =IF(AN112>0, "Under",IF(AN112<0,"Over","")) | AR112: =IF(AO112>0, "Under",IF(AO112<0,"Over",""))
A113: 0-4xxy | B113: Opps | G113: -1220810.6 | H113: -1200000 | I113: 0 | J113: 0 | K113: 0 | L113: 0 | M113: 0 | N113: 0 | O113: =L113+I113+F113+C113 | P113: =M113+J113+G113+D113 | Q113: =N113+K113+H113+E113 | R113: =SUMIFS('PO Log'!$E:$E,'PO Log'!$D:$D,'Category Table'!R$2,'PO Log'!$C:$C,'Category Table'!$A113) | S113: =SUMIFS('PO Log'!$E:$E,'PO Log'!$D:$D,'Category Table'!S$2,'PO Log'!$C:$C,'Category Table'!$A113) | T113: =SUMIFS('PO Log'!$E:$E,'PO Log'!$D:$D,'Category Table'!T$2,'PO Log'!$C:$C,'Category Table'!$A113) | U113: =SUMIFS('Committments Dump'!$Q:$Q,'Committments Dump'!$C:$C,'Category Table'!U$2,'Committments Dump'!$B:$B,'Category Table'!$A113) | V113: =SUMIFS('Committments Dump'!$Q:$Q,'Committments Dump'!$C:$C,'Category Table'!V$2,'Committments Dump'!$B:$B,'Category Table'!$A113) | W113: =SUMIFS('Committments Dump'!$Q:$Q,'Committments Dump'!$C:$C,'Category Table'!W$2,'Committments Dump'!$B:$B,'Category Table'!$A113) | X113: =SUMIFS('Committments Dump'!$R:$R,'Committments Dump'!$C:$C,'Category Table'!X$2,'Committments Dump'!$B:$B,'Category Table'!$A113) | Y113: =SUMIFS('Committments Dump'!$R:$R,'Committments Dump'!$C:$C,'Category Table'!Y$2,'Committments Dump'!$B:$B,'Category Table'!$A113) | Z113: =SUMIFS('Committments Dump'!$R:$R,'Committments Dump'!$C:$C,'Category Table'!Z$2,'Committments Dump'!$B:$B,'Category Table'!$A113) | AA113: =SUMIFS('Committments Dump'!$S:$S,'Committments Dump'!$C:$C,'Category Table'!AA$2,'Committments Dump'!$B:$B,'Category Table'!$A113) | AB113: =SUMIFS('Committments Dump'!$S:$S,'Committments Dump'!$C:$C,'Category Table'!AB$2,'Committments Dump'!$B:$B,'Category Table'!$A113) | AC113: =SUMIFS('Committments Dump'!$S:$S,'Committments Dump'!$C:$C,'Category Table'!AC$2,'Committments Dump'!$B:$B,'Category Table'!$A113) | AD113: =U113+X113+AA113 | AE113: =V113+Y113+AB113 | AF113: =W113+Z113+AC113 | AG113: =R113+AD113 | AH113: =S113+AE113 | AI113: =T113+AF113 | AM113: =(O113-AG113)+AJ113 | AN113: =(P113-AH113)+AK113 | AO113: =(Q113-AI113)+AL113 | AP113: =IF(AM113>0, "Under",IF(AM113<0,"Over","")) | AQ113: =IF(AN113>0, "Under",IF(AN113<0,"Over","")) | AR113: =IF(AO113>0, "Under",IF(AO113<0,"Over",""))
O114: =L114+I114+F114+C114 | P114: =M114+J114+G114+D114 | Q114: =N114+K114+H114+E114 | R114: =SUMIFS('PO Log'!$E:$E,'PO Log'!$D:$D,'Category Table'!R$2,'PO Log'!$C:$C,'Category Table'!$A114) | S114: =SUMIFS('PO Log'!$E:$E,'PO Log'!$D:$D,'Category Table'!S$2,'PO Log'!$C:$C,'Category Table'!$A114) | T114: =SUMIFS('PO Log'!$E:$E,'PO Log'!$D:$D,'Category Table'!T$2,'PO Log'!$C:$C,'Category Table'!$A114) | U114: =SUMIFS('Committments Dump'!$Q:$Q,'Committments Dump'!$C:$C,'Category Table'!U$2,'Committments Dump'!$B:$B,'Category Table'!$A114) | V114: =SUMIFS('Committments Dump'!$Q:$Q,'Committments Dump'!$C:$C,'Category Table'!V$2,'Committments Dump'!$B:$B,'Category Table'!$A114) | W114: =SUMIFS('Committments Dump'!$Q:$Q,'Committments Dump'!$C:$C,'Category Table'!W$2,'Committments Dump'!$B:$B,'Category Table'!$A114) | X114: =SUMIFS('Committments Dump'!$R:$R,'Committments Dump'!$C:$C,'Category Table'!X$2,'Committments Dump'!$B:$B,'Category Table'!$A114) | Y114: =SUMIFS('Committments Dump'!$R:$R,'Committments Dump'!$C:$C,'Category Table'!Y$2,'Committments Dump'!$B:$B,'Category Table'!$A114) | Z114: =SUMIFS('Committments Dump'!$R:$R,'Committments Dump'!$C:$C,'Category Table'!Z$2,'Committments Dump'!$B:$B,'Category Table'!$A114) | AA114: =SUMIFS('Committments Dump'!$S:$S,'Committments Dump'!$C:$C,'Category Table'!AA$2,'Committments Dump'!$B:$B,'Category Table'!$A114) | AB114: =SUMIFS('Committments Dump'!$S:$S,'Committments Dump'!$C:$C,'Category Table'!AB$2,'Committments Dump'!$B:$B,'Category Table'!$A114) | AC114: =SUMIFS('Committments Dump'!$S:$S,'Committments Dump'!$C:$C,'Category Table'!AC$2,'Committments Dump'!$B:$B,'Category Table'!$A114) | AD114: =U114+X114+AA114 | AE114: =V114+Y114+AB114 | AF114: =W114+Z114+AC114 | AG114: =R114+AD114 | AH114: =S114+AE114 | AI114: =T114+AF114 | AM114: =(O114-AG114)+AJ114 | AN114: =(P114-AH114)+AK114 | AO114: =(Q114-AI114)+AL114 | AP114: =IF(AM114>0, "Under",IF(AM114<0,"Over","")) | AQ114: =IF(AN114>0, "Under",IF(AN114<0,"Over","")) | AR114: =IF(AO114>0, "Under",IF(AO114<0,"Over",""))
O115: =L115+I115+F115+C115 | P115: =M115+J115+G115+D115 | Q115: =N115+K115+H115+E115 | R115: =SUMIFS('PO Log'!$E:$E,'PO Log'!$D:$D,'Category Table'!R$2,'PO Log'!$C:$C,'Category Table'!$A115) | S115: =SUMIFS('PO Log'!$E:$E,'PO Log'!$D:$D,'Category Table'!S$2,'PO Log'!$C:$C,'Category Table'!$A115) | T115: =SUMIFS('PO Log'!$E:$E,'PO Log'!$D:$D,'Category Table'!T$2,'PO Log'!$C:$C,'Category Table'!$A115) | U115: =SUMIFS('Committments Dump'!$Q:$Q,'Committments Dump'!$C:$C,'Category Table'!U$2,'Committments Dump'!$B:$B,'Category Table'!$A115) | V115: =SUMIFS('Committments Dump'!$Q:$Q,'Committments Dump'!$C:$C,'Category Table'!V$2,'Committments Dump'!$B:$B,'Category Table'!$A115) | W115: =SUMIFS('Committments Dump'!$Q:$Q,'Committments Dump'!$C:$C,'Category Table'!W$2,'Committments Dump'!$B:$B,'Category Table'!$A115) | X115: =SUMIFS('Committments Dump'!$R:$R,'Committments Dump'!$C:$C,'Category Table'!X$2,'Committments Dump'!$B:$B,'Category Table'!$A115) | Y115: =SUMIFS('Committments Dump'!$R:$R,'Committments Dump'!$C:$C,'Category Table'!Y$2,'Committments Dump'!$B:$B,'Category Table'!$A115) | Z115: =SUMIFS('Committments Dump'!$R:$R,'Committments Dump'!$C:$C,'Category Table'!Z$2,'Committments Dump'!$B:$B,'Category Table'!$A115) | AA115: =SUMIFS('Committments Dump'!$S:$S,'Committments Dump'!$C:$C,'Category Table'!AA$2,'Committments Dump'!$B:$B,'Category Table'!$A115) | AB115: =SUMIFS('Committments Dump'!$S:$S,'Committments Dump'!$C:$C,'Category Table'!AB$2,'Committments Dump'!$B:$B,'Category Table'!$A115) | AC115: =SUMIFS('Committments Dump'!$S:$S,'Committments Dump'!$C:$C,'Category Table'!AC$2,'Committments Dump'!$B:$B,'Category Table'!$A115) | AD115: =U115+X115+AA115 | AE115: =V115+Y115+AB115 | AF115: =W115+Z115+AC115 | AG115: =R115+AD115 | AH115: =S115+AE115 | AI115: =T115+AF115 | AM115: =(O115-AG115)+AJ115 | AN115: =(P115-AH115)+AK115 | AO115: =(Q115-AI115)+AL115 | AP115: =IF(AM115>0, "Under",IF(AM115<0,"Over","")) | AQ115: =IF(AN115>0, "Under",IF(AN115<0,"Over","")) | AR115: =IF(AO115>0, "Under",IF(AO115<0,"Over",""))
